Workbook

Sheet Assumptions
A1: VetFinance | 5-Year Financial Forecast | Assumptions
A3: PRACTICE GROWTH
A4: Model start date | B4: 46569 | C4: First month of operations
A5: Practices active at launch (Month 1) | B5: 1 | C5: Founding / pilot clinics
A6: New practices signed per month — Year 1 | B6: 6 | C6: Early-adopter ramp
A7: New practices signed per month — Year 2 | B7: 18
A8: New practices signed per month — Year 3 | B8: 25
A9: New practices signed per month — Year 4 | B9: 20 | C9: Growth moderating
A10: New practices signed per month — Year 5 | B10: 12 | C10: Market maturing
A11: Monthly churn rate (% of active practices) | B11: 0.005 | C11: ~6% annually; practices leaving
A13: LOAN ECONOMICS
A14: Referrals per practice per week | B14: 2 | C14: Pet-owner referrals sent to financing
A15: Application approval rate | B15: 0.65 | C15: % of referrals approved & funded
A16: Average loan size ($) | B16: 1800 | C16: Avg financed amount per approved loan
A17: Average repayment period (months) | B17: 14 | C17: Avg expected loan duration
A18: Annual interest rate charged to borrower (APR) | B18: 0.19 | C18: CareCredit charges 26.99% standard
A19: Origination / processing fee (% of loan) | B19: 0.02 | C19: Collected upfront at funding
A20: Annual net loss rate (% of avg portfolio) | B20: 0.06 | C20: Charge-offs net of recoveries
A22: FUNDING & CAPITAL STRUCTURE
A23: Annual cost of debt (warehouse / credit facility) | B23: 0.09 | C23: Interest on borrowed capital
A24: Max leverage — debt ÷ equity on loan portfolio | B24: 7 | C24: 3x = 75% debt / 25% equity funded
A25: Minimum cash buffer (months of operating expenses) | B25: 6 | C25: Liquidity reserve on top of portfolio funding
A27: OPERATING EXPENSES (Year 1 Annualised)
A28: Salaries & Benefits (4 FTEs) | B28: =(75000+65000)*1.2 | C28: 2 founders @$60k, 1 underwriter @$75k, 1 ops @$65k (+20% taxes/benefits)
A29: Technology & Platform | B29: 63000 | C29: AWS $30k | Plaid $0.50/app ~$4k | Experian $1.50/app ~$12k | LOS/SaaS $12k | misc $5k
A30: Sales & Marketing | B30: 100000 | C30: Practice acquisition, collateral
A31: Compliance & Legal | B31: 150000 | C31: Licensing, counsel, audits
A32: G&A / Office | B32: 25000 | C32: Remote-first; virtual office, insurance, accounting — minimal footprint
A33: Total Year 1 Annual Opex | B33: =SUM(B28:B32)
A34: Annual opex growth rate (Year 2 onward) | B34: 0.5 | C34: Headcount & infrastructure scaling
A35: STARTING CAPITAL
A36: Initial equity raised before launch ($) | B36: 1000000
A38: COLOUR LEGEND
A39: ● Blue = Hardcoded input — change these to model scenarios
A40: ● Black = Formula — do not edit
A41: ● Green = Cross-sheet link — do not edit
A43: WAREHOUSE FACILITY & CASH MANAGEMENT
A44: Warehouse facility committed limit ($) | B44: 10000000 | C44: Committed size of the revolving warehouse credit line
A45: (Legacy — superseded by the loan-count facility gate below; not used in formulas) | B45: 1
A46: Yield earned on excess cash above buffer (annualized) | B46: 0.045 | C46: Idle cash above the minimum buffer is swept into short-term investments (T-bills / money market)
A48: HOW THIS DRIVES THE CASH MODEL
A49: • Each month the warehouse facility draws/repays to fund the advance-rate share of the portfolio, capped at the committed limit above.
A50: • If the advance-rate need exceeds the committed limit, the gap must be equity-funded — this is flagged as a 'facility increase' recommendation.
A51: • Cash above the minimum buffer earns the excess-cash yield above instead of sitting idle.
A52: • Any month where cash would dip below the minimum buffer triggers an automatic capital raise sized to the exact shortfall (see Monthly Model cols AC/AL, and the Capital Plan sheet).
A53: Facility utilization trigger for upsize (%) | B53: 0.85 | C53: When drawn balance hits this % of the committed limit, the model flags/sizes a facility increase
A54: Target utilization after a facility upsize (%) | B54: 0.65 | C54: New commitment is sized so utilization drops back to this level, leaving headroom for growth
A56: Equity raise frequency (months between raises) | B56: 12 | C56: Equity is only raised once per year, at the start of each fiscal year, sized to cover the full year ahead
A57: Loans funded from equity before warehouse facility is available | B57: 250 | C57: The lender wants a proven track record before extending the facility — book must originate this many loans on its own equity first
A60: BANK PARTNERSHIP (e.g., WebBank — required since you don't hold a lending license)
A61: Bank's retained interest in each loan's receivable (%) | B61: 0.05 | C61: Bank keeps this % of every loan on its own books indefinitely ('skin in the game' — 5% is the figure used in the FinWise Bank true-lender case). You fund/economically own the rest.
A62: Bank program fee (% of gross monthly originations) | B62: 0.01 | C62: Estimate — actual bank program fees are individually negotiated and confidential; adjust once you have a term sheet
A63: Minimum monthly bank program fee ($) | B63: 15000 | C63: Floor that protects the bank's revenue during low-volume months, common in early-stage programs
A64: Incremental bank-partner compliance / program mgmt cost ($/yr) | B64: 75000 | C64: Extra compliance headcount/tooling, licensing & registration upkeep, quarterly bank audits, marketing material review, complaint handling — on top of the Compliance & Legal opex line
A66: HOW THE BANK PARTNERSHIP WORKS
A67: • WebBank (a Utah-chartered industrial bank) is the actual lender of record for every loan — it underwrites and funds each loan with its own capital at origination, which is why you don't need a lending license in any state.
A68: • Within a few days, WebBank sells/assigns ~95% of each loan's receivable to you (or a trust you control); you fund that purchase from cash/equity/the warehouse facility — this is what 'Originations ($)' in the model represents.
A69: • WebBank keeps the other ~5% on its own books permanently — this is the 'true lender' skin-in-the-game that keeps the program defensible against rent-a-bank challenges.
A70: • You pay WebBank an ongoing program fee (modeled as % of gross originations, with a monthly floor) plus you bear the extra compliance/oversight cost of running a bank-partner program.
A71: • Being on a Utah bank's charter also lets you charge the model's 19% APR nationwide without hitting state-by-state usury caps — that's the other side of this trade-off.

Sheet Monthly Model
A1: PERIOD | D1: PRACTICE GROWTH | G1: LOAN VOLUME | J1: LOAN PORTFOLIO | O1: REVENUE | R1: COSTS & NET OP INCOME | U1: FUNDING | Y1: CAPITAL REQUIREMENTS | AE1: WAREHOUSE FACILITY, CASH SWEEP & RAISE TRIGGER | AO1: BANK PARTNERSHIP (WEBBANK)
A2: Mo# | B2: Date | C2: Yr | D2: New Practices | E2: Churned Practices | F2: Active Practices | G2: Monthly Referrals | H2: Approved Loans | I2: Originations — Your Share ($) | J2: Beg Portfolio ($) | K2: Repayments ($) | L2: Charge-offs ($) | M2: End Portfolio ($) | N2: Avg Portfolio ($) | O2: Interest Income ($) | P2: Orig Fees ($) | Q2: Total Revenue ($) | R2: Opex ($) | S2: Provision ($) | T2: Net Op Income ($) | U2: End Debt Balance ($) | V2: Interest Expense ($) | W2: Net Income ($) | X2: Cum Net Income ($) | Y2: Portfolio Equity ($) | Z2: Cash Buffer ($) | AA2: Total Equity Required ($) | AB2: Peak Equity Required ($) | AC2: Raise Triggered ($) | AD2: End Cash & Investments ($) | AE2: Facility Limit ($) | AF2: Debt Draw / (Repay) ($) | AG2: Facility Utilization (%) | AH2: Facility Increase This Month ($) | AI2: Investable Excess Cash ($) | AJ2: Investment Income ($) | AK2: Cash Before Raise ($) | AL2: Recommended Action | AM2: Net CF ex-Raise, ex-Invest Inc ($) | AN2: Cumulative Loans Funded | AO2: Gross Program Originations ($) | AP2: Bank Partnership Costs ($) | AQ2: Est. Bank's Retained Interest & Fees ($)
A3: 0 | C3: 0 | U3: 0 | AD3: =Assumptions!B36 | AE3: =Assumptions!$B$44
A4: 1 | B4: =EDATE(Assumptions!$B$4,0) | C4: =INT((A4-1)/12)+1 | D4: =IF(C4=1,Assumptions!$B$6,IF(C4=2,Assumptions!$B$7,IF(C4=3,Assumptions!$B$8,IF(C4=4,Assumptions!$B$9,Assumptions!$B$10)))) | E4: 0 | F4: =Assumptions!B5 | G4: =ROUND(F4*Assumptions!$B$14*(365/12/7),0) | H4: =ROUND(G4*Assumptions!$B$15,0) | I4: =AO4*(1-Assumptions!$B$61) | J4: 0 | K4: =IFERROR(J4/Assumptions!$B$17,0) | L4: =J4*Assumptions!$B$20/12 | M4: =MAX(J4+I4-K4-L4,0) | N4: =(J4+M4)/2 | O4: =N4*Assumptions!$B$18/12 | P4: =I4*Assumptions!$B$19 | Q4: =O4+P4 | R4: =Assumptions!$B$33*(1+Assumptions!$B$34)^(C4-1)/12 | S4: =L4 | T4: =Q4-R4-S4-AP4 | U4: =MIN(AE4,M4*Assumptions!$B$24/(1+Assumptions!$B$24)) | V4: =((U4+U3)/2)*Assumptions!$B$23/12 | W4: =T4-V4+AJ4 | X4: =W4 | Y4: =MAX(M4-U4,0) | Z4: =R4*Assumptions!$B$25 | AA4: =Y4+Z4 | AB4: =AA4 | AC4: =MAX(0,MAX(Z4-AD3-AM4,Z5-AD3-SUM(AM4:AM5),Z6-AD3-SUM(AM4:AM6),Z7-AD3-SUM(AM4:AM7),Z8-AD3-SUM(AM4:AM8),Z9-AD3-SUM(AM4:AM9),Z10-AD3-SUM(AM4:AM10),Z11-AD3-SUM(AM4:AM11),Z12-AD3-SUM(AM4:AM12),Z13-AD3-SUM(AM4:AM13),Z14-AD3-SUM(AM4:AM14),Z15-AD3-SUM(AM4:AM15))) | AD4: =AK4+AC4 | AE4: =IF(SUM($H$4:H4)<Assumptions!$B$57,0,MAX(MAX(Assumptions!$B$44,AE3),IF(M4*Assumptions!$B$24/(1+Assumptions!$B$24)>MAX(Assumptions!$B$44,AE3)*Assumptions!$B$53,M4*Assumptions!$B$24/(1+Assumptions!$B$24)/Assumptions!$B$54,MAX(Assumptions!$B$44,AE3)))) | AF4: =U4-U3 | AG4: =IFERROR(U4/AE4,0) | AH4: =MAX(0,AE4-AE3) | AI4: =MAX(AD3-Z4,0) | AJ4: =AI4*Assumptions!$B$46/12 | AK4: =AD3+Q4-R4-I4+K4+AF4-V4+AJ4-AP4 | AL4: =TRIM(IF(AH4>0,"Increase warehouse facility to $"&TEXT(AE4,"#,##0")&" (from $"&TEXT(AE3,"#,##0")&"). ","")&IF(AC4>0,"Raise ~$"&TEXT(AC4,"#,##0")&" of equity — annual raise, funds the next 12 months.","")) | AM4: =Q4-R4-I4+K4+AF4-V4-AP4 | AN4: =SUM($H$4:H4) | AO4: =H4*Assumptions!$B$16 | AP4: =MAX(AO4*Assumptions!$B$62,Assumptions!$B$63)+Assumptions!$B$64/12 | AQ4: =(O4+P4)*Assumptions!$B$61/(1-Assumptions!$B$61)
A5: 2 | B5: =EDATE(Assumptions!$B$4,1) | C5: =INT((A5-1)/12)+1 | D5: =IF(C5=1,Assumptions!$B$6,IF(C5=2,Assumptions!$B$7,IF(C5=3,Assumptions!$B$8,IF(C5=4,Assumptions!$B$9,Assumptions!$B$10)))) | E5: =ROUND(F4*Assumptions!$B$11,0) | F5: =F4+1 | G5: =ROUND(F5*Assumptions!$B$14*(365/12/7),0) | H5: =ROUND(G5*Assumptions!$B$15,0) | I5: =AO5*(1-Assumptions!$B$61) | J5: =M4 | K5: =IFERROR(J5/Assumptions!$B$17,0) | L5: =J5*Assumptions!$B$20/12 | M5: =MAX(J5+I5-K5-L5,0) | N5: =(J5+M5)/2 | O5: =N5*Assumptions!$B$18/12 | P5: =I5*Assumptions!$B$19 | Q5: =O5+P5 | R5: =Assumptions!$B$33*(1+Assumptions!$B$34)^(C5-1)/12 | S5: =L5 | T5: =Q5-R5-S5-AP5 | U5: =MIN(AE5,M5*Assumptions!$B$24/(1+Assumptions!$B$24)) | V5: =((U5+U4)/2)*Assumptions!$B$23/12 | W5: =T5-V5+AJ5 | X5: =X4+W5 | Y5: =MAX(M5-U5,0) | Z5: =R5*Assumptions!$B$25 | AA5: =Y5+Z5 | AB5: =MAX(AB4,AA5) | AC5: 0 | AD5: =AK5+AC5 | AE5: =IF(SUM($H$4:H5)<Assumptions!$B$57,0,MAX(MAX(Assumptions!$B$44,AE4),IF(M5*Assumptions!$B$24/(1+Assumptions!$B$24)>MAX(Assumptions!$B$44,AE4)*Assumptions!$B$53,M5*Assumptions!$B$24/(1+Assumptions!$B$24)/Assumptions!$B$54,MAX(Assumptions!$B$44,AE4)))) | AF5: =U5-U4 | AG5: =IFERROR(U5/AE5,0) | AH5: =MAX(0,AE5-AE4) | AI5: =MAX(AD4-Z5,0) | AJ5: =AI5*Assumptions!$B$46/12 | AK5: =AD4+Q5-R5-I5+K5+AF5-V5+AJ5-AP5 | AL5: =TRIM(IF(AH5>0,"Increase warehouse facility to $"&TEXT(AE5,"#,##0")&" (from $"&TEXT(AE4,"#,##0")&"). ","")&IF(AC5>0,"Raise ~$"&TEXT(AC5,"#,##0")&" of equity — annual raise, funds the next 12 months.","")) | AM5: =Q5-R5-I5+K5+AF5-V5-AP5 | AN5: =SUM($H$4:H5) | AO5: =H5*Assumptions!$B$16 | AP5: =MAX(AO5*Assumptions!$B$62,Assumptions!$B$63)+Assumptions!$B$64/12 | AQ5: =(O5+P5)*Assumptions!$B$61/(1-Assumptions!$B$61)
A6: 3 | B6: =EDATE(Assumptions!$B$4,2) | C6: =INT((A6-1)/12)+1 | D6: =IF(C6=1,Assumptions!$B$6,IF(C6=2,Assumptions!$B$7,IF(C6=3,Assumptions!$B$8,IF(C6=4,Assumptions!$B$9,Assumptions!$B$10)))) | E6: =ROUND(F5*Assumptions!$B$11,0) | F6: =F5+1 | G6: =ROUND(F6*Assumptions!$B$14*(365/12/7),0) | H6: =ROUND(G6*Assumptions!$B$15,0) | I6: =AO6*(1-Assumptions!$B$61) | J6: =M5 | K6: =IFERROR(J6/Assumptions!$B$17,0) | L6: =J6*Assumptions!$B$20/12 | M6: =MAX(J6+I6-K6-L6,0) | N6: =(J6+M6)/2 | O6: =N6*Assumptions!$B$18/12 | P6: =I6*Assumptions!$B$19 | Q6: =O6+P6 | R6: =Assumptions!$B$33*(1+Assumptions!$B$34)^(C6-1)/12 | S6: =L6 | T6: =Q6-R6-S6-AP6 | U6: =MIN(AE6,M6*Assumptions!$B$24/(1+Assumptions!$B$24)) | V6: =((U6+U5)/2)*Assumptions!$B$23/12 | W6: =T6-V6+AJ6 | X6: =X5+W6 | Y6: =MAX(M6-U6,0) | Z6: =R6*Assumptions!$B$25 | AA6: =Y6+Z6 | AB6: =MAX(AB5,AA6) | AC6: 0 | AD6: =AK6+AC6 | AE6: =IF(SUM($H$4:H6)<Assumptions!$B$57,0,MAX(MAX(Assumptions!$B$44,AE5),IF(M6*Assumptions!$B$24/(1+Assumptions!$B$24)>MAX(Assumptions!$B$44,AE5)*Assumptions!$B$53,M6*Assumptions!$B$24/(1+Assumptions!$B$24)/Assumptions!$B$54,MAX(Assumptions!$B$44,AE5)))) | AF6: =U6-U5 | AG6: =IFERROR(U6/AE6,0) | AH6: =MAX(0,AE6-AE5) | AI6: =MAX(AD5-Z6,0) | AJ6: =AI6*Assumptions!$B$46/12 | AK6: =AD5+Q6-R6-I6+K6+AF6-V6+AJ6-AP6 | AL6: =TRIM(IF(AH6>0,"Increase warehouse facility to $"&TEXT(AE6,"#,##0")&" (from $"&TEXT(AE5,"#,##0")&"). ","")&IF(AC6>0,"Raise ~$"&TEXT(AC6,"#,##0")&" of equity — annual raise, funds the next 12 months.","")) | AM6: =Q6-R6-I6+K6+AF6-V6-AP6 | AN6: =SUM($H$4:H6) | AO6: =H6*Assumptions!$B$16 | AP6: =MAX(AO6*Assumptions!$B$62,Assumptions!$B$63)+Assumptions!$B$64/12 | AQ6: =(O6+P6)*Assumptions!$B$61/(1-Assumptions!$B$61)
A7: 4 | B7: =EDATE(Assumptions!$B$4,3) | C7: =INT((A7-1)/12)+1 | D7: =IF(C7=1,Assumptions!$B$6,IF(C7=2,Assumptions!$B$7,IF(C7=3,Assumptions!$B$8,IF(C7=4,Assumptions!$B$9,Assumptions!$B$10)))) | E7: =ROUND(F6*Assumptions!$B$11,0) | F7: =F6+1 | G7: =ROUND(F7*Assumptions!$B$14*(365/12/7),0) | H7: =ROUND(G7*Assumptions!$B$15,0) | I7: =AO7*(1-Assumptions!$B$61) | J7: =M6 | K7: =IFERROR(J7/Assumptions!$B$17,0) | L7: =J7*Assumptions!$B$20/12 | M7: =MAX(J7+I7-K7-L7,0) | N7: =(J7+M7)/2 | O7: =N7*Assumptions!$B$18/12 | P7: =I7*Assumptions!$B$19 | Q7: =O7+P7 | R7: =Assumptions!$B$33*(1+Assumptions!$B$34)^(C7-1)/12 | S7: =L7 | T7: =Q7-R7-S7-AP7 | U7: =MIN(AE7,M7*Assumptions!$B$24/(1+Assumptions!$B$24)) | V7: =((U7+U6)/2)*Assumptions!$B$23/12 | W7: =T7-V7+AJ7 | X7: =X6+W7 | Y7: =MAX(M7-U7,0) | Z7: =R7*Assumptions!$B$25 | AA7: =Y7+Z7 | AB7: =MAX(AB6,AA7) | AC7: 0 | AD7: =AK7+AC7 | AE7: =IF(SUM($H$4:H7)<Assumptions!$B$57,0,MAX(MAX(Assumptions!$B$44,AE6),IF(M7*Assumptions!$B$24/(1+Assumptions!$B$24)>MAX(Assumptions!$B$44,AE6)*Assumptions!$B$53,M7*Assumptions!$B$24/(1+Assumptions!$B$24)/Assumptions!$B$54,MAX(Assumptions!$B$44,AE6)))) | AF7: =U7-U6 | AG7: =IFERROR(U7/AE7,0) | AH7: =MAX(0,AE7-AE6) | AI7: =MAX(AD6-Z7,0) | AJ7: =AI7*Assumptions!$B$46/12 | AK7: =AD6+Q7-R7-I7+K7+AF7-V7+AJ7-AP7 | AL7: =TRIM(IF(AH7>0,"Increase warehouse facility to $"&TEXT(AE7,"#,##0")&" (from $"&TEXT(AE6,"#,##0")&"). ","")&IF(AC7>0,"Raise ~$"&TEXT(AC7,"#,##0")&" of equity — annual raise, funds the next 12 months.","")) | AM7: =Q7-R7-I7+K7+AF7-V7-AP7 | AN7: =SUM($H$4:H7) | AO7: =H7*Assumptions!$B$16 | AP7: =MAX(AO7*Assumptions!$B$62,Assumptions!$B$63)+Assumptions!$B$64/12 | AQ7: =(O7+P7)*Assumptions!$B$61/(1-Assumptions!$B$61)
A8: 5 | B8: =EDATE(Assumptions!$B$4,4) | C8: =INT((A8-1)/12)+1 | D8: =IF(C8=1,Assumptions!$B$6,IF(C8=2,Assumptions!$B$7,IF(C8=3,Assumptions!$B$8,IF(C8=4,Assumptions!$B$9,Assumptions!$B$10)))) | E8: =ROUND(F7*Assumptions!$B$11,0) | F8: =F7+1 | G8: =ROUND(F8*Assumptions!$B$14*(365/12/7),0) | H8: =ROUND(G8*Assumptions!$B$15,0) | I8: =AO8*(1-Assumptions!$B$61) | J8: =M7 | K8: =IFERROR(J8/Assumptions!$B$17,0) | L8: =J8*Assumptions!$B$20/12 | M8: =MAX(J8+I8-K8-L8,0) | N8: =(J8+M8)/2 | O8: =N8*Assumptions!$B$18/12 | P8: =I8*Assumptions!$B$19 | Q8: =O8+P8 | R8: =Assumptions!$B$33*(1+Assumptions!$B$34)^(C8-1)/12 | S8: =L8 | T8: =Q8-R8-S8-AP8 | U8: =MIN(AE8,M8*Assumptions!$B$24/(1+Assumptions!$B$24)) | V8: =((U8+U7)/2)*Assumptions!$B$23/12 | W8: =T8-V8+AJ8 | X8: =X7+W8 | Y8: =MAX(M8-U8,0) | Z8: =R8*Assumptions!$B$25 | AA8: =Y8+Z8 | AB8: =MAX(AB7,AA8) | AC8: 0 | AD8: =AK8+AC8 | AE8: =IF(SUM($H$4:H8)<Assumptions!$B$57,0,MAX(MAX(Assumptions!$B$44,AE7),IF(M8*Assumptions!$B$24/(1+Assumptions!$B$24)>MAX(Assumptions!$B$44,AE7)*Assumptions!$B$53,M8*Assumptions!$B$24/(1+Assumptions!$B$24)/Assumptions!$B$54,MAX(Assumptions!$B$44,AE7)))) | AF8: =U8-U7 | AG8: =IFERROR(U8/AE8,0) | AH8: =MAX(0,AE8-AE7) | AI8: =MAX(AD7-Z8,0) | AJ8: =AI8*Assumptions!$B$46/12 | AK8: =AD7+Q8-R8-I8+K8+AF8-V8+AJ8-AP8 | AL8: =TRIM(IF(AH8>0,"Increase warehouse facility to $"&TEXT(AE8,"#,##0")&" (from $"&TEXT(AE7,"#,##0")&"). ","")&IF(AC8>0,"Raise ~$"&TEXT(AC8,"#,##0")&" of equity — annual raise, funds the next 12 months.","")) | AM8: =Q8-R8-I8+K8+AF8-V8-AP8 | AN8: =SUM($H$4:H8) | AO8: =H8*Assumptions!$B$16 | AP8: =MAX(AO8*Assumptions!$B$62,Assumptions!$B$63)+Assumptions!$B$64/12 | AQ8: =(O8+P8)*Assumptions!$B$61/(1-Assumptions!$B$61)
A9: 6 | B9: =EDATE(Assumptions!$B$4,5) | C9: =INT((A9-1)/12)+1 | D9: =IF(C9=1,Assumptions!$B$6,IF(C9=2,Assumptions!$B$7,IF(C9=3,Assumptions!$B$8,IF(C9=4,Assumptions!$B$9,Assumptions!$B$10)))) | E9: =ROUND(F8*Assumptions!$B$11,0) | F9: =F8+1 | G9: =ROUND(F9*Assumptions!$B$14*(365/12/7),0) | H9: =ROUND(G9*Assumptions!$B$15,0) | I9: =AO9*(1-Assumptions!$B$61) | J9: =M8 | K9: =IFERROR(J9/Assumptions!$B$17,0) | L9: =J9*Assumptions!$B$20/12 | M9: =MAX(J9+I9-K9-L9,0) | N9: =(J9+M9)/2 | O9: =N9*Assumptions!$B$18/12 | P9: =I9*Assumptions!$B$19 | Q9: =O9+P9 | R9: =Assumptions!$B$33*(1+Assumptions!$B$34)^(C9-1)/12 | S9: =L9 | T9: =Q9-R9-S9-AP9 | U9: =MIN(AE9,M9*Assumptions!$B$24/(1+Assumptions!$B$24)) | V9: =((U9+U8)/2)*Assumptions!$B$23/12 | W9: =T9-V9+AJ9 | X9: =X8+W9 | Y9: =MAX(M9-U9,0) | Z9: =R9*Assumptions!$B$25 | AA9: =Y9+Z9 | AB9: =MAX(AB8,AA9) | AC9: 0 | AD9: =AK9+AC9 | AE9: =IF(SUM($H$4:H9)<Assumptions!$B$57,0,MAX(MAX(Assumptions!$B$44,AE8),IF(M9*Assumptions!$B$24/(1+Assumptions!$B$24)>MAX(Assumptions!$B$44,AE8)*Assumptions!$B$53,M9*Assumptions!$B$24/(1+Assumptions!$B$24)/Assumptions!$B$54,MAX(Assumptions!$B$44,AE8)))) | AF9: =U9-U8 | AG9: =IFERROR(U9/AE9,0) | AH9: =MAX(0,AE9-AE8) | AI9: =MAX(AD8-Z9,0) | AJ9: =AI9*Assumptions!$B$46/12 | AK9: =AD8+Q9-R9-I9+K9+AF9-V9+AJ9-AP9 | AL9: =TRIM(IF(AH9>0,"Increase warehouse facility to $"&TEXT(AE9,"#,##0")&" (from $"&TEXT(AE8,"#,##0")&"). ","")&IF(AC9>0,"Raise ~$"&TEXT(AC9,"#,##0")&" of equity — annual raise, funds the next 12 months.","")) | AM9: =Q9-R9-I9+K9+AF9-V9-AP9 | AN9: =SUM($H$4:H9) | AO9: =H9*Assumptions!$B$16 | AP9: =MAX(AO9*Assumptions!$B$62,Assumptions!$B$63)+Assumptions!$B$64/12 | AQ9: =(O9+P9)*Assumptions!$B$61/(1-Assumptions!$B$61)
A10: 7 | B10: =EDATE(Assumptions!$B$4,6) | C10: =INT((A10-1)/12)+1 | D10: =IF(C10=1,Assumptions!$B$6,IF(C10=2,Assumptions!$B$7,IF(C10=3,Assumptions!$B$8,IF(C10=4,Assumptions!$B$9,Assumptions!$B$10)))) | E10: =ROUND(F9*Assumptions!$B$11,0) | F10: =F9+D10-E10 | G10: =ROUND(F10*Assumptions!$B$14*(365/12/7),0) | H10: =ROUND(G10*Assumptions!$B$15,0) | I10: =AO10*(1-Assumptions!$B$61) | J10: =M9 | K10: =IFERROR(J10/Assumptions!$B$17,0) | L10: =J10*Assumptions!$B$20/12 | M10: =MAX(J10+I10-K10-L10,0) | N10: =(J10+M10)/2 | O10: =N10*Assumptions!$B$18/12 | P10: =I10*Assumptions!$B$19 | Q10: =O10+P10 | R10: =Assumptions!$B$33*(1+Assumptions!$B$34)^(C10-1)/12 | S10: =L10 | T10: =Q10-R10-S10-AP10 | U10: =MIN(AE10,M10*Assumptions!$B$24/(1+Assumptions!$B$24)) | V10: =((U10+U9)/2)*Assumptions!$B$23/12 | W10: =T10-V10+AJ10 | X10: =X9+W10 | Y10: =MAX(M10-U10,0) | Z10: =R10*Assumptions!$B$25 | AA10: =Y10+Z10 | AB10: =MAX(AB9,AA10) | AC10: 0 | AD10: =AK10+AC10 | AE10: =IF(SUM($H$4:H10)<Assumptions!$B$57,0,MAX(MAX(Assumptions!$B$44,AE9),IF(M10*Assumptions!$B$24/(1+Assumptions!$B$24)>MAX(Assumptions!$B$44,AE9)*Assumptions!$B$53,M10*Assumptions!$B$24/(1+Assumptions!$B$24)/Assumptions!$B$54,MAX(Assumptions!$B$44,AE9)))) | AF10: =U10-U9 | AG10: =IFERROR(U10/AE10,0) | AH10: =MAX(0,AE10-AE9) | AI10: =MAX(AD9-Z10,0) | AJ10: =AI10*Assumptions!$B$46/12 | AK10: =AD9+Q10-R10-I10+K10+AF10-V10+AJ10-AP10 | AL10: =TRIM(IF(AH10>0,"Increase warehouse facility to $"&TEXT(AE10,"#,##0")&" (from $"&TEXT(AE9,"#,##0")&"). ","")&IF(AC10>0,"Raise ~$"&TEXT(AC10,"#,##0")&" of equity — annual raise, funds the next 12 months.","")) | AM10: =Q10-R10-I10+K10+AF10-V10-AP10 | AN10: =SUM($H$4:H10) | AO10: =H10*Assumptions!$B$16 | AP10: =MAX(AO10*Assumptions!$B$62,Assumptions!$B$63)+Assumptions!$B$64/12 | AQ10: =(O10+P10)*Assumptions!$B$61/(1-Assumptions!$B$61)
A11: 8 | B11: =EDATE(Assumptions!$B$4,7) | C11: =INT((A11-1)/12)+1 | D11: =IF(C11=1,Assumptions!$B$6,IF(C11=2,Assumptions!$B$7,IF(C11=3,Assumptions!$B$8,IF(C11=4,Assumptions!$B$9,Assumptions!$B$10)))) | E11: =ROUND(F10*Assumptions!$B$11,0) | F11: =F10+D11-E11 | G11: =ROUND(F11*Assumptions!$B$14*(365/12/7),0) | H11: =ROUND(G11*Assumptions!$B$15,0) | I11: =AO11*(1-Assumptions!$B$61) | J11: =M10 | K11: =IFERROR(J11/Assumptions!$B$17,0) | L11: =J11*Assumptions!$B$20/12 | M11: =MAX(J11+I11-K11-L11,0) | N11: =(J11+M11)/2 | O11: =N11*Assumptions!$B$18/12 | P11: =I11*Assumptions!$B$19 | Q11: =O11+P11 | R11: =Assumptions!$B$33*(1+Assumptions!$B$34)^(C11-1)/12 | S11: =L11 | T11: =Q11-R11-S11-AP11 | U11: =MIN(AE11,M11*Assumptions!$B$24/(1+Assumptions!$B$24)) | V11: =((U11+U10)/2)*Assumptions!$B$23/12 | W11: =T11-V11+AJ11 | X11: =X10+W11 | Y11: =MAX(M11-U11,0) | Z11: =R11*Assumptions!$B$25 | AA11: =Y11+Z11 | AB11: =MAX(AB10,AA11) | AC11: 0 | AD11: =AK11+AC11 | AE11: =IF(SUM($H$4:H11)<Assumptions!$B$57,0,MAX(MAX(Assumptions!$B$44,AE10),IF(M11*Assumptions!$B$24/(1+Assumptions!$B$24)>MAX(Assumptions!$B$44,AE10)*Assumptions!$B$53,M11*Assumptions!$B$24/(1+Assumptions!$B$24)/Assumptions!$B$54,MAX(Assumptions!$B$44,AE10)))) | AF11: =U11-U10 | AG11: =IFERROR(U11/AE11,0) | AH11: =MAX(0,AE11-AE10) | AI11: =MAX(AD10-Z11,0) | AJ11: =AI11*Assumptions!$B$46/12 | AK11: =AD10+Q11-R11-I11+K11+AF11-V11+AJ11-AP11 | AL11: =TRIM(IF(AH11>0,"Increase warehouse facility to $"&TEXT(AE11,"#,##0")&" (from $"&TEXT(AE10,"#,##0")&"). ","")&IF(AC11>0,"Raise ~$"&TEXT(AC11,"#,##0")&" of equity — annual raise, funds the next 12 months.","")) | AM11: =Q11-R11-I11+K11+AF11-V11-AP11 | AN11: =SUM($H$4:H11) | AO11: =H11*Assumptions!$B$16 | AP11: =MAX(AO11*Assumptions!$B$62,Assumptions!$B$63)+Assumptions!$B$64/12 | AQ11: =(O11+P11)*Assumptions!$B$61/(1-Assumptions!$B$61)
A12: 9 | B12: =EDATE(Assumptions!$B$4,8) | C12: =INT((A12-1)/12)+1 | D12: =IF(C12=1,Assumptions!$B$6,IF(C12=2,Assumptions!$B$7,IF(C12=3,Assumptions!$B$8,IF(C12=4,Assumptions!$B$9,Assumptions!$B$10)))) | E12: =ROUND(F11*Assumptions!$B$11,0) | F12: =F11+D12-E12 | G12: =ROUND(F12*Assumptions!$B$14*(365/12/7),0) | H12: =ROUND(G12*Assumptions!$B$15,0) | I12: =AO12*(1-Assumptions!$B$61) | J12: =M11 | K12: =IFERROR(J12/Assumptions!$B$17,0) | L12: =J12*Assumptions!$B$20/12 | M12: =MAX(J12+I12-K12-L12,0) | N12: =(J12+M12)/2 | O12: =N12*Assumptions!$B$18/12 | P12: =I12*Assumptions!$B$19 | Q12: =O12+P12 | R12: =Assumptions!$B$33*(1+Assumptions!$B$34)^(C12-1)/12 | S12: =L12 | T12: =Q12-R12-S12-AP12 | U12: =MIN(AE12,M12*Assumptions!$B$24/(1+Assumptions!$B$24)) | V12: =((U12+U11)/2)*Assumptions!$B$23/12 | W12: =T12-V12+AJ12 | X12: =X11+W12 | Y12: =MAX(M12-U12,0) | Z12: =R12*Assumptions!$B$25 | AA12: =Y12+Z12 | AB12: =MAX(AB11,AA12) | AC12: 0 | AD12: =AK12+AC12 | AE12: =IF(SUM($H$4:H12)<Assumptions!$B$57,0,MAX(MAX(Assumptions!$B$44,AE11),IF(M12*Assumptions!$B$24/(1+Assumptions!$B$24)>MAX(Assumptions!$B$44,AE11)*Assumptions!$B$53,M12*Assumptions!$B$24/(1+Assumptions!$B$24)/Assumptions!$B$54,MAX(Assumptions!$B$44,AE11)))) | AF12: =U12-U11 | AG12: =IFERROR(U12/AE12,0) | AH12: =MAX(0,AE12-AE11) | AI12: =MAX(AD11-Z12,0) | AJ12: =AI12*Assumptions!$B$46/12 | AK12: =AD11+Q12-R12-I12+K12+AF12-V12+AJ12-AP12 | AL12: =TRIM(IF(AH12>0,"Increase warehouse facility to $"&TEXT(AE12,"#,##0")&" (from $"&TEXT(AE11,"#,##0")&"). ","")&IF(AC12>0,"Raise ~$"&TEXT(AC12,"#,##0")&" of equity — annual raise, funds the next 12 months.","")) | AM12: =Q12-R12-I12+K12+AF12-V12-AP12 | AN12: =SUM($H$4:H12) | AO12: =H12*Assumptions!$B$16 | AP12: =MAX(AO12*Assumptions!$B$62,Assumptions!$B$63)+Assumptions!$B$64/12 | AQ12: =(O12+P12)*Assumptions!$B$61/(1-Assumptions!$B$61)
A13: 10 | B13: =EDATE(Assumptions!$B$4,9) | C13: =INT((A13-1)/12)+1 | D13: =IF(C13=1,Assumptions!$B$6,IF(C13=2,Assumptions!$B$7,IF(C13=3,Assumptions!$B$8,IF(C13=4,Assumptions!$B$9,Assumptions!$B$10)))) | E13: =ROUND(F12*Assumptions!$B$11,0) | F13: =F12+D13-E13 | G13: =ROUND(F13*Assumptions!$B$14*(365/12/7),0) | H13: =ROUND(G13*Assumptions!$B$15,0) | I13: =AO13*(1-Assumptions!$B$61) | J13: =M12 | K13: =IFERROR(J13/Assumptions!$B$17,0) | L13: =J13*Assumptions!$B$20/12 | M13: =MAX(J13+I13-K13-L13,0) | N13: =(J13+M13)/2 | O13: =N13*Assumptions!$B$18/12 | P13: =I13*Assumptions!$B$19 | Q13: =O13+P13 | R13: =Assumptions!$B$33*(1+Assumptions!$B$34)^(C13-1)/12 | S13: =L13 | T13: =Q13-R13-S13-AP13 | U13: =MIN(AE13,M13*Assumptions!$B$24/(1+Assumptions!$B$24)) | V13: =((U13+U12)/2)*Assumptions!$B$23/12 | W13: =T13-V13+AJ13 | X13: =X12+W13 | Y13: =MAX(M13-U13,0) | Z13: =R13*Assumptions!$B$25 | AA13: =Y13+Z13 | AB13: =MAX(AB12,AA13) | AC13: 0 | AD13: =AK13+AC13 | AE13: =IF(SUM($H$4:H13)<Assumptions!$B$57,0,MAX(MAX(Assumptions!$B$44,AE12),IF(M13*Assumptions!$B$24/(1+Assumptions!$B$24)>MAX(Assumptions!$B$44,AE12)*Assumptions!$B$53,M13*Assumptions!$B$24/(1+Assumptions!$B$24)/Assumptions!$B$54,MAX(Assumptions!$B$44,AE12)))) | AF13: =U13-U12 | AG13: =IFERROR(U13/AE13,0) | AH13: =MAX(0,AE13-AE12) | AI13: =MAX(AD12-Z13,0) | AJ13: =AI13*Assumptions!$B$46/12 | AK13: =AD12+Q13-R13-I13+K13+AF13-V13+AJ13-AP13 | AL13: =TRIM(IF(AH13>0,"Increase warehouse facility to $"&TEXT(AE13,"#,##0")&" (from $"&TEXT(AE12,"#,##0")&"). ","")&IF(AC13>0,"Raise ~$"&TEXT(AC13,"#,##0")&" of equity — annual raise, funds the next 12 months.","")) | AM13: =Q13-R13-I13+K13+AF13-V13-AP13 | AN13: =SUM($H$4:H13) | AO13: =H13*Assumptions!$B$16 | AP13: =MAX(AO13*Assumptions!$B$62,Assumptions!$B$63)+Assumptions!$B$64/12 | AQ13: =(O13+P13)*Assumptions!$B$61/(1-Assumptions!$B$61)
A14: 11 | B14: =EDATE(Assumptions!$B$4,10) | C14: =INT((A14-1)/12)+1 | D14: =IF(C14=1,Assumptions!$B$6,IF(C14=2,Assumptions!$B$7,IF(C14=3,Assumptions!$B$8,IF(C14=4,Assumptions!$B$9,Assumptions!$B$10)))) | E14: =ROUND(F13*Assumptions!$B$11,0) | F14: =F13+D14-E14 | G14: =ROUND(F14*Assumptions!$B$14*(365/12/7),0) | H14: =ROUND(G14*Assumptions!$B$15,0) | I14: =AO14*(1-Assumptions!$B$61) | J14: =M13 | K14: =IFERROR(J14/Assumptions!$B$17,0) | L14: =J14*Assumptions!$B$20/12 | M14: =MAX(J14+I14-K14-L14,0) | N14: =(J14+M14)/2 | O14: =N14*Assumptions!$B$18/12 | P14: =I14*Assumptions!$B$19 | Q14: =O14+P14 | R14: =Assumptions!$B$33*(1+Assumptions!$B$34)^(C14-1)/12 | S14: =L14 | T14: =Q14-R14-S14-AP14 | U14: =MIN(AE14,M14*Assumptions!$B$24/(1+Assumptions!$B$24)) | V14: =((U14+U13)/2)*Assumptions!$B$23/12 | W14: =T14-V14+AJ14 | X14: =X13+W14 | Y14: =MAX(M14-U14,0) | Z14: =R14*Assumptions!$B$25 | AA14: =Y14+Z14 | AB14: =MAX(AB13,AA14) | AC14: 0 | AD14: =AK14+AC14 | AE14: =IF(SUM($H$4:H14)<Assumptions!$B$57,0,MAX(MAX(Assumptions!$B$44,AE13),IF(M14*Assumptions!$B$24/(1+Assumptions!$B$24)>MAX(Assumptions!$B$44,AE13)*Assumptions!$B$53,M14*Assumptions!$B$24/(1+Assumptions!$B$24)/Assumptions!$B$54,MAX(Assumptions!$B$44,AE13)))) | AF14: =U14-U13 | AG14: =IFERROR(U14/AE14,0) | AH14: =MAX(0,AE14-AE13) | AI14: =MAX(AD13-Z14,0) | AJ14: =AI14*Assumptions!$B$46/12 | AK14: =AD13+Q14-R14-I14+K14+AF14-V14+AJ14-AP14 | AL14: =TRIM(IF(AH14>0,"Increase warehouse facility to $"&TEXT(AE14,"#,##0")&" (from $"&TEXT(AE13,"#,##0")&"). ","")&IF(AC14>0,"Raise ~$"&TEXT(AC14,"#,##0")&" of equity — annual raise, funds the next 12 months.","")) | AM14: =Q14-R14-I14+K14+AF14-V14-AP14 | AN14: =SUM($H$4:H14) | AO14: =H14*Assumptions!$B$16 | AP14: =MAX(AO14*Assumptions!$B$62,Assumptions!$B$63)+Assumptions!$B$64/12 | AQ14: =(O14+P14)*Assumptions!$B$61/(1-Assumptions!$B$61)
A15: 12 | B15: =EDATE(Assumptions!$B$4,11) | C15: =INT((A15-1)/12)+1 | D15: =IF(C15=1,Assumptions!$B$6,IF(C15=2,Assumptions!$B$7,IF(C15=3,Assumptions!$B$8,IF(C15=4,Assumptions!$B$9,Assumptions!$B$10)))) | E15: =ROUND(F14*Assumptions!$B$11,0) | F15: =F14+D15-E15 | G15: =ROUND(F15*Assumptions!$B$14*(365/12/7),0) | H15: =ROUND(G15*Assumptions!$B$15,0) | I15: =AO15*(1-Assumptions!$B$61) | J15: =M14 | K15: =IFERROR(J15/Assumptions!$B$17,0) | L15: =J15*Assumptions!$B$20/12 | M15: =MAX(J15+I15-K15-L15,0) | N15: =(J15+M15)/2 | O15: =N15*Assumptions!$B$18/12 | P15: =I15*Assumptions!$B$19 | Q15: =O15+P15 | R15: =Assumptions!$B$33*(1+Assumptions!$B$34)^(C15-1)/12 | S15: =L15 | T15: =Q15-R15-S15-AP15 | U15: =MIN(AE15,M15*Assumptions!$B$24/(1+Assumptions!$B$24)) | V15: =((U15+U14)/2)*Assumptions!$B$23/12 | W15: =T15-V15+AJ15 | X15: =X14+W15 | Y15: =MAX(M15-U15,0) | Z15: =R15*Assumptions!$B$25 | AA15: =Y15+Z15 | AB15: =MAX(AB14,AA15) | AC15: 0 | AD15: =AK15+AC15 | AE15: =IF(SUM($H$4:H15)<Assumptions!$B$57,0,MAX(MAX(Assumptions!$B$44,AE14),IF(M15*Assumptions!$B$24/(1+Assumptions!$B$24)>MAX(Assumptions!$B$44,AE14)*Assumptions!$B$53,M15*Assumptions!$B$24/(1+Assumptions!$B$24)/Assumptions!$B$54,MAX(Assumptions!$B$44,AE14)))) | AF15: =U15-U14 | AG15: =IFERROR(U15/AE15,0) | AH15: =MAX(0,AE15-AE14) | AI15: =MAX(AD14-Z15,0) | AJ15: =AI15*Assumptions!$B$46/12 | AK15: =AD14+Q15-R15-I15+K15+AF15-V15+AJ15-AP15 | AL15: =TRIM(IF(AH15>0,"Increase warehouse facility to $"&TEXT(AE15,"#,##0")&" (from $"&TEXT(AE14,"#,##0")&"). ","")&IF(AC15>0,"Raise ~$"&TEXT(AC15,"#,##0")&" of equity — annual raise, funds the next 12 months.","")) | AM15: =Q15-R15-I15+K15+AF15-V15-AP15 | AN15: =SUM($H$4:H15) | AO15: =H15*Assumptions!$B$16 | AP15: =MAX(AO15*Assumptions!$B$62,Assumptions!$B$63)+Assumptions!$B$64/12 | AQ15: =(O15+P15)*Assumptions!$B$61/(1-Assumptions!$B$61)
A16: 13 | B16: =EDATE(Assumptions!$B$4,12) | C16: =INT((A16-1)/12)+1 | D16: =IF(C16=1,Assumptions!$B$6,IF(C16=2,Assumptions!$B$7,IF(C16=3,Assumptions!$B$8,IF(C16=4,Assumptions!$B$9,Assumptions!$B$10)))) | E16: =ROUND(F15*Assumptions!$B$11,0) | F16: =F15+D16-E16 | G16: =ROUND(F16*Assumptions!$B$14*(365/12/7),0) | H16: =ROUND(G16*Assumptions!$B$15,0) | I16: =AO16*(1-Assumptions!$B$61) | J16: =M15 | K16: =IFERROR(J16/Assumptions!$B$17,0) | L16: =J16*Assumptions!$B$20/12 | M16: =MAX(J16+I16-K16-L16,0) | N16: =(J16+M16)/2 | O16: =N16*Assumptions!$B$18/12 | P16: =I16*Assumptions!$B$19 | Q16: =O16+P16 | R16: =Assumptions!$B$33*(1+Assumptions!$B$34)^(C16-1)/12 | S16: =L16 | T16: =Q16-R16-S16-AP16 | U16: =MIN(AE16,M16*Assumptions!$B$24/(1+Assumptions!$B$24)) | V16: =((U16+U15)/2)*Assumptions!$B$23/12 | W16: =T16-V16+AJ16 | X16: =X15+W16 | Y16: =MAX(M16-U16,0) | Z16: =R16*Assumptions!$B$25 | AA16: =Y16+Z16 | AB16: =MAX(AB15,AA16) | AC16: =MAX(0,MAX(Z16-AD15-AM16,Z17-AD15-SUM(AM16:AM17),Z18-AD15-SUM(AM16:AM18),Z19-AD15-SUM(AM16:AM19),Z20-AD15-SUM(AM16:AM20),Z21-AD15-SUM(AM16:AM21),Z22-AD15-SUM(AM16:AM22),Z23-AD15-SUM(AM16:AM23),Z24-AD15-SUM(AM16:AM24),Z25-AD15-SUM(AM16:AM25),Z26-AD15-SUM(AM16:AM26),Z27-AD15-SUM(AM16:AM27))) | AD16: =AK16+AC16 | AE16: =IF(SUM($H$4:H16)<Assumptions!$B$57,0,MAX(MAX(Assumptions!$B$44,AE15),IF(M16*Assumptions!$B$24/(1+Assumptions!$B$24)>MAX(Assumptions!$B$44,AE15)*Assumptions!$B$53,M16*Assumptions!$B$24/(1+Assumptions!$B$24)/Assumptions!$B$54,MAX(Assumptions!$B$44,AE15)))) | AF16: =U16-U15 | AG16: =IFERROR(U16/AE16,0) | AH16: =MAX(0,AE16-AE15) | AI16: =MAX(AD15-Z16,0) | AJ16: =AI16*Assumptions!$B$46/12 | AK16: =AD15+Q16-R16-I16+K16+AF16-V16+AJ16-AP16 | AL16: =TRIM(IF(AH16>0,"Increase warehouse facility to $"&TEXT(AE16,"#,##0")&" (from $"&TEXT(AE15,"#,##0")&"). ","")&IF(AC16>0,"Raise ~$"&TEXT(AC16,"#,##0")&" of equity — annual raise, funds the next 12 months.","")) | AM16: =Q16-R16-I16+K16+AF16-V16-AP16 | AN16: =SUM($H$4:H16) | AO16: =H16*Assumptions!$B$16 | AP16: =MAX(AO16*Assumptions!$B$62,Assumptions!$B$63)+Assumptions!$B$64/12 | AQ16: =(O16+P16)*Assumptions!$B$61/(1-Assumptions!$B$61)
A17: 14 | B17: =EDATE(Assumptions!$B$4,13) | C17: =INT((A17-1)/12)+1 | D17: =IF(C17=1,Assumptions!$B$6,IF(C17=2,Assumptions!$B$7,IF(C17=3,Assumptions!$B$8,IF(C17=4,Assumptions!$B$9,Assumptions!$B$10)))) | E17: =ROUND(F16*Assumptions!$B$11,0) | F17: =F16+D17-E17 | G17: =ROUND(F17*Assumptions!$B$14*(365/12/7),0) | H17: =ROUND(G17*Assumptions!$B$15,0) | I17: =AO17*(1-Assumptions!$B$61) | J17: =M16 | K17: =IFERROR(J17/Assumptions!$B$17,0) | L17: =J17*Assumptions!$B$20/12 | M17: =MAX(J17+I17-K17-L17,0) | N17: =(J17+M17)/2 | O17: =N17*Assumptions!$B$18/12 | P17: =I17*Assumptions!$B$19 | Q17: =O17+P17 | R17: =Assumptions!$B$33*(1+Assumptions!$B$34)^(C17-1)/12 | S17: =L17 | T17: =Q17-R17-S17-AP17 | U17: =MIN(AE17,M17*Assumptions!$B$24/(1+Assumptions!$B$24)) | V17: =((U17+U16)/2)*Assumptions!$B$23/12 | W17: =T17-V17+AJ17 | X17: =X16+W17 | Y17: =MAX(M17-U17,0) | Z17: =R17*Assumptions!$B$25 | AA17: =Y17+Z17 | AB17: =MAX(AB16,AA17) | AC17: 0 | AD17: =AK17+AC17 | AE17: =IF(SUM($H$4:H17)<Assumptions!$B$57,0,MAX(MAX(Assumptions!$B$44,AE16),IF(M17*Assumptions!$B$24/(1+Assumptions!$B$24)>MAX(Assumptions!$B$44,AE16)*Assumptions!$B$53,M17*Assumptions!$B$24/(1+Assumptions!$B$24)/Assumptions!$B$54,MAX(Assumptions!$B$44,AE16)))) | AF17: =U17-U16 | AG17: =IFERROR(U17/AE17,0) | AH17: =MAX(0,AE17-AE16) | AI17: =MAX(AD16-Z17,0) | AJ17: =AI17*Assumptions!$B$46/12 | AK17: =AD16+Q17-R17-I17+K17+AF17-V17+AJ17-AP17 | AL17: =TRIM(IF(AH17>0,"Increase warehouse facility to $"&TEXT(AE17,"#,##0")&" (from $"&TEXT(AE16,"#,##0")&"). ","")&IF(AC17>0,"Raise ~$"&TEXT(AC17,"#,##0")&" of equity — annual raise, funds the next 12 months.","")) | AM17: =Q17-R17-I17+K17+AF17-V17-AP17 | AN17: =SUM($H$4:H17) | AO17: =H17*Assumptions!$B$16 | AP17: =MAX(AO17*Assumptions!$B$62,Assumptions!$B$63)+Assumptions!$B$64/12 | AQ17: =(O17+P17)*Assumptions!$B$61/(1-Assumptions!$B$61)
A18: 15 | B18: =EDATE(Assumptions!$B$4,14) | C18: =INT((A18-1)/12)+1 | D18: =IF(C18=1,Assumptions!$B$6,IF(C18=2,Assumptions!$B$7,IF(C18=3,Assumptions!$B$8,IF(C18=4,Assumptions!$B$9,Assumptions!$B$10)))) | E18: =ROUND(F17*Assumptions!$B$11,0) | F18: =F17+D18-E18 | G18: =ROUND(F18*Assumptions!$B$14*(365/12/7),0) | H18: =ROUND(G18*Assumptions!$B$15,0) | I18: =AO18*(1-Assumptions!$B$61) | J18: =M17 | K18: =IFERROR(J18/Assumptions!$B$17,0) | L18: =J18*Assumptions!$B$20/12 | M18: =MAX(J18+I18-K18-L18,0) | N18: =(J18+M18)/2 | O18: =N18*Assumptions!$B$18/12 | P18: =I18*Assumptions!$B$19 | Q18: =O18+P18 | R18: =Assumptions!$B$33*(1+Assumptions!$B$34)^(C18-1)/12 | S18: =L18 | T18: =Q18-R18-S18-AP18 | U18: =MIN(AE18,M18*Assumptions!$B$24/(1+Assumptions!$B$24)) | V18: =((U18+U17)/2)*Assumptions!$B$23/12 | W18: =T18-V18+AJ18 | X18: =X17+W18 | Y18: =MAX(M18-U18,0) | Z18: =R18*Assumptions!$B$25 | AA18: =Y18+Z18 | AB18: =MAX(AB17,AA18) | AC18: 0 | AD18: =AK18+AC18 | AE18: =IF(SUM($H$4:H18)<Assumptions!$B$57,0,MAX(MAX(Assumptions!$B$44,AE17),IF(M18*Assumptions!$B$24/(1+Assumptions!$B$24)>MAX(Assumptions!$B$44,AE17)*Assumptions!$B$53,M18*Assumptions!$B$24/(1+Assumptions!$B$24)/Assumptions!$B$54,MAX(Assumptions!$B$44,AE17)))) | AF18: =U18-U17 | AG18: =IFERROR(U18/AE18,0) | AH18: =MAX(0,AE18-AE17) | AI18: =MAX(AD17-Z18,0) | AJ18: =AI18*Assumptions!$B$46/12 | AK18: =AD17+Q18-R18-I18+K18+AF18-V18+AJ18-AP18 | AL18: =TRIM(IF(AH18>0,"Increase warehouse facility to $"&TEXT(AE18,"#,##0")&" (from $"&TEXT(AE17,"#,##0")&"). ","")&IF(AC18>0,"Raise ~$"&TEXT(AC18,"#,##0")&" of equity — annual raise, funds the next 12 months.","")) | AM18: =Q18-R18-I18+K18+AF18-V18-AP18 | AN18: =SUM($H$4:H18) | AO18: =H18*Assumptions!$B$16 | AP18: =MAX(AO18*Assumptions!$B$62,Assumptions!$B$63)+Assumptions!$B$64/12 | AQ18: =(O18+P18)*Assumptions!$B$61/(1-Assumptions!$B$61)
A19: 16 | B19: =EDATE(Assumptions!$B$4,15) | C19: =INT((A19-1)/12)+1 | D19: =IF(C19=1,Assumptions!$B$6,IF(C19=2,Assumptions!$B$7,IF(C19=3,Assumptions!$B$8,IF(C19=4,Assumptions!$B$9,Assumptions!$B$10)))) | E19: =ROUND(F18*Assumptions!$B$11,0) | F19: =F18+D19-E19 | G19: =ROUND(F19*Assumptions!$B$14*(365/12/7),0) | H19: =ROUND(G19*Assumptions!$B$15,0) | I19: =AO19*(1-Assumptions!$B$61) | J19: =M18 | K19: =IFERROR(J19/Assumptions!$B$17,0) | L19: =J19*Assumptions!$B$20/12 | M19: =MAX(J19+I19-K19-L19,0) | N19: =(J19+M19)/2 | O19: =N19*Assumptions!$B$18/12 | P19: =I19*Assumptions!$B$19 | Q19: =O19+P19 | R19: =Assumptions!$B$33*(1+Assumptions!$B$34)^(C19-1)/12 | S19: =L19 | T19: =Q19-R19-S19-AP19 | U19: =MIN(AE19,M19*Assumptions!$B$24/(1+Assumptions!$B$24)) | V19: =((U19+U18)/2)*Assumptions!$B$23/12 | W19: =T19-V19+AJ19 | X19: =X18+W19 | Y19: =MAX(M19-U19,0) | Z19: =R19*Assumptions!$B$25 | AA19: =Y19+Z19 | AB19: =MAX(AB18,AA19) | AC19: 0 | AD19: =AK19+AC19 | AE19: =IF(SUM($H$4:H19)<Assumptions!$B$57,0,MAX(MAX(Assumptions!$B$44,AE18),IF(M19*Assumptions!$B$24/(1+Assumptions!$B$24)>MAX(Assumptions!$B$44,AE18)*Assumptions!$B$53,M19*Assumptions!$B$24/(1+Assumptions!$B$24)/Assumptions!$B$54,MAX(Assumptions!$B$44,AE18)))) | AF19: =U19-U18 | AG19: =IFERROR(U19/AE19,0) | AH19: =MAX(0,AE19-AE18) | AI19: =MAX(AD18-Z19,0) | AJ19: =AI19*Assumptions!$B$46/12 | AK19: =AD18+Q19-R19-I19+K19+AF19-V19+AJ19-AP19 | AL19: =TRIM(IF(AH19>0,"Increase warehouse facility to $"&TEXT(AE19,"#,##0")&" (from $"&TEXT(AE18,"#,##0")&"). ","")&IF(AC19>0,"Raise ~$"&TEXT(AC19,"#,##0")&" of equity — annual raise, funds the next 12 months.","")) | AM19: =Q19-R19-I19+K19+AF19-V19-AP19 | AN19: =SUM($H$4:H19) | AO19: =H19*Assumptions!$B$16 | AP19: =MAX(AO19*Assumptions!$B$62,Assumptions!$B$63)+Assumptions!$B$64/12 | AQ19: =(O19+P19)*Assumptions!$B$61/(1-Assumptions!$B$61)
A20: 17 | B20: =EDATE(Assumptions!$B$4,16) | C20: =INT((A20-1)/12)+1 | D20: =IF(C20=1,Assumptions!$B$6,IF(C20=2,Assumptions!$B$7,IF(C20=3,Assumptions!$B$8,IF(C20=4,Assumptions!$B$9,Assumptions!$B$10)))) | E20: =ROUND(F19*Assumptions!$B$11,0) | F20: =F19+D20-E20 | G20: =ROUND(F20*Assumptions!$B$14*(365/12/7),0) | H20: =ROUND(G20*Assumptions!$B$15,0) | I20: =AO20*(1-Assumptions!$B$61) | J20: =M19 | K20: =IFERROR(J20/Assumptions!$B$17,0) | L20: =J20*Assumptions!$B$20/12 | M20: =MAX(J20+I20-K20-L20,0) | N20: =(J20+M20)/2 | O20: =N20*Assumptions!$B$18/12 | P20: =I20*Assumptions!$B$19 | Q20: =O20+P20 | R20: =Assumptions!$B$33*(1+Assumptions!$B$34)^(C20-1)/12 | S20: =L20 | T20: =Q20-R20-S20-AP20 | U20: =MIN(AE20,M20*Assumptions!$B$24/(1+Assumptions!$B$24)) | V20: =((U20+U19)/2)*Assumptions!$B$23/12 | W20: =T20-V20+AJ20 | X20: =X19+W20 | Y20: =MAX(M20-U20,0) | Z20: =R20*Assumptions!$B$25 | AA20: =Y20+Z20 | AB20: =MAX(AB19,AA20) | AC20: 0 | AD20: =AK20+AC20 | AE20: =IF(SUM($H$4:H20)<Assumptions!$B$57,0,MAX(MAX(Assumptions!$B$44,AE19),IF(M20*Assumptions!$B$24/(1+Assumptions!$B$24)>MAX(Assumptions!$B$44,AE19)*Assumptions!$B$53,M20*Assumptions!$B$24/(1+Assumptions!$B$24)/Assumptions!$B$54,MAX(Assumptions!$B$44,AE19)))) | AF20: =U20-U19 | AG20: =IFERROR(U20/AE20,0) | AH20: =MAX(0,AE20-AE19) | AI20: =MAX(AD19-Z20,0) | AJ20: =AI20*Assumptions!$B$46/12 | AK20: =AD19+Q20-R20-I20+K20+AF20-V20+AJ20-AP20 | AL20: =TRIM(IF(AH20>0,"Increase warehouse facility to $"&TEXT(AE20,"#,##0")&" (from $"&TEXT(AE19,"#,##0")&"). ","")&IF(AC20>0,"Raise ~$"&TEXT(AC20,"#,##0")&" of equity — annual raise, funds the next 12 months.","")) | AM20: =Q20-R20-I20+K20+AF20-V20-AP20 | AN20: =SUM($H$4:H20) | AO20: =H20*Assumptions!$B$16 | AP20: =MAX(AO20*Assumptions!$B$62,Assumptions!$B$63)+Assumptions!$B$64/12 | AQ20: =(O20+P20)*Assumptions!$B$61/(1-Assumptions!$B$61)
A21: 18 | B21: =EDATE(Assumptions!$B$4,17) | C21: =INT((A21-1)/12)+1 | D21: =IF(C21=1,Assumptions!$B$6,IF(C21=2,Assumptions!$B$7,IF(C21=3,Assumptions!$B$8,IF(C21=4,Assumptions!$B$9,Assumptions!$B$10)))) | E21: =ROUND(F20*Assumptions!$B$11,0) | F21: =F20+D21-E21 | G21: =ROUND(F21*Assumptions!$B$14*(365/12/7),0) | H21: =ROUND(G21*Assumptions!$B$15,0) | I21: =AO21*(1-Assumptions!$B$61) | J21: =M20 | K21: =IFERROR(J21/Assumptions!$B$17,0) | L21: =J21*Assumptions!$B$20/12 | M21: =MAX(J21+I21-K21-L21,0) | N21: =(J21+M21)/2 | O21: =N21*Assumptions!$B$18/12 | P21: =I21*Assumptions!$B$19 | Q21: =O21+P21 | R21: =Assumptions!$B$33*(1+Assumptions!$B$34)^(C21-1)/12 | S21: =L21 | T21: =Q21-R21-S21-AP21 | U21: =MIN(AE21,M21*Assumptions!$B$24/(1+Assumptions!$B$24)) | V21: =((U21+U20)/2)*Assumptions!$B$23/12 | W21: =T21-V21+AJ21 | X21: =X20+W21 | Y21: =MAX(M21-U21,0) | Z21: =R21*Assumptions!$B$25 | AA21: =Y21+Z21 | AB21: =MAX(AB20,AA21) | AC21: 0 | AD21: =AK21+AC21 | AE21: =IF(SUM($H$4:H21)<Assumptions!$B$57,0,MAX(MAX(Assumptions!$B$44,AE20),IF(M21*Assumptions!$B$24/(1+Assumptions!$B$24)>MAX(Assumptions!$B$44,AE20)*Assumptions!$B$53,M21*Assumptions!$B$24/(1+Assumptions!$B$24)/Assumptions!$B$54,MAX(Assumptions!$B$44,AE20)))) | AF21: =U21-U20 | AG21: =IFERROR(U21/AE21,0) | AH21: =MAX(0,AE21-AE20) | AI21: =MAX(AD20-Z21,0) | AJ21: =AI21*Assumptions!$B$46/12 | AK21: =AD20+Q21-R21-I21+K21+AF21-V21+AJ21-AP21 | AL21: =TRIM(IF(AH21>0,"Increase warehouse facility to $"&TEXT(AE21,"#,##0")&" (from $"&TEXT(AE20,"#,##0")&"). ","")&IF(AC21>0,"Raise ~$"&TEXT(AC21,"#,##0")&" of equity — annual raise, funds the next 12 months.","")) | AM21: =Q21-R21-I21+K21+AF21-V21-AP21 | AN21: =SUM($H$4:H21) | AO21: =H21*Assumptions!$B$16 | AP21: =MAX(AO21*Assumptions!$B$62,Assumptions!$B$63)+Assumptions!$B$64/12 | AQ21: =(O21+P21)*Assumptions!$B$61/(1-Assumptions!$B$61)
A22: 19 | B22: =EDATE(Assumptions!$B$4,18) | C22: =INT((A22-1)/12)+1 | D22: =IF(C22=1,Assumptions!$B$6,IF(C22=2,Assumptions!$B$7,IF(C22=3,Assumptions!$B$8,IF(C22=4,Assumptions!$B$9,Assumptions!$B$10)))) | E22: =ROUND(F21*Assumptions!$B$11,0) | F22: =F21+D22-E22 | G22: =ROUND(F22*Assumptions!$B$14*(365/12/7),0) | H22: =ROUND(G22*Assumptions!$B$15,0) | I22: =AO22*(1-Assumptions!$B$61) | J22: =M21 | K22: =IFERROR(J22/Assumptions!$B$17,0) | L22: =J22*Assumptions!$B$20/12 | M22: =MAX(J22+I22-K22-L22,0) | N22: =(J22+M22)/2 | O22: =N22*Assumptions!$B$18/12 | P22: =I22*Assumptions!$B$19 | Q22: =O22+P22 | R22: =Assumptions!$B$33*(1+Assumptions!$B$34)^(C22-1)/12 | S22: =L22 | T22: =Q22-R22-S22-AP22 | U22: =MIN(AE22,M22*Assumptions!$B$24/(1+Assumptions!$B$24)) | V22: =((U22+U21)/2)*Assumptions!$B$23/12 | W22: =T22-V22+AJ22 | X22: =X21+W22 | Y22: =MAX(M22-U22,0) | Z22: =R22*Assumptions!$B$25 | AA22: =Y22+Z22 | AB22: =MAX(AB21,AA22) | AC22: 0 | AD22: =AK22+AC22 | AE22: =IF(SUM($H$4:H22)<Assumptions!$B$57,0,MAX(MAX(Assumptions!$B$44,AE21),IF(M22*Assumptions!$B$24/(1+Assumptions!$B$24)>MAX(Assumptions!$B$44,AE21)*Assumptions!$B$53,M22*Assumptions!$B$24/(1+Assumptions!$B$24)/Assumptions!$B$54,MAX(Assumptions!$B$44,AE21)))) | AF22: =U22-U21 | AG22: =IFERROR(U22/AE22,0) | AH22: =MAX(0,AE22-AE21) | AI22: =MAX(AD21-Z22,0) | AJ22: =AI22*Assumptions!$B$46/12 | AK22: =AD21+Q22-R22-I22+K22+AF22-V22+AJ22-AP22 | AL22: =TRIM(IF(AH22>0,"Increase warehouse facility to $"&TEXT(AE22,"#,##0")&" (from $"&TEXT(AE21,"#,##0")&"). ","")&IF(AC22>0,"Raise ~$"&TEXT(AC22,"#,##0")&" of equity — annual raise, funds the next 12 months.","")) | AM22: =Q22-R22-I22+K22+AF22-V22-AP22 | AN22: =SUM($H$4:H22) | AO22: =H22*Assumptions!$B$16 | AP22: =MAX(AO22*Assumptions!$B$62,Assumptions!$B$63)+Assumptions!$B$64/12 | AQ22: =(O22+P22)*Assumptions!$B$61/(1-Assumptions!$B$61)
A23: 20 | B23: =EDATE(Assumptions!$B$4,19) | C23: =INT((A23-1)/12)+1 | D23: =IF(C23=1,Assumptions!$B$6,IF(C23=2,Assumptions!$B$7,IF(C23=3,Assumptions!$B$8,IF(C23=4,Assumptions!$B$9,Assumptions!$B$10)))) | E23: =ROUND(F22*Assumptions!$B$11,0) | F23: =F22+D23-E23 | G23: =ROUND(F23*Assumptions!$B$14*(365/12/7),0) | H23: =ROUND(G23*Assumptions!$B$15,0) | I23: =AO23*(1-Assumptions!$B$61) | J23: =M22 | K23: =IFERROR(J23/Assumptions!$B$17,0) | L23: =J23*Assumptions!$B$20/12 | M23: =MAX(J23+I23-K23-L23,0) | N23: =(J23+M23)/2 | O23: =N23*Assumptions!$B$18/12 | P23: =I23*Assumptions!$B$19 | Q23: =O23+P23 | R23: =Assumptions!$B$33*(1+Assumptions!$B$34)^(C23-1)/12 | S23: =L23 | T23: =Q23-R23-S23-AP23 | U23: =MIN(AE23,M23*Assumptions!$B$24/(1+Assumptions!$B$24)) | V23: =((U23+U22)/2)*Assumptions!$B$23/12 | W23: =T23-V23+AJ23 | X23: =X22+W23 | Y23: =MAX(M23-U23,0) | Z23: =R23*Assumptions!$B$25 | AA23: =Y23+Z23 | AB23: =MAX(AB22,AA23) | AC23: 0 | AD23: =AK23+AC23 | AE23: =IF(SUM($H$4:H23)<Assumptions!$B$57,0,MAX(MAX(Assumptions!$B$44,AE22),IF(M23*Assumptions!$B$24/(1+Assumptions!$B$24)>MAX(Assumptions!$B$44,AE22)*Assumptions!$B$53,M23*Assumptions!$B$24/(1+Assumptions!$B$24)/Assumptions!$B$54,MAX(Assumptions!$B$44,AE22)))) | AF23: =U23-U22 | AG23: =IFERROR(U23/AE23,0) | AH23: =MAX(0,AE23-AE22) | AI23: =MAX(AD22-Z23,0) | AJ23: =AI23*Assumptions!$B$46/12 | AK23: =AD22+Q23-R23-I23+K23+AF23-V23+AJ23-AP23 | AL23: =TRIM(IF(AH23>0,"Increase warehouse facility to $"&TEXT(AE23,"#,##0")&" (from $"&TEXT(AE22,"#,##0")&"). ","")&IF(AC23>0,"Raise ~$"&TEXT(AC23,"#,##0")&" of equity — annual raise, funds the next 12 months.","")) | AM23: =Q23-R23-I23+K23+AF23-V23-AP23 | AN23: =SUM($H$4:H23) | AO23: =H23*Assumptions!$B$16 | AP23: =MAX(AO23*Assumptions!$B$62,Assumptions!$B$63)+Assumptions!$B$64/12 | AQ23: =(O23+P23)*Assumptions!$B$61/(1-Assumptions!$B$61)
A24: 21 | B24: =EDATE(Assumptions!$B$4,20) | C24: =INT((A24-1)/12)+1 | D24: =IF(C24=1,Assumptions!$B$6,IF(C24=2,Assumptions!$B$7,IF(C24=3,Assumptions!$B$8,IF(C24=4,Assumptions!$B$9,Assumptions!$B$10)))) | E24: =ROUND(F23*Assumptions!$B$11,0) | F24: =F23+D24-E24 | G24: =ROUND(F24*Assumptions!$B$14*(365/12/7),0) | H24: =ROUND(G24*Assumptions!$B$15,0) | I24: =AO24*(1-Assumptions!$B$61) | J24: =M23 | K24: =IFERROR(J24/Assumptions!$B$17,0) | L24: =J24*Assumptions!$B$20/12 | M24: =MAX(J24+I24-K24-L24,0) | N24: =(J24+M24)/2 | O24: =N24*Assumptions!$B$18/12 | P24: =I24*Assumptions!$B$19 | Q24: =O24+P24 | R24: =Assumptions!$B$33*(1+Assumptions!$B$34)^(C24-1)/12 | S24: =L24 | T24: =Q24-R24-S24-AP24 | U24: =MIN(AE24,M24*Assumptions!$B$24/(1+Assumptions!$B$24)) | V24: =((U24+U23)/2)*Assumptions!$B$23/12 | W24: =T24-V24+AJ24 | X24: =X23+W24 | Y24: =MAX(M24-U24,0) | Z24: =R24*Assumptions!$B$25 | AA24: =Y24+Z24 | AB24: =MAX(AB23,AA24) | AC24: 0 | AD24: =AK24+AC24 | AE24: =IF(SUM($H$4:H24)<Assumptions!$B$57,0,MAX(MAX(Assumptions!$B$44,AE23),IF(M24*Assumptions!$B$24/(1+Assumptions!$B$24)>MAX(Assumptions!$B$44,AE23)*Assumptions!$B$53,M24*Assumptions!$B$24/(1+Assumptions!$B$24)/Assumptions!$B$54,MAX(Assumptions!$B$44,AE23)))) | AF24: =U24-U23 | AG24: =IFERROR(U24/AE24,0) | AH24: =MAX(0,AE24-AE23) | AI24: =MAX(AD23-Z24,0) | AJ24: =AI24*Assumptions!$B$46/12 | AK24: =AD23+Q24-R24-I24+K24+AF24-V24+AJ24-AP24 | AL24: =TRIM(IF(AH24>0,"Increase warehouse facility to $"&TEXT(AE24,"#,##0")&" (from $"&TEXT(AE23,"#,##0")&"). ","")&IF(AC24>0,"Raise ~$"&TEXT(AC24,"#,##0")&" of equity — annual raise, funds the next 12 months.","")) | AM24: =Q24-R24-I24+K24+AF24-V24-AP24 | AN24: =SUM($H$4:H24) | AO24: =H24*Assumptions!$B$16 | AP24: =MAX(AO24*Assumptions!$B$62,Assumptions!$B$63)+Assumptions!$B$64/12 | AQ24: =(O24+P24)*Assumptions!$B$61/(1-Assumptions!$B$61)
A25: 22 | B25: =EDATE(Assumptions!$B$4,21) | C25: =INT((A25-1)/12)+1 | D25: =IF(C25=1,Assumptions!$B$6,IF(C25=2,Assumptions!$B$7,IF(C25=3,Assumptions!$B$8,IF(C25=4,Assumptions!$B$9,Assumptions!$B$10)))) | E25: =ROUND(F24*Assumptions!$B$11,0) | F25: =F24+D25-E25 | G25: =ROUND(F25*Assumptions!$B$14*(365/12/7),0) | H25: =ROUND(G25*Assumptions!$B$15,0) | I25: =AO25*(1-Assumptions!$B$61) | J25: =M24 | K25: =IFERROR(J25/Assumptions!$B$17,0) | L25: =J25*Assumptions!$B$20/12 | M25: =MAX(J25+I25-K25-L25,0) | N25: =(J25+M25)/2 | O25: =N25*Assumptions!$B$18/12 | P25: =I25*Assumptions!$B$19 | Q25: =O25+P25 | R25: =Assumptions!$B$33*(1+Assumptions!$B$34)^(C25-1)/12 | S25: =L25 | T25: =Q25-R25-S25-AP25 | U25: =MIN(AE25,M25*Assumptions!$B$24/(1+Assumptions!$B$24)) | V25: =((U25+U24)/2)*Assumptions!$B$23/12 | W25: =T25-V25+AJ25 | X25: =X24+W25 | Y25: =MAX(M25-U25,0) | Z25: =R25*Assumptions!$B$25 | AA25: =Y25+Z25 | AB25: =MAX(AB24,AA25) | AC25: 0 | AD25: =AK25+AC25 | AE25: =IF(SUM($H$4:H25)<Assumptions!$B$57,0,MAX(MAX(Assumptions!$B$44,AE24),IF(M25*Assumptions!$B$24/(1+Assumptions!$B$24)>MAX(Assumptions!$B$44,AE24)*Assumptions!$B$53,M25*Assumptions!$B$24/(1+Assumptions!$B$24)/Assumptions!$B$54,MAX(Assumptions!$B$44,AE24)))) | AF25: =U25-U24 | AG25: =IFERROR(U25/AE25,0) | AH25: =MAX(0,AE25-AE24) | AI25: =MAX(AD24-Z25,0) | AJ25: =AI25*Assumptions!$B$46/12 | AK25: =AD24+Q25-R25-I25+K25+AF25-V25+AJ25-AP25 | AL25: =TRIM(IF(AH25>0,"Increase warehouse facility to $"&TEXT(AE25,"#,##0")&" (from $"&TEXT(AE24,"#,##0")&"). ","")&IF(AC25>0,"Raise ~$"&TEXT(AC25,"#,##0")&" of equity — annual raise, funds the next 12 months.","")) | AM25: =Q25-R25-I25+K25+AF25-V25-AP25 | AN25: =SUM($H$4:H25) | AO25: =H25*Assumptions!$B$16 | AP25: =MAX(AO25*Assumptions!$B$62,Assumptions!$B$63)+Assumptions!$B$64/12 | AQ25: =(O25+P25)*Assumptions!$B$61/(1-Assumptions!$B$61)
A26: 23 | B26: =EDATE(Assumptions!$B$4,22) | C26: =INT((A26-1)/12)+1 | D26: =IF(C26=1,Assumptions!$B$6,IF(C26=2,Assumptions!$B$7,IF(C26=3,Assumptions!$B$8,IF(C26=4,Assumptions!$B$9,Assumptions!$B$10)))) | E26: =ROUND(F25*Assumptions!$B$11,0) | F26: =F25+D26-E26 | G26: =ROUND(F26*Assumptions!$B$14*(365/12/7),0) | H26: =ROUND(G26*Assumptions!$B$15,0) | I26: =AO26*(1-Assumptions!$B$61) | J26: =M25 | K26: =IFERROR(J26/Assumptions!$B$17,0) | L26: =J26*Assumptions!$B$20/12 | M26: =MAX(J26+I26-K26-L26,0) | N26: =(J26+M26)/2 | O26: =N26*Assumptions!$B$18/12 | P26: =I26*Assumptions!$B$19 | Q26: =O26+P26 | R26: =Assumptions!$B$33*(1+Assumptions!$B$34)^(C26-1)/12 | S26: =L26 | T26: =Q26-R26-S26-AP26 | U26: =MIN(AE26,M26*Assumptions!$B$24/(1+Assumptions!$B$24)) | V26: =((U26+U25)/2)*Assumptions!$B$23/12 | W26: =T26-V26+AJ26 | X26: =X25+W26 | Y26: =MAX(M26-U26,0) | Z26: =R26*Assumptions!$B$25 | AA26: =Y26+Z26 | AB26: =MAX(AB25,AA26) | AC26: 0 | AD26: =AK26+AC26 | AE26: =IF(SUM($H$4:H26)<Assumptions!$B$57,0,MAX(MAX(Assumptions!$B$44,AE25),IF(M26*Assumptions!$B$24/(1+Assumptions!$B$24)>MAX(Assumptions!$B$44,AE25)*Assumptions!$B$53,M26*Assumptions!$B$24/(1+Assumptions!$B$24)/Assumptions!$B$54,MAX(Assumptions!$B$44,AE25)))) | AF26: =U26-U25 | AG26: =IFERROR(U26/AE26,0) | AH26: =MAX(0,AE26-AE25) | AI26: =MAX(AD25-Z26,0) | AJ26: =AI26*Assumptions!$B$46/12 | AK26: =AD25+Q26-R26-I26+K26+AF26-V26+AJ26-AP26 | AL26: =TRIM(IF(AH26>0,"Increase warehouse facility to $"&TEXT(AE26,"#,##0")&" (from $"&TEXT(AE25,"#,##0")&"). ","")&IF(AC26>0,"Raise ~$"&TEXT(AC26,"#,##0")&" of equity — annual raise, funds the next 12 months.","")) | AM26: =Q26-R26-I26+K26+AF26-V26-AP26 | AN26: =SUM($H$4:H26) | AO26: =H26*Assumptions!$B$16 | AP26: =MAX(AO26*Assumptions!$B$62,Assumptions!$B$63)+Assumptions!$B$64/12 | AQ26: =(O26+P26)*Assumptions!$B$61/(1-Assumptions!$B$61)
A27: 24 | B27: =EDATE(Assumptions!$B$4,23) | C27: =INT((A27-1)/12)+1 | D27: =IF(C27=1,Assumptions!$B$6,IF(C27=2,Assumptions!$B$7,IF(C27=3,Assumptions!$B$8,IF(C27=4,Assumptions!$B$9,Assumptions!$B$10)))) | E27: =ROUND(F26*Assumptions!$B$11,0) | F27: =F26+D27-E27 | G27: =ROUND(F27*Assumptions!$B$14*(365/12/7),0) | H27: =ROUND(G27*Assumptions!$B$15,0) | I27: =AO27*(1-Assumptions!$B$61) | J27: =M26 | K27: =IFERROR(J27/Assumptions!$B$17,0) | L27: =J27*Assumptions!$B$20/12 | M27: =MAX(J27+I27-K27-L27,0) | N27: =(J27+M27)/2 | O27: =N27*Assumptions!$B$18/12 | P27: =I27*Assumptions!$B$19 | Q27: =O27+P27 | R27: =Assumptions!$B$33*(1+Assumptions!$B$34)^(C27-1)/12 | S27: =L27 | T27: =Q27-R27-S27-AP27 | U27: =MIN(AE27,M27*Assumptions!$B$24/(1+Assumptions!$B$24)) | V27: =((U27+U26)/2)*Assumptions!$B$23/12 | W27: =T27-V27+AJ27 | X27: =X26+W27 | Y27: =MAX(M27-U27,0) | Z27: =R27*Assumptions!$B$25 | AA27: =Y27+Z27 | AB27: =MAX(AB26,AA27) | AC27: 0 | AD27: =AK27+AC27 | AE27: =IF(SUM($H$4:H27)<Assumptions!$B$57,0,MAX(MAX(Assumptions!$B$44,AE26),IF(M27*Assumptions!$B$24/(1+Assumptions!$B$24)>MAX(Assumptions!$B$44,AE26)*Assumptions!$B$53,M27*Assumptions!$B$24/(1+Assumptions!$B$24)/Assumptions!$B$54,MAX(Assumptions!$B$44,AE26)))) | AF27: =U27-U26 | AG27: =IFERROR(U27/AE27,0) | AH27: =MAX(0,AE27-AE26) | AI27: =MAX(AD26-Z27,0) | AJ27: =AI27*Assumptions!$B$46/12 | AK27: =AD26+Q27-R27-I27+K27+AF27-V27+AJ27-AP27 | AL27: =TRIM(IF(AH27>0,"Increase warehouse facility to $"&TEXT(AE27,"#,##0")&" (from $"&TEXT(AE26,"#,##0")&"). ","")&IF(AC27>0,"Raise ~$"&TEXT(AC27,"#,##0")&" of equity — annual raise, funds the next 12 months.","")) | AM27: =Q27-R27-I27+K27+AF27-V27-AP27 | AN27: =SUM($H$4:H27) | AO27: =H27*Assumptions!$B$16 | AP27: =MAX(AO27*Assumptions!$B$62,Assumptions!$B$63)+Assumptions!$B$64/12 | AQ27: =(O27+P27)*Assumptions!$B$61/(1-Assumptions!$B$61)
A28: 25 | B28: =EDATE(Assumptions!$B$4,24) | C28: =INT((A28-1)/12)+1 | D28: =IF(C28=1,Assumptions!$B$6,IF(C28=2,Assumptions!$B$7,IF(C28=3,Assumptions!$B$8,IF(C28=4,Assumptions!$B$9,Assumptions!$B$10)))) | E28: =ROUND(F27*Assumptions!$B$11,0) | F28: =F27+D28-E28 | G28: =ROUND(F28*Assumptions!$B$14*(365/12/7),0) | H28: =ROUND(G28*Assumptions!$B$15,0) | I28: =AO28*(1-Assumptions!$B$61) | J28: =M27 | K28: =IFERROR(J28/Assumptions!$B$17,0) | L28: =J28*Assumptions!$B$20/12 | M28: =MAX(J28+I28-K28-L28,0) | N28: =(J28+M28)/2 | O28: =N28*Assumptions!$B$18/12 | P28: =I28*Assumptions!$B$19 | Q28: =O28+P28 | R28: =Assumptions!$B$33*(1+Assumptions!$B$34)^(C28-1)/12 | S28: =L28 | T28: =Q28-R28-S28-AP28 | U28: =MIN(AE28,M28*Assumptions!$B$24/(1+Assumptions!$B$24)) | V28: =((U28+U27)/2)*Assumptions!$B$23/12 | W28: =T28-V28+AJ28 | X28: =X27+W28 | Y28: =MAX(M28-U28,0) | Z28: =R28*Assumptions!$B$25 | AA28: =Y28+Z28 | AB28: =MAX(AB27,AA28) | AC28: =MAX(0,MAX(Z28-AD27-AM28,Z29-AD27-SUM(AM28:AM29),Z30-AD27-SUM(AM28:AM30),Z31-AD27-SUM(AM28:AM31),Z32-AD27-SUM(AM28:AM32),Z33-AD27-SUM(AM28:AM33),Z34-AD27-SUM(AM28:AM34),Z35-AD27-SUM(AM28:AM35),Z36-AD27-SUM(AM28:AM36),Z37-AD27-SUM(AM28:AM37),Z38-AD27-SUM(AM28:AM38),Z39-AD27-SUM(AM28:AM39))) | AD28: =AK28+AC28 | AE28: =IF(SUM($H$4:H28)<Assumptions!$B$57,0,MAX(MAX(Assumptions!$B$44,AE27),IF(M28*Assumptions!$B$24/(1+Assumptions!$B$24)>MAX(Assumptions!$B$44,AE27)*Assumptions!$B$53,M28*Assumptions!$B$24/(1+Assumptions!$B$24)/Assumptions!$B$54,MAX(Assumptions!$B$44,AE27)))) | AF28: =U28-U27 | AG28: =IFERROR(U28/AE28,0) | AH28: =MAX(0,AE28-AE27) | AI28: =MAX(AD27-Z28,0) | AJ28: =AI28*Assumptions!$B$46/12 | AK28: =AD27+Q28-R28-I28+K28+AF28-V28+AJ28-AP28 | AL28: =TRIM(IF(AH28>0,"Increase warehouse facility to $"&TEXT(AE28,"#,##0")&" (from $"&TEXT(AE27,"#,##0")&"). ","")&IF(AC28>0,"Raise ~$"&TEXT(AC28,"#,##0")&" of equity — annual raise, funds the next 12 months.","")) | AM28: =Q28-R28-I28+K28+AF28-V28-AP28 | AN28: =SUM($H$4:H28) | AO28: =H28*Assumptions!$B$16 | AP28: =MAX(AO28*Assumptions!$B$62,Assumptions!$B$63)+Assumptions!$B$64/12 | AQ28: =(O28+P28)*Assumptions!$B$61/(1-Assumptions!$B$61)
A29: 26 | B29: =EDATE(Assumptions!$B$4,25) | C29: =INT((A29-1)/12)+1 | D29: =IF(C29=1,Assumptions!$B$6,IF(C29=2,Assumptions!$B$7,IF(C29=3,Assumptions!$B$8,IF(C29=4,Assumptions!$B$9,Assumptions!$B$10)))) | E29: =ROUND(F28*Assumptions!$B$11,0) | F29: =F28+D29-E29 | G29: =ROUND(F29*Assumptions!$B$14*(365/12/7),0) | H29: =ROUND(G29*Assumptions!$B$15,0) | I29: =AO29*(1-Assumptions!$B$61) | J29: =M28 | K29: =IFERROR(J29/Assumptions!$B$17,0) | L29: =J29*Assumptions!$B$20/12 | M29: =MAX(J29+I29-K29-L29,0) | N29: =(J29+M29)/2 | O29: =N29*Assumptions!$B$18/12 | P29: =I29*Assumptions!$B$19 | Q29: =O29+P29 | R29: =Assumptions!$B$33*(1+Assumptions!$B$34)^(C29-1)/12 | S29: =L29 | T29: =Q29-R29-S29-AP29 | U29: =MIN(AE29,M29*Assumptions!$B$24/(1+Assumptions!$B$24)) | V29: =((U29+U28)/2)*Assumptions!$B$23/12 | W29: =T29-V29+AJ29 | X29: =X28+W29 | Y29: =MAX(M29-U29,0) | Z29: =R29*Assumptions!$B$25 | AA29: =Y29+Z29 | AB29: =MAX(AB28,AA29) | AC29: 0 | AD29: =AK29+AC29 | AE29: =IF(SUM($H$4:H29)<Assumptions!$B$57,0,MAX(MAX(Assumptions!$B$44,AE28),IF(M29*Assumptions!$B$24/(1+Assumptions!$B$24)>MAX(Assumptions!$B$44,AE28)*Assumptions!$B$53,M29*Assumptions!$B$24/(1+Assumptions!$B$24)/Assumptions!$B$54,MAX(Assumptions!$B$44,AE28)))) | AF29: =U29-U28 | AG29: =IFERROR(U29/AE29,0) | AH29: =MAX(0,AE29-AE28) | AI29: =MAX(AD28-Z29,0) | AJ29: =AI29*Assumptions!$B$46/12 | AK29: =AD28+Q29-R29-I29+K29+AF29-V29+AJ29-AP29 | AL29: =TRIM(IF(AH29>0,"Increase warehouse facility to $"&TEXT(AE29,"#,##0")&" (from $"&TEXT(AE28,"#,##0")&"). ","")&IF(AC29>0,"Raise ~$"&TEXT(AC29,"#,##0")&" of equity — annual raise, funds the next 12 months.","")) | AM29: =Q29-R29-I29+K29+AF29-V29-AP29 | AN29: =SUM($H$4:H29) | AO29: =H29*Assumptions!$B$16 | AP29: =MAX(AO29*Assumptions!$B$62,Assumptions!$B$63)+Assumptions!$B$64/12 | AQ29: =(O29+P29)*Assumptions!$B$61/(1-Assumptions!$B$61)
A30: 27 | B30: =EDATE(Assumptions!$B$4,26) | C30: =INT((A30-1)/12)+1 | D30: =IF(C30=1,Assumptions!$B$6,IF(C30=2,Assumptions!$B$7,IF(C30=3,Assumptions!$B$8,IF(C30=4,Assumptions!$B$9,Assumptions!$B$10)))) | E30: =ROUND(F29*Assumptions!$B$11,0) | F30: =F29+D30-E30 | G30: =ROUND(F30*Assumptions!$B$14*(365/12/7),0) | H30: =ROUND(G30*Assumptions!$B$15,0) | I30: =AO30*(1-Assumptions!$B$61) | J30: =M29 | K30: =IFERROR(J30/Assumptions!$B$17,0) | L30: =J30*Assumptions!$B$20/12 | M30: =MAX(J30+I30-K30-L30,0) | N30: =(J30+M30)/2 | O30: =N30*Assumptions!$B$18/12 | P30: =I30*Assumptions!$B$19 | Q30: =O30+P30 | R30: =Assumptions!$B$33*(1+Assumptions!$B$34)^(C30-1)/12 | S30: =L30 | T30: =Q30-R30-S30-AP30 | U30: =MIN(AE30,M30*Assumptions!$B$24/(1+Assumptions!$B$24)) | V30: =((U30+U29)/2)*Assumptions!$B$23/12 | W30: =T30-V30+AJ30 | X30: =X29+W30 | Y30: =MAX(M30-U30,0) | Z30: =R30*Assumptions!$B$25 | AA30: =Y30+Z30 | AB30: =MAX(AB29,AA30) | AC30: 0 | AD30: =AK30+AC30 | AE30: =IF(SUM($H$4:H30)<Assumptions!$B$57,0,MAX(MAX(Assumptions!$B$44,AE29),IF(M30*Assumptions!$B$24/(1+Assumptions!$B$24)>MAX(Assumptions!$B$44,AE29)*Assumptions!$B$53,M30*Assumptions!$B$24/(1+Assumptions!$B$24)/Assumptions!$B$54,MAX(Assumptions!$B$44,AE29)))) | AF30: =U30-U29 | AG30: =IFERROR(U30/AE30,0) | AH30: =MAX(0,AE30-AE29) | AI30: =MAX(AD29-Z30,0) | AJ30: =AI30*Assumptions!$B$46/12 | AK30: =AD29+Q30-R30-I30+K30+AF30-V30+AJ30-AP30 | AL30: =TRIM(IF(AH30>0,"Increase warehouse facility to $"&TEXT(AE30,"#,##0")&" (from $"&TEXT(AE29,"#,##0")&"). ","")&IF(AC30>0,"Raise ~$"&TEXT(AC30,"#,##0")&" of equity — annual raise, funds the next 12 months.","")) | AM30: =Q30-R30-I30+K30+AF30-V30-AP30 | AN30: =SUM($H$4:H30) | AO30: =H30*Assumptions!$B$16 | AP30: =MAX(AO30*Assumptions!$B$62,Assumptions!$B$63)+Assumptions!$B$64/12 | AQ30: =(O30+P30)*Assumptions!$B$61/(1-Assumptions!$B$61)
A31: 28 | B31: =EDATE(Assumptions!$B$4,27) | C31: =INT((A31-1)/12)+1 | D31: =IF(C31=1,Assumptions!$B$6,IF(C31=2,Assumptions!$B$7,IF(C31=3,Assumptions!$B$8,IF(C31=4,Assumptions!$B$9,Assumptions!$B$10)))) | E31: =ROUND(F30*Assumptions!$B$11,0) | F31: =F30+D31-E31 | G31: =ROUND(F31*Assumptions!$B$14*(365/12/7),0) | H31: =ROUND(G31*Assumptions!$B$15,0) | I31: =AO31*(1-Assumptions!$B$61) | J31: =M30 | K31: =IFERROR(J31/Assumptions!$B$17,0) | L31: =J31*Assumptions!$B$20/12 | M31: =MAX(J31+I31-K31-L31,0) | N31: =(J31+M31)/2 | O31: =N31*Assumptions!$B$18/12 | P31: =I31*Assumptions!$B$19 | Q31: =O31+P31 | R31: =Assumptions!$B$33*(1+Assumptions!$B$34)^(C31-1)/12 | S31: =L31 | T31: =Q31-R31-S31-AP31 | U31: =MIN(AE31,M31*Assumptions!$B$24/(1+Assumptions!$B$24)) | V31: =((U31+U30)/2)*Assumptions!$B$23/12 | W31: =T31-V31+AJ31 | X31: =X30+W31 | Y31: =MAX(M31-U31,0) | Z31: =R31*Assumptions!$B$25 | AA31: =Y31+Z31 | AB31: =MAX(AB30,AA31) | AC31: 0 | AD31: =AK31+AC31 | AE31: =IF(SUM($H$4:H31)<Assumptions!$B$57,0,MAX(MAX(Assumptions!$B$44,AE30),IF(M31*Assumptions!$B$24/(1+Assumptions!$B$24)>MAX(Assumptions!$B$44,AE30)*Assumptions!$B$53,M31*Assumptions!$B$24/(1+Assumptions!$B$24)/Assumptions!$B$54,MAX(Assumptions!$B$44,AE30)))) | AF31: =U31-U30 | AG31: =IFERROR(U31/AE31,0) | AH31: =MAX(0,AE31-AE30) | AI31: =MAX(AD30-Z31,0) | AJ31: =AI31*Assumptions!$B$46/12 | AK31: =AD30+Q31-R31-I31+K31+AF31-V31+AJ31-AP31 | AL31: =TRIM(IF(AH31>0,"Increase warehouse facility to $"&TEXT(AE31,"#,##0")&" (from $"&TEXT(AE30,"#,##0")&"). ","")&IF(AC31>0,"Raise ~$"&TEXT(AC31,"#,##0")&" of equity — annual raise, funds the next 12 months.","")) | AM31: =Q31-R31-I31+K31+AF31-V31-AP31 | AN31: =SUM($H$4:H31) | AO31: =H31*Assumptions!$B$16 | AP31: =MAX(AO31*Assumptions!$B$62,Assumptions!$B$63)+Assumptions!$B$64/12 | AQ31: =(O31+P31)*Assumptions!$B$61/(1-Assumptions!$B$61)
A32: 29 | B32: =EDATE(Assumptions!$B$4,28) | C32: =INT((A32-1)/12)+1 | D32: =IF(C32=1,Assumptions!$B$6,IF(C32=2,Assumptions!$B$7,IF(C32=3,Assumptions!$B$8,IF(C32=4,Assumptions!$B$9,Assumptions!$B$10)))) | E32: =ROUND(F31*Assumptions!$B$11,0) | F32: =F31+D32-E32 | G32: =ROUND(F32*Assumptions!$B$14*(365/12/7),0) | H32: =ROUND(G32*Assumptions!$B$15,0) | I32: =AO32*(1-Assumptions!$B$61) | J32: =M31 | K32: =IFERROR(J32/Assumptions!$B$17,0) | L32: =J32*Assumptions!$B$20/12 | M32: =MAX(J32+I32-K32-L32,0) | N32: =(J32+M32)/2 | O32: =N32*Assumptions!$B$18/12 | P32: =I32*Assumptions!$B$19 | Q32: =O32+P32 | R32: =Assumptions!$B$33*(1+Assumptions!$B$34)^(C32-1)/12 | S32: =L32 | T32: =Q32-R32-S32-AP32 | U32: =MIN(AE32,M32*Assumptions!$B$24/(1+Assumptions!$B$24)) | V32: =((U32+U31)/2)*Assumptions!$B$23/12 | W32: =T32-V32+AJ32 | X32: =X31+W32 | Y32: =MAX(M32-U32,0) | Z32: =R32*Assumptions!$B$25 | AA32: =Y32+Z32 | AB32: =MAX(AB31,AA32) | AC32: 0 | AD32: =AK32+AC32 | AE32: =IF(SUM($H$4:H32)<Assumptions!$B$57,0,MAX(MAX(Assumptions!$B$44,AE31),IF(M32*Assumptions!$B$24/(1+Assumptions!$B$24)>MAX(Assumptions!$B$44,AE31)*Assumptions!$B$53,M32*Assumptions!$B$24/(1+Assumptions!$B$24)/Assumptions!$B$54,MAX(Assumptions!$B$44,AE31)))) | AF32: =U32-U31 | AG32: =IFERROR(U32/AE32,0) | AH32: =MAX(0,AE32-AE31) | AI32: =MAX(AD31-Z32,0) | AJ32: =AI32*Assumptions!$B$46/12 | AK32: =AD31+Q32-R32-I32+K32+AF32-V32+AJ32-AP32 | AL32: =TRIM(IF(AH32>0,"Increase warehouse facility to $"&TEXT(AE32,"#,##0")&" (from $"&TEXT(AE31,"#,##0")&"). ","")&IF(AC32>0,"Raise ~$"&TEXT(AC32,"#,##0")&" of equity — annual raise, funds the next 12 months.","")) | AM32: =Q32-R32-I32+K32+AF32-V32-AP32 | AN32: =SUM($H$4:H32) | AO32: =H32*Assumptions!$B$16 | AP32: =MAX(AO32*Assumptions!$B$62,Assumptions!$B$63)+Assumptions!$B$64/12 | AQ32: =(O32+P32)*Assumptions!$B$61/(1-Assumptions!$B$61)
A33: 30 | B33: =EDATE(Assumptions!$B$4,29) | C33: =INT((A33-1)/12)+1 | D33: =IF(C33=1,Assumptions!$B$6,IF(C33=2,Assumptions!$B$7,IF(C33=3,Assumptions!$B$8,IF(C33=4,Assumptions!$B$9,Assumptions!$B$10)))) | E33: =ROUND(F32*Assumptions!$B$11,0) | F33: =F32+D33-E33 | G33: =ROUND(F33*Assumptions!$B$14*(365/12/7),0) | H33: =ROUND(G33*Assumptions!$B$15,0) | I33: =AO33*(1-Assumptions!$B$61) | J33: =M32 | K33: =IFERROR(J33/Assumptions!$B$17,0) | L33: =J33*Assumptions!$B$20/12 | M33: =MAX(J33+I33-K33-L33,0) | N33: =(J33+M33)/2 | O33: =N33*Assumptions!$B$18/12 | P33: =I33*Assumptions!$B$19 | Q33: =O33+P33 | R33: =Assumptions!$B$33*(1+Assumptions!$B$34)^(C33-1)/12 | S33: =L33 | T33: =Q33-R33-S33-AP33 | U33: =MIN(AE33,M33*Assumptions!$B$24/(1+Assumptions!$B$24)) | V33: =((U33+U32)/2)*Assumptions!$B$23/12 | W33: =T33-V33+AJ33 | X33: =X32+W33 | Y33: =MAX(M33-U33,0) | Z33: =R33*Assumptions!$B$25 | AA33: =Y33+Z33 | AB33: =MAX(AB32,AA33) | AC33: 0 | AD33: =AK33+AC33 | AE33: =IF(SUM($H$4:H33)<Assumptions!$B$57,0,MAX(MAX(Assumptions!$B$44,AE32),IF(M33*Assumptions!$B$24/(1+Assumptions!$B$24)>MAX(Assumptions!$B$44,AE32)*Assumptions!$B$53,M33*Assumptions!$B$24/(1+Assumptions!$B$24)/Assumptions!$B$54,MAX(Assumptions!$B$44,AE32)))) | AF33: =U33-U32 | AG33: =IFERROR(U33/AE33,0) | AH33: =MAX(0,AE33-AE32) | AI33: =MAX(AD32-Z33,0) | AJ33: =AI33*Assumptions!$B$46/12 | AK33: =AD32+Q33-R33-I33+K33+AF33-V33+AJ33-AP33 | AL33: =TRIM(IF(AH33>0,"Increase warehouse facility to $"&TEXT(AE33,"#,##0")&" (from $"&TEXT(AE32,"#,##0")&"). ","")&IF(AC33>0,"Raise ~$"&TEXT(AC33,"#,##0")&" of equity — annual raise, funds the next 12 months.","")) | AM33: =Q33-R33-I33+K33+AF33-V33-AP33 | AN33: =SUM($H$4:H33) | AO33: =H33*Assumptions!$B$16 | AP33: =MAX(AO33*Assumptions!$B$62,Assumptions!$B$63)+Assumptions!$B$64/12 | AQ33: =(O33+P33)*Assumptions!$B$61/(1-Assumptions!$B$61)
A34: 31 | B34: =EDATE(Assumptions!$B$4,30) | C34: =INT((A34-1)/12)+1 | D34: =IF(C34=1,Assumptions!$B$6,IF(C34=2,Assumptions!$B$7,IF(C34=3,Assumptions!$B$8,IF(C34=4,Assumptions!$B$9,Assumptions!$B$10)))) | E34: =ROUND(F33*Assumptions!$B$11,0) | F34: =F33+D34-E34 | G34: =ROUND(F34*Assumptions!$B$14*(365/12/7),0) | H34: =ROUND(G34*Assumptions!$B$15,0) | I34: =AO34*(1-Assumptions!$B$61) | J34: =M33 | K34: =IFERROR(J34/Assumptions!$B$17,0) | L34: =J34*Assumptions!$B$20/12 | M34: =MAX(J34+I34-K34-L34,0) | N34: =(J34+M34)/2 | O34: =N34*Assumptions!$B$18/12 | P34: =I34*Assumptions!$B$19 | Q34: =O34+P34 | R34: =Assumptions!$B$33*(1+Assumptions!$B$34)^(C34-1)/12 | S34: =L34 | T34: =Q34-R34-S34-AP34 | U34: =MIN(AE34,M34*Assumptions!$B$24/(1+Assumptions!$B$24)) | V34: =((U34+U33)/2)*Assumptions!$B$23/12 | W34: =T34-V34+AJ34 | X34: =X33+W34 | Y34: =MAX(M34-U34,0) | Z34: =R34*Assumptions!$B$25 | AA34: =Y34+Z34 | AB34: =MAX(AB33,AA34) | AC34: 0 | AD34: =AK34+AC34 | AE34: =IF(SUM($H$4:H34)<Assumptions!$B$57,0,MAX(MAX(Assumptions!$B$44,AE33),IF(M34*Assumptions!$B$24/(1+Assumptions!$B$24)>MAX(Assumptions!$B$44,AE33)*Assumptions!$B$53,M34*Assumptions!$B$24/(1+Assumptions!$B$24)/Assumptions!$B$54,MAX(Assumptions!$B$44,AE33)))) | AF34: =U34-U33 | AG34: =IFERROR(U34/AE34,0) | AH34: =MAX(0,AE34-AE33) | AI34: =MAX(AD33-Z34,0) | AJ34: =AI34*Assumptions!$B$46/12 | AK34: =AD33+Q34-R34-I34+K34+AF34-V34+AJ34-AP34 | AL34: =TRIM(IF(AH34>0,"Increase warehouse facility to $"&TEXT(AE34,"#,##0")&" (from $"&TEXT(AE33,"#,##0")&"). ","")&IF(AC34>0,"Raise ~$"&TEXT(AC34,"#,##0")&" of equity — annual raise, funds the next 12 months.","")) | AM34: =Q34-R34-I34+K34+AF34-V34-AP34 | AN34: =SUM($H$4:H34) | AO34: =H34*Assumptions!$B$16 | AP34: =MAX(AO34*Assumptions!$B$62,Assumptions!$B$63)+Assumptions!$B$64/12 | AQ34: =(O34+P34)*Assumptions!$B$61/(1-Assumptions!$B$61)
A35: 32 | B35: =EDATE(Assumptions!$B$4,31) | C35: =INT((A35-1)/12)+1 | D35: =IF(C35=1,Assumptions!$B$6,IF(C35=2,Assumptions!$B$7,IF(C35=3,Assumptions!$B$8,IF(C35=4,Assumptions!$B$9,Assumptions!$B$10)))) | E35: =ROUND(F34*Assumptions!$B$11,0) | F35: =F34+D35-E35 | G35: =ROUND(F35*Assumptions!$B$14*(365/12/7),0) | H35: =ROUND(G35*Assumptions!$B$15,0) | I35: =AO35*(1-Assumptions!$B$61) | J35: =M34 | K35: =IFERROR(J35/Assumptions!$B$17,0) | L35: =J35*Assumptions!$B$20/12 | M35: =MAX(J35+I35-K35-L35,0) | N35: =(J35+M35)/2 | O35: =N35*Assumptions!$B$18/12 | P35: =I35*Assumptions!$B$19 | Q35: =O35+P35 | R35: =Assumptions!$B$33*(1+Assumptions!$B$34)^(C35-1)/12 | S35: =L35 | T35: =Q35-R35-S35-AP35 | U35: =MIN(AE35,M35*Assumptions!$B$24/(1+Assumptions!$B$24)) | V35: =((U35+U34)/2)*Assumptions!$B$23/12 | W35: =T35-V35+AJ35 | X35: =X34+W35 | Y35: =MAX(M35-U35,0) | Z35: =R35*Assumptions!$B$25 | AA35: =Y35+Z35 | AB35: =MAX(AB34,AA35) | AC35: 0 | AD35: =AK35+AC35 | AE35: =IF(SUM($H$4:H35)<Assumptions!$B$57,0,MAX(MAX(Assumptions!$B$44,AE34),IF(M35*Assumptions!$B$24/(1+Assumptions!$B$24)>MAX(Assumptions!$B$44,AE34)*Assumptions!$B$53,M35*Assumptions!$B$24/(1+Assumptions!$B$24)/Assumptions!$B$54,MAX(Assumptions!$B$44,AE34)))) | AF35: =U35-U34 | AG35: =IFERROR(U35/AE35,0) | AH35: =MAX(0,AE35-AE34) | AI35: =MAX(AD34-Z35,0) | AJ35: =AI35*Assumptions!$B$46/12 | AK35: =AD34+Q35-R35-I35+K35+AF35-V35+AJ35-AP35 | AL35: =TRIM(IF(AH35>0,"Increase warehouse facility to $"&TEXT(AE35,"#,##0")&" (from $"&TEXT(AE34,"#,##0")&"). ","")&IF(AC35>0,"Raise ~$"&TEXT(AC35,"#,##0")&" of equity — annual raise, funds the next 12 months.","")) | AM35: =Q35-R35-I35+K35+AF35-V35-AP35 | AN35: =SUM($H$4:H35) | AO35: =H35*Assumptions!$B$16 | AP35: =MAX(AO35*Assumptions!$B$62,Assumptions!$B$63)+Assumptions!$B$64/12 | AQ35: =(O35+P35)*Assumptions!$B$61/(1-Assumptions!$B$61)
A36: 33 | B36: =EDATE(Assumptions!$B$4,32) | C36: =INT((A36-1)/12)+1 | D36: =IF(C36=1,Assumptions!$B$6,IF(C36=2,Assumptions!$B$7,IF(C36=3,Assumptions!$B$8,IF(C36=4,Assumptions!$B$9,Assumptions!$B$10)))) | E36: =ROUND(F35*Assumptions!$B$11,0) | F36: =F35+D36-E36 | G36: =ROUND(F36*Assumptions!$B$14*(365/12/7),0) | H36: =ROUND(G36*Assumptions!$B$15,0) | I36: =AO36*(1-Assumptions!$B$61) | J36: =M35 | K36: =IFERROR(J36/Assumptions!$B$17,0) | L36: =J36*Assumptions!$B$20/12 | M36: =MAX(J36+I36-K36-L36,0) | N36: =(J36+M36)/2 | O36: =N36*Assumptions!$B$18/12 | P36: =I36*Assumptions!$B$19 | Q36: =O36+P36 | R36: =Assumptions!$B$33*(1+Assumptions!$B$34)^(C36-1)/12 | S36: =L36 | T36: =Q36-R36-S36-AP36 | U36: =MIN(AE36,M36*Assumptions!$B$24/(1+Assumptions!$B$24)) | V36: =((U36+U35)/2)*Assumptions!$B$23/12 | W36: =T36-V36+AJ36 | X36: =X35+W36 | Y36: =MAX(M36-U36,0) | Z36: =R36*Assumptions!$B$25 | AA36: =Y36+Z36 | AB36: =MAX(AB35,AA36) | AC36: 0 | AD36: =AK36+AC36 | AE36: =IF(SUM($H$4:H36)<Assumptions!$B$57,0,MAX(MAX(Assumptions!$B$44,AE35),IF(M36*Assumptions!$B$24/(1+Assumptions!$B$24)>MAX(Assumptions!$B$44,AE35)*Assumptions!$B$53,M36*Assumptions!$B$24/(1+Assumptions!$B$24)/Assumptions!$B$54,MAX(Assumptions!$B$44,AE35)))) | AF36: =U36-U35 | AG36: =IFERROR(U36/AE36,0) | AH36: =MAX(0,AE36-AE35) | AI36: =MAX(AD35-Z36,0) | AJ36: =AI36*Assumptions!$B$46/12 | AK36: =AD35+Q36-R36-I36+K36+AF36-V36+AJ36-AP36 | AL36: =TRIM(IF(AH36>0,"Increase warehouse facility to $"&TEXT(AE36,"#,##0")&" (from $"&TEXT(AE35,"#,##0")&"). ","")&IF(AC36>0,"Raise ~$"&TEXT(AC36,"#,##0")&" of equity — annual raise, funds the next 12 months.","")) | AM36: =Q36-R36-I36+K36+AF36-V36-AP36 | AN36: =SUM($H$4:H36) | AO36: =H36*Assumptions!$B$16 | AP36: =MAX(AO36*Assumptions!$B$62,Assumptions!$B$63)+Assumptions!$B$64/12 | AQ36: =(O36+P36)*Assumptions!$B$61/(1-Assumptions!$B$61)
A37: 34 | B37: =EDATE(Assumptions!$B$4,33) | C37: =INT((A37-1)/12)+1 | D37: =IF(C37=1,Assumptions!$B$6,IF(C37=2,Assumptions!$B$7,IF(C37=3,Assumptions!$B$8,IF(C37=4,Assumptions!$B$9,Assumptions!$B$10)))) | E37: =ROUND(F36*Assumptions!$B$11,0) | F37: =F36+D37-E37 | G37: =ROUND(F37*Assumptions!$B$14*(365/12/7),0) | H37: =ROUND(G37*Assumptions!$B$15,0) | I37: =AO37*(1-Assumptions!$B$61) | J37: =M36 | K37: =IFERROR(J37/Assumptions!$B$17,0) | L37: =J37*Assumptions!$B$20/12 | M37: =MAX(J37+I37-K37-L37,0) | N37: =(J37+M37)/2 | O37: =N37*Assumptions!$B$18/12 | P37: =I37*Assumptions!$B$19 | Q37: =O37+P37 | R37: =Assumptions!$B$33*(1+Assumptions!$B$34)^(C37-1)/12 | S37: =L37 | T37: =Q37-R37-S37-AP37 | U37: =MIN(AE37,M37*Assumptions!$B$24/(1+Assumptions!$B$24)) | V37: =((U37+U36)/2)*Assumptions!$B$23/12 | W37: =T37-V37+AJ37 | X37: =X36+W37 | Y37: =MAX(M37-U37,0) | Z37: =R37*Assumptions!$B$25 | AA37: =Y37+Z37 | AB37: =MAX(AB36,AA37) | AC37: 0 | AD37: =AK37+AC37 | AE37: =IF(SUM($H$4:H37)<Assumptions!$B$57,0,MAX(MAX(Assumptions!$B$44,AE36),IF(M37*Assumptions!$B$24/(1+Assumptions!$B$24)>MAX(Assumptions!$B$44,AE36)*Assumptions!$B$53,M37*Assumptions!$B$24/(1+Assumptions!$B$24)/Assumptions!$B$54,MAX(Assumptions!$B$44,AE36)))) | AF37: =U37-U36 | AG37: =IFERROR(U37/AE37,0) | AH37: =MAX(0,AE37-AE36) | AI37: =MAX(AD36-Z37,0) | AJ37: =AI37*Assumptions!$B$46/12 | AK37: =AD36+Q37-R37-I37+K37+AF37-V37+AJ37-AP37 | AL37: =TRIM(IF(AH37>0,"Increase warehouse facility to $"&TEXT(AE37,"#,##0")&" (from $"&TEXT(AE36,"#,##0")&"). ","")&IF(AC37>0,"Raise ~$"&TEXT(AC37,"#,##0")&" of equity — annual raise, funds the next 12 months.","")) | AM37: =Q37-R37-I37+K37+AF37-V37-AP37 | AN37: =SUM($H$4:H37) | AO37: =H37*Assumptions!$B$16 | AP37: =MAX(AO37*Assumptions!$B$62,Assumptions!$B$63)+Assumptions!$B$64/12 | AQ37: =(O37+P37)*Assumptions!$B$61/(1-Assumptions!$B$61)
A38: 35 | B38: =EDATE(Assumptions!$B$4,34) | C38: =INT((A38-1)/12)+1 | D38: =IF(C38=1,Assumptions!$B$6,IF(C38=2,Assumptions!$B$7,IF(C38=3,Assumptions!$B$8,IF(C38=4,Assumptions!$B$9,Assumptions!$B$10)))) | E38: =ROUND(F37*Assumptions!$B$11,0) | F38: =F37+D38-E38 | G38: =ROUND(F38*Assumptions!$B$14*(365/12/7),0) | H38: =ROUND(G38*Assumptions!$B$15,0) | I38: =AO38*(1-Assumptions!$B$61) | J38: =M37 | K38: =IFERROR(J38/Assumptions!$B$17,0) | L38: =J38*Assumptions!$B$20/12 | M38: =MAX(J38+I38-K38-L38,0) | N38: =(J38+M38)/2 | O38: =N38*Assumptions!$B$18/12 | P38: =I38*Assumptions!$B$19 | Q38: =O38+P38 | R38: =Assumptions!$B$33*(1+Assumptions!$B$34)^(C38-1)/12 | S38: =L38 | T38: =Q38-R38-S38-AP38 | U38: =MIN(AE38,M38*Assumptions!$B$24/(1+Assumptions!$B$24)) | V38: =((U38+U37)/2)*Assumptions!$B$23/12 | W38: =T38-V38+AJ38 | X38: =X37+W38 | Y38: =MAX(M38-U38,0) | Z38: =R38*Assumptions!$B$25 | AA38: =Y38+Z38 | AB38: =MAX(AB37,AA38) | AC38: 0 | AD38: =AK38+AC38 | AE38: =IF(SUM($H$4:H38)<Assumptions!$B$57,0,MAX(MAX(Assumptions!$B$44,AE37),IF(M38*Assumptions!$B$24/(1+Assumptions!$B$24)>MAX(Assumptions!$B$44,AE37)*Assumptions!$B$53,M38*Assumptions!$B$24/(1+Assumptions!$B$24)/Assumptions!$B$54,MAX(Assumptions!$B$44,AE37)))) | AF38: =U38-U37 | AG38: =IFERROR(U38/AE38,0) | AH38: =MAX(0,AE38-AE37) | AI38: =MAX(AD37-Z38,0) | AJ38: =AI38*Assumptions!$B$46/12 | AK38: =AD37+Q38-R38-I38+K38+AF38-V38+AJ38-AP38 | AL38: =TRIM(IF(AH38>0,"Increase warehouse facility to $"&TEXT(AE38,"#,##0")&" (from $"&TEXT(AE37,"#,##0")&"). ","")&IF(AC38>0,"Raise ~$"&TEXT(AC38,"#,##0")&" of equity — annual raise, funds the next 12 months.","")) | AM38: =Q38-R38-I38+K38+AF38-V38-AP38 | AN38: =SUM($H$4:H38) | AO38: =H38*Assumptions!$B$16 | AP38: =MAX(AO38*Assumptions!$B$62,Assumptions!$B$63)+Assumptions!$B$64/12 | AQ38: =(O38+P38)*Assumptions!$B$61/(1-Assumptions!$B$61)
A39: 36 | B39: =EDATE(Assumptions!$B$4,35) | C39: =INT((A39-1)/12)+1 | D39: =IF(C39=1,Assumptions!$B$6,IF(C39=2,Assumptions!$B$7,IF(C39=3,Assumptions!$B$8,IF(C39=4,Assumptions!$B$9,Assumptions!$B$10)))) | E39: =ROUND(F38*Assumptions!$B$11,0) | F39: =F38+D39-E39 | G39: =ROUND(F39*Assumptions!$B$14*(365/12/7),0) | H39: =ROUND(G39*Assumptions!$B$15,0) | I39: =AO39*(1-Assumptions!$B$61) | J39: =M38 | K39: =IFERROR(J39/Assumptions!$B$17,0) | L39: =J39*Assumptions!$B$20/12 | M39: =MAX(J39+I39-K39-L39,0) | N39: =(J39+M39)/2 | O39: =N39*Assumptions!$B$18/12 | P39: =I39*Assumptions!$B$19 | Q39: =O39+P39 | R39: =Assumptions!$B$33*(1+Assumptions!$B$34)^(C39-1)/12 | S39: =L39 | T39: =Q39-R39-S39-AP39 | U39: =MIN(AE39,M39*Assumptions!$B$24/(1+Assumptions!$B$24)) | V39: =((U39+U38)/2)*Assumptions!$B$23/12 | W39: =T39-V39+AJ39 | X39: =X38+W39 | Y39: =MAX(M39-U39,0) | Z39: =R39*Assumptions!$B$25 | AA39: =Y39+Z39 | AB39: =MAX(AB38,AA39) | AC39: 0 | AD39: =AK39+AC39 | AE39: =IF(SUM($H$4:H39)<Assumptions!$B$57,0,MAX(MAX(Assumptions!$B$44,AE38),IF(M39*Assumptions!$B$24/(1+Assumptions!$B$24)>MAX(Assumptions!$B$44,AE38)*Assumptions!$B$53,M39*Assumptions!$B$24/(1+Assumptions!$B$24)/Assumptions!$B$54,MAX(Assumptions!$B$44,AE38)))) | AF39: =U39-U38 | AG39: =IFERROR(U39/AE39,0) | AH39: =MAX(0,AE39-AE38) | AI39: =MAX(AD38-Z39,0) | AJ39: =AI39*Assumptions!$B$46/12 | AK39: =AD38+Q39-R39-I39+K39+AF39-V39+AJ39-AP39 | AL39: =TRIM(IF(AH39>0,"Increase warehouse facility to $"&TEXT(AE39,"#,##0")&" (from $"&TEXT(AE38,"#,##0")&"). ","")&IF(AC39>0,"Raise ~$"&TEXT(AC39,"#,##0")&" of equity — annual raise, funds the next 12 months.","")) | AM39: =Q39-R39-I39+K39+AF39-V39-AP39 | AN39: =SUM($H$4:H39) | AO39: =H39*Assumptions!$B$16 | AP39: =MAX(AO39*Assumptions!$B$62,Assumptions!$B$63)+Assumptions!$B$64/12 | AQ39: =(O39+P39)*Assumptions!$B$61/(1-Assumptions!$B$61)
A40: 37 | B40: =EDATE(Assumptions!$B$4,36) | C40: =INT((A40-1)/12)+1 | D40: =IF(C40=1,Assumptions!$B$6,IF(C40=2,Assumptions!$B$7,IF(C40=3,Assumptions!$B$8,IF(C40=4,Assumptions!$B$9,Assumptions!$B$10)))) | E40: =ROUND(F39*Assumptions!$B$11,0) | F40: =F39+D40-E40 | G40: =ROUND(F40*Assumptions!$B$14*(365/12/7),0) | H40: =ROUND(G40*Assumptions!$B$15,0) | I40: =AO40*(1-Assumptions!$B$61) | J40: =M39 | K40: =IFERROR(J40/Assumptions!$B$17,0) | L40: =J40*Assumptions!$B$20/12 | M40: =MAX(J40+I40-K40-L40,0) | N40: =(J40+M40)/2 | O40: =N40*Assumptions!$B$18/12 | P40: =I40*Assumptions!$B$19 | Q40: =O40+P40 | R40: =Assumptions!$B$33*(1+Assumptions!$B$34)^(C40-1)/12 | S40: =L40 | T40: =Q40-R40-S40-AP40 | U40: =MIN(AE40,M40*Assumptions!$B$24/(1+Assumptions!$B$24)) | V40: =((U40+U39)/2)*Assumptions!$B$23/12 | W40: =T40-V40+AJ40 | X40: =X39+W40 | Y40: =MAX(M40-U40,0) | Z40: =R40*Assumptions!$B$25 | AA40: =Y40+Z40 | AB40: =MAX(AB39,AA40) | AC40: =MAX(0,MAX(Z40-AD39-AM40,Z41-AD39-SUM(AM40:AM41),Z42-AD39-SUM(AM40:AM42),Z43-AD39-SUM(AM40:AM43),Z44-AD39-SUM(AM40:AM44),Z45-AD39-SUM(AM40:AM45),Z46-AD39-SUM(AM40:AM46),Z47-AD39-SUM(AM40:AM47),Z48-AD39-SUM(AM40:AM48),Z49-AD39-SUM(AM40:AM49),Z50-AD39-SUM(AM40:AM50),Z51-AD39-SUM(AM40:AM51))) | AD40: =AK40+AC40 | AE40: =IF(SUM($H$4:H40)<Assumptions!$B$57,0,MAX(MAX(Assumptions!$B$44,AE39),IF(M40*Assumptions!$B$24/(1+Assumptions!$B$24)>MAX(Assumptions!$B$44,AE39)*Assumptions!$B$53,M40*Assumptions!$B$24/(1+Assumptions!$B$24)/Assumptions!$B$54,MAX(Assumptions!$B$44,AE39)))) | AF40: =U40-U39 | AG40: =IFERROR(U40/AE40,0) | AH40: =MAX(0,AE40-AE39) | AI40: =MAX(AD39-Z40,0) | AJ40: =AI40*Assumptions!$B$46/12 | AK40: =AD39+Q40-R40-I40+K40+AF40-V40+AJ40-AP40 | AL40: =TRIM(IF(AH40>0,"Increase warehouse facility to $"&TEXT(AE40,"#,##0")&" (from $"&TEXT(AE39,"#,##0")&"). ","")&IF(AC40>0,"Raise ~$"&TEXT(AC40,"#,##0")&" of equity — annual raise, funds the next 12 months.","")) | AM40: =Q40-R40-I40+K40+AF40-V40-AP40 | AN40: =SUM($H$4:H40) | AO40: =H40*Assumptions!$B$16 | AP40: =MAX(AO40*Assumptions!$B$62,Assumptions!$B$63)+Assumptions!$B$64/12 | AQ40: =(O40+P40)*Assumptions!$B$61/(1-Assumptions!$B$61)
A41: 38 | B41: =EDATE(Assumptions!$B$4,37) | C41: =INT((A41-1)/12)+1 | D41: =IF(C41=1,Assumptions!$B$6,IF(C41=2,Assumptions!$B$7,IF(C41=3,Assumptions!$B$8,IF(C41=4,Assumptions!$B$9,Assumptions!$B$10)))) | E41: =ROUND(F40*Assumptions!$B$11,0) | F41: =F40+D41-E41 | G41: =ROUND(F41*Assumptions!$B$14*(365/12/7),0) | H41: =ROUND(G41*Assumptions!$B$15,0) | I41: =AO41*(1-Assumptions!$B$61) | J41: =M40 | K41: =IFERROR(J41/Assumptions!$B$17,0) | L41: =J41*Assumptions!$B$20/12 | M41: =MAX(J41+I41-K41-L41,0) | N41: =(J41+M41)/2 | O41: =N41*Assumptions!$B$18/12 | P41: =I41*Assumptions!$B$19 | Q41: =O41+P41 | R41: =Assumptions!$B$33*(1+Assumptions!$B$34)^(C41-1)/12 | S41: =L41 | T41: =Q41-R41-S41-AP41 | U41: =MIN(AE41,M41*Assumptions!$B$24/(1+Assumptions!$B$24)) | V41: =((U41+U40)/2)*Assumptions!$B$23/12 | W41: =T41-V41+AJ41 | X41: =X40+W41 | Y41: =MAX(M41-U41,0) | Z41: =R41*Assumptions!$B$25 | AA41: =Y41+Z41 | AB41: =MAX(AB40,AA41) | AC41: 0 | AD41: =AK41+AC41 | AE41: =IF(SUM($H$4:H41)<Assumptions!$B$57,0,MAX(MAX(Assumptions!$B$44,AE40),IF(M41*Assumptions!$B$24/(1+Assumptions!$B$24)>MAX(Assumptions!$B$44,AE40)*Assumptions!$B$53,M41*Assumptions!$B$24/(1+Assumptions!$B$24)/Assumptions!$B$54,MAX(Assumptions!$B$44,AE40)))) | AF41: =U41-U40 | AG41: =IFERROR(U41/AE41,0) | AH41: =MAX(0,AE41-AE40) | AI41: =MAX(AD40-Z41,0) | AJ41: =AI41*Assumptions!$B$46/12 | AK41: =AD40+Q41-R41-I41+K41+AF41-V41+AJ41-AP41 | AL41: =TRIM(IF(AH41>0,"Increase warehouse facility to $"&TEXT(AE41,"#,##0")&" (from $"&TEXT(AE40,"#,##0")&"). ","")&IF(AC41>0,"Raise ~$"&TEXT(AC41,"#,##0")&" of equity — annual raise, funds the next 12 months.","")) | AM41: =Q41-R41-I41+K41+AF41-V41-AP41 | AN41: =SUM($H$4:H41) | AO41: =H41*Assumptions!$B$16 | AP41: =MAX(AO41*Assumptions!$B$62,Assumptions!$B$63)+Assumptions!$B$64/12 | AQ41: =(O41+P41)*Assumptions!$B$61/(1-Assumptions!$B$61)
A42: 39 | B42: =EDATE(Assumptions!$B$4,38) | C42: =INT((A42-1)/12)+1 | D42: =IF(C42=1,Assumptions!$B$6,IF(C42=2,Assumptions!$B$7,IF(C42=3,Assumptions!$B$8,IF(C42=4,Assumptions!$B$9,Assumptions!$B$10)))) | E42: =ROUND(F41*Assumptions!$B$11,0) | F42: =F41+D42-E42 | G42: =ROUND(F42*Assumptions!$B$14*(365/12/7),0) | H42: =ROUND(G42*Assumptions!$B$15,0) | I42: =AO42*(1-Assumptions!$B$61) | J42: =M41 | K42: =IFERROR(J42/Assumptions!$B$17,0) | L42: =J42*Assumptions!$B$20/12 | M42: =MAX(J42+I42-K42-L42,0) | N42: =(J42+M42)/2 | O42: =N42*Assumptions!$B$18/12 | P42: =I42*Assumptions!$B$19 | Q42: =O42+P42 | R42: =Assumptions!$B$33*(1+Assumptions!$B$34)^(C42-1)/12 | S42: =L42 | T42: =Q42-R42-S42-AP42 | U42: =MIN(AE42,M42*Assumptions!$B$24/(1+Assumptions!$B$24)) | V42: =((U42+U41)/2)*Assumptions!$B$23/12 | W42: =T42-V42+AJ42 | X42: =X41+W42 | Y42: =MAX(M42-U42,0) | Z42: =R42*Assumptions!$B$25 | AA42: =Y42+Z42 | AB42: =MAX(AB41,AA42) | AC42: 0 | AD42: =AK42+AC42 | AE42: =IF(SUM($H$4:H42)<Assumptions!$B$57,0,MAX(MAX(Assumptions!$B$44,AE41),IF(M42*Assumptions!$B$24/(1+Assumptions!$B$24)>MAX(Assumptions!$B$44,AE41)*Assumptions!$B$53,M42*Assumptions!$B$24/(1+Assumptions!$B$24)/Assumptions!$B$54,MAX(Assumptions!$B$44,AE41)))) | AF42: =U42-U41 | AG42: =IFERROR(U42/AE42,0) | AH42: =MAX(0,AE42-AE41) | AI42: =MAX(AD41-Z42,0) | AJ42: =AI42*Assumptions!$B$46/12 | AK42: =AD41+Q42-R42-I42+K42+AF42-V42+AJ42-AP42 | AL42: =TRIM(IF(AH42>0,"Increase warehouse facility to $"&TEXT(AE42,"#,##0")&" (from $"&TEXT(AE41,"#,##0")&"). ","")&IF(AC42>0,"Raise ~$"&TEXT(AC42,"#,##0")&" of equity — annual raise, funds the next 12 months.","")) | AM42: =Q42-R42-I42+K42+AF42-V42-AP42 | AN42: =SUM($H$4:H42) | AO42: =H42*Assumptions!$B$16 | AP42: =MAX(AO42*Assumptions!$B$62,Assumptions!$B$63)+Assumptions!$B$64/12 | AQ42: =(O42+P42)*Assumptions!$B$61/(1-Assumptions!$B$61)
A43: 40 | B43: =EDATE(Assumptions!$B$4,39) | C43: =INT((A43-1)/12)+1 | D43: =IF(C43=1,Assumptions!$B$6,IF(C43=2,Assumptions!$B$7,IF(C43=3,Assumptions!$B$8,IF(C43=4,Assumptions!$B$9,Assumptions!$B$10)))) | E43: =ROUND(F42*Assumptions!$B$11,0) | F43: =F42+D43-E43 | G43: =ROUND(F43*Assumptions!$B$14*(365/12/7),0) | H43: =ROUND(G43*Assumptions!$B$15,0) | I43: =AO43*(1-Assumptions!$B$61) | J43: =M42 | K43: =IFERROR(J43/Assumptions!$B$17,0) | L43: =J43*Assumptions!$B$20/12 | M43: =MAX(J43+I43-K43-L43,0) | N43: =(J43+M43)/2 | O43: =N43*Assumptions!$B$18/12 | P43: =I43*Assumptions!$B$19 | Q43: =O43+P43 | R43: =Assumptions!$B$33*(1+Assumptions!$B$34)^(C43-1)/12 | S43: =L43 | T43: =Q43-R43-S43-AP43 | U43: =MIN(AE43,M43*Assumptions!$B$24/(1+Assumptions!$B$24)) | V43: =((U43+U42)/2)*Assumptions!$B$23/12 | W43: =T43-V43+AJ43 | X43: =X42+W43 | Y43: =MAX(M43-U43,0) | Z43: =R43*Assumptions!$B$25 | AA43: =Y43+Z43 | AB43: =MAX(AB42,AA43) | AC43: 0 | AD43: =AK43+AC43 | AE43: =IF(SUM($H$4:H43)<Assumptions!$B$57,0,MAX(MAX(Assumptions!$B$44,AE42),IF(M43*Assumptions!$B$24/(1+Assumptions!$B$24)>MAX(Assumptions!$B$44,AE42)*Assumptions!$B$53,M43*Assumptions!$B$24/(1+Assumptions!$B$24)/Assumptions!$B$54,MAX(Assumptions!$B$44,AE42)))) | AF43: =U43-U42 | AG43: =IFERROR(U43/AE43,0) | AH43: =MAX(0,AE43-AE42) | AI43: =MAX(AD42-Z43,0) | AJ43: =AI43*Assumptions!$B$46/12 | AK43: =AD42+Q43-R43-I43+K43+AF43-V43+AJ43-AP43 | AL43: =TRIM(IF(AH43>0,"Increase warehouse facility to $"&TEXT(AE43,"#,##0")&" (from $"&TEXT(AE42,"#,##0")&"). ","")&IF(AC43>0,"Raise ~$"&TEXT(AC43,"#,##0")&" of equity — annual raise, funds the next 12 months.","")) | AM43: =Q43-R43-I43+K43+AF43-V43-AP43 | AN43: =SUM($H$4:H43) | AO43: =H43*Assumptions!$B$16 | AP43: =MAX(AO43*Assumptions!$B$62,Assumptions!$B$63)+Assumptions!$B$64/12 | AQ43: =(O43+P43)*Assumptions!$B$61/(1-Assumptions!$B$61)
A44: 41 | B44: =EDATE(Assumptions!$B$4,40) | C44: =INT((A44-1)/12)+1 | D44: =IF(C44=1,Assumptions!$B$6,IF(C44=2,Assumptions!$B$7,IF(C44=3,Assumptions!$B$8,IF(C44=4,Assumptions!$B$9,Assumptions!$B$10)))) | E44: =ROUND(F43*Assumptions!$B$11,0) | F44: =F43+D44-E44 | G44: =ROUND(F44*Assumptions!$B$14*(365/12/7),0) | H44: =ROUND(G44*Assumptions!$B$15,0) | I44: =AO44*(1-Assumptions!$B$61) | J44: =M43 | K44: =IFERROR(J44/Assumptions!$B$17,0) | L44: =J44*Assumptions!$B$20/12 | M44: =MAX(J44+I44-K44-L44,0) | N44: =(J44+M44)/2 | O44: =N44*Assumptions!$B$18/12 | P44: =I44*Assumptions!$B$19 | Q44: =O44+P44 | R44: =Assumptions!$B$33*(1+Assumptions!$B$34)^(C44-1)/12 | S44: =L44 | T44: =Q44-R44-S44-AP44 | U44: =MIN(AE44,M44*Assumptions!$B$24/(1+Assumptions!$B$24)) | V44: =((U44+U43)/2)*Assumptions!$B$23/12 | W44: =T44-V44+AJ44 | X44: =X43+W44 | Y44: =MAX(M44-U44,0) | Z44: =R44*Assumptions!$B$25 | AA44: =Y44+Z44 | AB44: =MAX(AB43,AA44) | AC44: 0 | AD44: =AK44+AC44 | AE44: =IF(SUM($H$4:H44)<Assumptions!$B$57,0,MAX(MAX(Assumptions!$B$44,AE43),IF(M44*Assumptions!$B$24/(1+Assumptions!$B$24)>MAX(Assumptions!$B$44,AE43)*Assumptions!$B$53,M44*Assumptions!$B$24/(1+Assumptions!$B$24)/Assumptions!$B$54,MAX(Assumptions!$B$44,AE43)))) | AF44: =U44-U43 | AG44: =IFERROR(U44/AE44,0) | AH44: =MAX(0,AE44-AE43) | AI44: =MAX(AD43-Z44,0) | AJ44: =AI44*Assumptions!$B$46/12 | AK44: =AD43+Q44-R44-I44+K44+AF44-V44+AJ44-AP44 | AL44: =TRIM(IF(AH44>0,"Increase warehouse facility to $"&TEXT(AE44,"#,##0")&" (from $"&TEXT(AE43,"#,##0")&"). ","")&IF(AC44>0,"Raise ~$"&TEXT(AC44,"#,##0")&" of equity — annual raise, funds the next 12 months.","")) | AM44: =Q44-R44-I44+K44+AF44-V44-AP44 | AN44: =SUM($H$4:H44) | AO44: =H44*Assumptions!$B$16 | AP44: =MAX(AO44*Assumptions!$B$62,Assumptions!$B$63)+Assumptions!$B$64/12 | AQ44: =(O44+P44)*Assumptions!$B$61/(1-Assumptions!$B$61)
A45: 42 | B45: =EDATE(Assumptions!$B$4,41) | C45: =INT((A45-1)/12)+1 | D45: =IF(C45=1,Assumptions!$B$6,IF(C45=2,Assumptions!$B$7,IF(C45=3,Assumptions!$B$8,IF(C45=4,Assumptions!$B$9,Assumptions!$B$10)))) | E45: =ROUND(F44*Assumptions!$B$11,0) | F45: =F44+D45-E45 | G45: =ROUND(F45*Assumptions!$B$14*(365/12/7),0) | H45: =ROUND(G45*Assumptions!$B$15,0) | I45: =AO45*(1-Assumptions!$B$61) | J45: =M44 | K45: =IFERROR(J45/Assumptions!$B$17,0) | L45: =J45*Assumptions!$B$20/12 | M45: =MAX(J45+I45-K45-L45,0) | N45: =(J45+M45)/2 | O45: =N45*Assumptions!$B$18/12 | P45: =I45*Assumptions!$B$19 | Q45: =O45+P45 | R45: =Assumptions!$B$33*(1+Assumptions!$B$34)^(C45-1)/12 | S45: =L45 | T45: =Q45-R45-S45-AP45 | U45: =MIN(AE45,M45*Assumptions!$B$24/(1+Assumptions!$B$24)) | V45: =((U45+U44)/2)*Assumptions!$B$23/12 | W45: =T45-V45+AJ45 | X45: =X44+W45 | Y45: =MAX(M45-U45,0) | Z45: =R45*Assumptions!$B$25 | AA45: =Y45+Z45 | AB45: =MAX(AB44,AA45) | AC45: 0 | AD45: =AK45+AC45 | AE45: =IF(SUM($H$4:H45)<Assumptions!$B$57,0,MAX(MAX(Assumptions!$B$44,AE44),IF(M45*Assumptions!$B$24/(1+Assumptions!$B$24)>MAX(Assumptions!$B$44,AE44)*Assumptions!$B$53,M45*Assumptions!$B$24/(1+Assumptions!$B$24)/Assumptions!$B$54,MAX(Assumptions!$B$44,AE44)))) | AF45: =U45-U44 | AG45: =IFERROR(U45/AE45,0) | AH45: =MAX(0,AE45-AE44) | AI45: =MAX(AD44-Z45,0) | AJ45: =AI45*Assumptions!$B$46/12 | AK45: =AD44+Q45-R45-I45+K45+AF45-V45+AJ45-AP45 | AL45: =TRIM(IF(AH45>0,"Increase warehouse facility to $"&TEXT(AE45,"#,##0")&" (from $"&TEXT(AE44,"#,##0")&"). ","")&IF(AC45>0,"Raise ~$"&TEXT(AC45,"#,##0")&" of equity — annual raise, funds the next 12 months.","")) | AM45: =Q45-R45-I45+K45+AF45-V45-AP45 | AN45: =SUM($H$4:H45) | AO45: =H45*Assumptions!$B$16 | AP45: =MAX(AO45*Assumptions!$B$62,Assumptions!$B$63)+Assumptions!$B$64/12 | AQ45: =(O45+P45)*Assumptions!$B$61/(1-Assumptions!$B$61)
A46: 43 | B46: =EDATE(Assumptions!$B$4,42) | C46: =INT((A46-1)/12)+1 | D46: =IF(C46=1,Assumptions!$B$6,IF(C46=2,Assumptions!$B$7,IF(C46=3,Assumptions!$B$8,IF(C46=4,Assumptions!$B$9,Assumptions!$B$10)))) | E46: =ROUND(F45*Assumptions!$B$11,0) | F46: =F45+D46-E46 | G46: =ROUND(F46*Assumptions!$B$14*(365/12/7),0) | H46: =ROUND(G46*Assumptions!$B$15,0) | I46: =AO46*(1-Assumptions!$B$61) | J46: =M45 | K46: =IFERROR(J46/Assumptions!$B$17,0) | L46: =J46*Assumptions!$B$20/12 | M46: =MAX(J46+I46-K46-L46,0) | N46: =(J46+M46)/2 | O46: =N46*Assumptions!$B$18/12 | P46: =I46*Assumptions!$B$19 | Q46: =O46+P46 | R46: =Assumptions!$B$33*(1+Assumptions!$B$34)^(C46-1)/12 | S46: =L46 | T46: =Q46-R46-S46-AP46 | U46: =MIN(AE46,M46*Assumptions!$B$24/(1+Assumptions!$B$24)) | V46: =((U46+U45)/2)*Assumptions!$B$23/12 | W46: =T46-V46+AJ46 | X46: =X45+W46 | Y46: =MAX(M46-U46,0) | Z46: =R46*Assumptions!$B$25 | AA46: =Y46+Z46 | AB46: =MAX(AB45,AA46) | AC46: 0 | AD46: =AK46+AC46 | AE46: =IF(SUM($H$4:H46)<Assumptions!$B$57,0,MAX(MAX(Assumptions!$B$44,AE45),IF(M46*Assumptions!$B$24/(1+Assumptions!$B$24)>MAX(Assumptions!$B$44,AE45)*Assumptions!$B$53,M46*Assumptions!$B$24/(1+Assumptions!$B$24)/Assumptions!$B$54,MAX(Assumptions!$B$44,AE45)))) | AF46: =U46-U45 | AG46: =IFERROR(U46/AE46,0) | AH46: =MAX(0,AE46-AE45) | AI46: =MAX(AD45-Z46,0) | AJ46: =AI46*Assumptions!$B$46/12 | AK46: =AD45+Q46-R46-I46+K46+AF46-V46+AJ46-AP46 | AL46: =TRIM(IF(AH46>0,"Increase warehouse facility to $"&TEXT(AE46,"#,##0")&" (from $"&TEXT(AE45,"#,##0")&"). ","")&IF(AC46>0,"Raise ~$"&TEXT(AC46,"#,##0")&" of equity — annual raise, funds the next 12 months.","")) | AM46: =Q46-R46-I46+K46+AF46-V46-AP46 | AN46: =SUM($H$4:H46) | AO46: =H46*Assumptions!$B$16 | AP46: =MAX(AO46*Assumptions!$B$62,Assumptions!$B$63)+Assumptions!$B$64/12 | AQ46: =(O46+P46)*Assumptions!$B$61/(1-Assumptions!$B$61)
A47: 44 | B47: =EDATE(Assumptions!$B$4,43) | C47: =INT((A47-1)/12)+1 | D47: =IF(C47=1,Assumptions!$B$6,IF(C47=2,Assumptions!$B$7,IF(C47=3,Assumptions!$B$8,IF(C47=4,Assumptions!$B$9,Assumptions!$B$10)))) | E47: =ROUND(F46*Assumptions!$B$11,0) | F47: =F46+D47-E47 | G47: =ROUND(F47*Assumptions!$B$14*(365/12/7),0) | H47: =ROUND(G47*Assumptions!$B$15,0) | I47: =AO47*(1-Assumptions!$B$61) | J47: =M46 | K47: =IFERROR(J47/Assumptions!$B$17,0) | L47: =J47*Assumptions!$B$20/12 | M47: =MAX(J47+I47-K47-L47,0) | N47: =(J47+M47)/2 | O47: =N47*Assumptions!$B$18/12 | P47: =I47*Assumptions!$B$19 | Q47: =O47+P47 | R47: =Assumptions!$B$33*(1+Assumptions!$B$34)^(C47-1)/12 | S47: =L47 | T47: =Q47-R47-S47-AP47 | U47: =MIN(AE47,M47*Assumptions!$B$24/(1+Assumptions!$B$24)) | V47: =((U47+U46)/2)*Assumptions!$B$23/12 | W47: =T47-V47+AJ47 | X47: =X46+W47 | Y47: =MAX(M47-U47,0) | Z47: =R47*Assumptions!$B$25 | AA47: =Y47+Z47 | AB47: =MAX(AB46,AA47) | AC47: 0 | AD47: =AK47+AC47 | AE47: =IF(SUM($H$4:H47)<Assumptions!$B$57,0,MAX(MAX(Assumptions!$B$44,AE46),IF(M47*Assumptions!$B$24/(1+Assumptions!$B$24)>MAX(Assumptions!$B$44,AE46)*Assumptions!$B$53,M47*Assumptions!$B$24/(1+Assumptions!$B$24)/Assumptions!$B$54,MAX(Assumptions!$B$44,AE46)))) | AF47: =U47-U46 | AG47: =IFERROR(U47/AE47,0) | AH47: =MAX(0,AE47-AE46) | AI47: =MAX(AD46-Z47,0) | AJ47: =AI47*Assumptions!$B$46/12 | AK47: =AD46+Q47-R47-I47+K47+AF47-V47+AJ47-AP47 | AL47: =TRIM(IF(AH47>0,"Increase warehouse facility to $"&TEXT(AE47,"#,##0")&" (from $"&TEXT(AE46,"#,##0")&"). ","")&IF(AC47>0,"Raise ~$"&TEXT(AC47,"#,##0")&" of equity — annual raise, funds the next 12 months.","")) | AM47: =Q47-R47-I47+K47+AF47-V47-AP47 | AN47: =SUM($H$4:H47) | AO47: =H47*Assumptions!$B$16 | AP47: =MAX(AO47*Assumptions!$B$62,Assumptions!$B$63)+Assumptions!$B$64/12 | AQ47: =(O47+P47)*Assumptions!$B$61/(1-Assumptions!$B$61)
A48: 45 | B48: =EDATE(Assumptions!$B$4,44) | C48: =INT((A48-1)/12)+1 | D48: =IF(C48=1,Assumptions!$B$6,IF(C48=2,Assumptions!$B$7,IF(C48=3,Assumptions!$B$8,IF(C48=4,Assumptions!$B$9,Assumptions!$B$10)))) | E48: =ROUND(F47*Assumptions!$B$11,0) | F48: =F47+D48-E48 | G48: =ROUND(F48*Assumptions!$B$14*(365/12/7),0) | H48: =ROUND(G48*Assumptions!$B$15,0) | I48: =AO48*(1-Assumptions!$B$61) | J48: =M47 | K48: =IFERROR(J48/Assumptions!$B$17,0) | L48: =J48*Assumptions!$B$20/12 | M48: =MAX(J48+I48-K48-L48,0) | N48: =(J48+M48)/2 | O48: =N48*Assumptions!$B$18/12 | P48: =I48*Assumptions!$B$19 | Q48: =O48+P48 | R48: =Assumptions!$B$33*(1+Assumptions!$B$34)^(C48-1)/12 | S48: =L48 | T48: =Q48-R48-S48-AP48 | U48: =MIN(AE48,M48*Assumptions!$B$24/(1+Assumptions!$B$24)) | V48: =((U48+U47)/2)*Assumptions!$B$23/12 | W48: =T48-V48+AJ48 | X48: =X47+W48 | Y48: =MAX(M48-U48,0) | Z48: =R48*Assumptions!$B$25 | AA48: =Y48+Z48 | AB48: =MAX(AB47,AA48) | AC48: 0 | AD48: =AK48+AC48 | AE48: =IF(SUM($H$4:H48)<Assumptions!$B$57,0,MAX(MAX(Assumptions!$B$44,AE47),IF(M48*Assumptions!$B$24/(1+Assumptions!$B$24)>MAX(Assumptions!$B$44,AE47)*Assumptions!$B$53,M48*Assumptions!$B$24/(1+Assumptions!$B$24)/Assumptions!$B$54,MAX(Assumptions!$B$44,AE47)))) | AF48: =U48-U47 | AG48: =IFERROR(U48/AE48,0) | AH48: =MAX(0,AE48-AE47) | AI48: =MAX(AD47-Z48,0) | AJ48: =AI48*Assumptions!$B$46/12 | AK48: =AD47+Q48-R48-I48+K48+AF48-V48+AJ48-AP48 | AL48: =TRIM(IF(AH48>0,"Increase warehouse facility to $"&TEXT(AE48,"#,##0")&" (from $"&TEXT(AE47,"#,##0")&"). ","")&IF(AC48>0,"Raise ~$"&TEXT(AC48,"#,##0")&" of equity — annual raise, funds the next 12 months.","")) | AM48: =Q48-R48-I48+K48+AF48-V48-AP48 | AN48: =SUM($H$4:H48) | AO48: =H48*Assumptions!$B$16 | AP48: =MAX(AO48*Assumptions!$B$62,Assumptions!$B$63)+Assumptions!$B$64/12 | AQ48: =(O48+P48)*Assumptions!$B$61/(1-Assumptions!$B$61)
A49: 46 | B49: =EDATE(Assumptions!$B$4,45) | C49: =INT((A49-1)/12)+1 | D49: =IF(C49=1,Assumptions!$B$6,IF(C49=2,Assumptions!$B$7,IF(C49=3,Assumptions!$B$8,IF(C49=4,Assumptions!$B$9,Assumptions!$B$10)))) | E49: =ROUND(F48*Assumptions!$B$11,0) | F49: =F48+D49-E49 | G49: =ROUND(F49*Assumptions!$B$14*(365/12/7),0) | H49: =ROUND(G49*Assumptions!$B$15,0) | I49: =AO49*(1-Assumptions!$B$61) | J49: =M48 | K49: =IFERROR(J49/Assumptions!$B$17,0) | L49: =J49*Assumptions!$B$20/12 | M49: =MAX(J49+I49-K49-L49,0) | N49: =(J49+M49)/2 | O49: =N49*Assumptions!$B$18/12 | P49: =I49*Assumptions!$B$19 | Q49: =O49+P49 | R49: =Assumptions!$B$33*(1+Assumptions!$B$34)^(C49-1)/12 | S49: =L49 | T49: =Q49-R49-S49-AP49 | U49: =MIN(AE49,M49*Assumptions!$B$24/(1+Assumptions!$B$24)) | V49: =((U49+U48)/2)*Assumptions!$B$23/12 | W49: =T49-V49+AJ49 | X49: =X48+W49 | Y49: =MAX(M49-U49,0) | Z49: =R49*Assumptions!$B$25 | AA49: =Y49+Z49 | AB49: =MAX(AB48,AA49) | AC49: 0 | AD49: =AK49+AC49 | AE49: =IF(SUM($H$4:H49)<Assumptions!$B$57,0,MAX(MAX(Assumptions!$B$44,AE48),IF(M49*Assumptions!$B$24/(1+Assumptions!$B$24)>MAX(Assumptions!$B$44,AE48)*Assumptions!$B$53,M49*Assumptions!$B$24/(1+Assumptions!$B$24)/Assumptions!$B$54,MAX(Assumptions!$B$44,AE48)))) | AF49: =U49-U48 | AG49: =IFERROR(U49/AE49,0) | AH49: =MAX(0,AE49-AE48) | AI49: =MAX(AD48-Z49,0) | AJ49: =AI49*Assumptions!$B$46/12 | AK49: =AD48+Q49-R49-I49+K49+AF49-V49+AJ49-AP49 | AL49: =TRIM(IF(AH49>0,"Increase warehouse facility to $"&TEXT(AE49,"#,##0")&" (from $"&TEXT(AE48,"#,##0")&"). ","")&IF(AC49>0,"Raise ~$"&TEXT(AC49,"#,##0")&" of equity — annual raise, funds the next 12 months.","")) | AM49: =Q49-R49-I49+K49+AF49-V49-AP49 | AN49: =SUM($H$4:H49) | AO49: =H49*Assumptions!$B$16 | AP49: =MAX(AO49*Assumptions!$B$62,Assumptions!$B$63)+Assumptions!$B$64/12 | AQ49: =(O49+P49)*Assumptions!$B$61/(1-Assumptions!$B$61)
A50: 47 | B50: =EDATE(Assumptions!$B$4,46) | C50: =INT((A50-1)/12)+1 | D50: =IF(C50=1,Assumptions!$B$6,IF(C50=2,Assumptions!$B$7,IF(C50=3,Assumptions!$B$8,IF(C50=4,Assumptions!$B$9,Assumptions!$B$10)))) | E50: =ROUND(F49*Assumptions!$B$11,0) | F50: =F49+D50-E50 | G50: =ROUND(F50*Assumptions!$B$14*(365/12/7),0) | H50: =ROUND(G50*Assumptions!$B$15,0) | I50: =AO50*(1-Assumptions!$B$61) | J50: =M49 | K50: =IFERROR(J50/Assumptions!$B$17,0) | L50: =J50*Assumptions!$B$20/12 | M50: =MAX(J50+I50-K50-L50,0) | N50: =(J50+M50)/2 | O50: =N50*Assumptions!$B$18/12 | P50: =I50*Assumptions!$B$19 | Q50: =O50+P50 | R50: =Assumptions!$B$33*(1+Assumptions!$B$34)^(C50-1)/12 | S50: =L50 | T50: =Q50-R50-S50-AP50 | U50: =MIN(AE50,M50*Assumptions!$B$24/(1+Assumptions!$B$24)) | V50: =((U50+U49)/2)*Assumptions!$B$23/12 | W50: =T50-V50+AJ50 | X50: =X49+W50 | Y50: =MAX(M50-U50,0) | Z50: =R50*Assumptions!$B$25 | AA50: =Y50+Z50 | AB50: =MAX(AB49,AA50) | AC50: 0 | AD50: =AK50+AC50 | AE50: =IF(SUM($H$4:H50)<Assumptions!$B$57,0,MAX(MAX(Assumptions!$B$44,AE49),IF(M50*Assumptions!$B$24/(1+Assumptions!$B$24)>MAX(Assumptions!$B$44,AE49)*Assumptions!$B$53,M50*Assumptions!$B$24/(1+Assumptions!$B$24)/Assumptions!$B$54,MAX(Assumptions!$B$44,AE49)))) | AF50: =U50-U49 | AG50: =IFERROR(U50/AE50,0) | AH50: =MAX(0,AE50-AE49) | AI50: =MAX(AD49-Z50,0) | AJ50: =AI50*Assumptions!$B$46/12 | AK50: =AD49+Q50-R50-I50+K50+AF50-V50+AJ50-AP50 | AL50: =TRIM(IF(AH50>0,"Increase warehouse facility to $"&TEXT(AE50,"#,##0")&" (from $"&TEXT(AE49,"#,##0")&"). ","")&IF(AC50>0,"Raise ~$"&TEXT(AC50,"#,##0")&" of equity — annual raise, funds the next 12 months.","")) | AM50: =Q50-R50-I50+K50+AF50-V50-AP50 | AN50: =SUM($H$4:H50) | AO50: =H50*Assumptions!$B$16 | AP50: =MAX(AO50*Assumptions!$B$62,Assumptions!$B$63)+Assumptions!$B$64/12 | AQ50: =(O50+P50)*Assumptions!$B$61/(1-Assumptions!$B$61)
A51: 48 | B51: =EDATE(Assumptions!$B$4,47) | C51: =INT((A51-1)/12)+1 | D51: =IF(C51=1,Assumptions!$B$6,IF(C51=2,Assumptions!$B$7,IF(C51=3,Assumptions!$B$8,IF(C51=4,Assumptions!$B$9,Assumptions!$B$10)))) | E51: =ROUND(F50*Assumptions!$B$11,0) | F51: =F50+D51-E51 | G51: =ROUND(F51*Assumptions!$B$14*(365/12/7),0) | H51: =ROUND(G51*Assumptions!$B$15,0) | I51: =AO51*(1-Assumptions!$B$61) | J51: =M50 | K51: =IFERROR(J51/Assumptions!$B$17,0) | L51: =J51*Assumptions!$B$20/12 | M51: =MAX(J51+I51-K51-L51,0) | N51: =(J51+M51)/2 | O51: =N51*Assumptions!$B$18/12 | P51: =I51*Assumptions!$B$19 | Q51: =O51+P51 | R51: =Assumptions!$B$33*(1+Assumptions!$B$34)^(C51-1)/12 | S51: =L51 | T51: =Q51-R51-S51-AP51 | U51: =MIN(AE51,M51*Assumptions!$B$24/(1+Assumptions!$B$24)) | V51: =((U51+U50)/2)*Assumptions!$B$23/12 | W51: =T51-V51+AJ51 | X51: =X50+W51 | Y51: =MAX(M51-U51,0) | Z51: =R51*Assumptions!$B$25 | AA51: =Y51+Z51 | AB51: =MAX(AB50,AA51) | AC51: 0 | AD51: =AK51+AC51 | AE51: =IF(SUM($H$4:H51)<Assumptions!$B$57,0,MAX(MAX(Assumptions!$B$44,AE50),IF(M51*Assumptions!$B$24/(1+Assumptions!$B$24)>MAX(Assumptions!$B$44,AE50)*Assumptions!$B$53,M51*Assumptions!$B$24/(1+Assumptions!$B$24)/Assumptions!$B$54,MAX(Assumptions!$B$44,AE50)))) | AF51: =U51-U50 | AG51: =IFERROR(U51/AE51,0) | AH51: =MAX(0,AE51-AE50) | AI51: =MAX(AD50-Z51,0) | AJ51: =AI51*Assumptions!$B$46/12 | AK51: =AD50+Q51-R51-I51+K51+AF51-V51+AJ51-AP51 | AL51: =TRIM(IF(AH51>0,"Increase warehouse facility to $"&TEXT(AE51,"#,##0")&" (from $"&TEXT(AE50,"#,##0")&"). ","")&IF(AC51>0,"Raise ~$"&TEXT(AC51,"#,##0")&" of equity — annual raise, funds the next 12 months.","")) | AM51: =Q51-R51-I51+K51+AF51-V51-AP51 | AN51: =SUM($H$4:H51) | AO51: =H51*Assumptions!$B$16 | AP51: =MAX(AO51*Assumptions!$B$62,Assumptions!$B$63)+Assumptions!$B$64/12 | AQ51: =(O51+P51)*Assumptions!$B$61/(1-Assumptions!$B$61)
A52: 49 | B52: =EDATE(Assumptions!$B$4,48) | C52: =INT((A52-1)/12)+1 | D52: =IF(C52=1,Assumptions!$B$6,IF(C52=2,Assumptions!$B$7,IF(C52=3,Assumptions!$B$8,IF(C52=4,Assumptions!$B$9,Assumptions!$B$10)))) | E52: =ROUND(F51*Assumptions!$B$11,0) | F52: =F51+D52-E52 | G52: =ROUND(F52*Assumptions!$B$14*(365/12/7),0) | H52: =ROUND(G52*Assumptions!$B$15,0) | I52: =AO52*(1-Assumptions!$B$61) | J52: =M51 | K52: =IFERROR(J52/Assumptions!$B$17,0) | L52: =J52*Assumptions!$B$20/12 | M52: =MAX(J52+I52-K52-L52,0) | N52: =(J52+M52)/2 | O52: =N52*Assumptions!$B$18/12 | P52: =I52*Assumptions!$B$19 | Q52: =O52+P52 | R52: =Assumptions!$B$33*(1+Assumptions!$B$34)^(C52-1)/12 | S52: =L52 | T52: =Q52-R52-S52-AP52 | U52: =MIN(AE52,M52*Assumptions!$B$24/(1+Assumptions!$B$24)) | V52: =((U52+U51)/2)*Assumptions!$B$23/12 | W52: =T52-V52+AJ52 | X52: =X51+W52 | Y52: =MAX(M52-U52,0) | Z52: =R52*Assumptions!$B$25 | AA52: =Y52+Z52 | AB52: =MAX(AB51,AA52) | AC52: =MAX(0,MAX(Z52-AD51-AM52,Z53-AD51-SUM(AM52:AM53),Z54-AD51-SUM(AM52:AM54),Z55-AD51-SUM(AM52:AM55),Z56-AD51-SUM(AM52:AM56),Z57-AD51-SUM(AM52:AM57),Z58-AD51-SUM(AM52:AM58),Z59-AD51-SUM(AM52:AM59),Z60-AD51-SUM(AM52:AM60),Z61-AD51-SUM(AM52:AM61),Z62-AD51-SUM(AM52:AM62),Z63-AD51-SUM(AM52:AM63))) | AD52: =AK52+AC52 | AE52: =IF(SUM($H$4:H52)<Assumptions!$B$57,0,MAX(MAX(Assumptions!$B$44,AE51),IF(M52*Assumptions!$B$24/(1+Assumptions!$B$24)>MAX(Assumptions!$B$44,AE51)*Assumptions!$B$53,M52*Assumptions!$B$24/(1+Assumptions!$B$24)/Assumptions!$B$54,MAX(Assumptions!$B$44,AE51)))) | AF52: =U52-U51 | AG52: =IFERROR(U52/AE52,0) | AH52: =MAX(0,AE52-AE51) | AI52: =MAX(AD51-Z52,0) | AJ52: =AI52*Assumptions!$B$46/12 | AK52: =AD51+Q52-R52-I52+K52+AF52-V52+AJ52-AP52 | AL52: =TRIM(IF(AH52>0,"Increase warehouse facility to $"&TEXT(AE52,"#,##0")&" (from $"&TEXT(AE51,"#,##0")&"). ","")&IF(AC52>0,"Raise ~$"&TEXT(AC52,"#,##0")&" of equity — annual raise, funds the next 12 months.","")) | AM52: =Q52-R52-I52+K52+AF52-V52-AP52 | AN52: =SUM($H$4:H52) | AO52: =H52*Assumptions!$B$16 | AP52: =MAX(AO52*Assumptions!$B$62,Assumptions!$B$63)+Assumptions!$B$64/12 | AQ52: =(O52+P52)*Assumptions!$B$61/(1-Assumptions!$B$61)
A53: 50 | B53: =EDATE(Assumptions!$B$4,49) | C53: =INT((A53-1)/12)+1 | D53: =IF(C53=1,Assumptions!$B$6,IF(C53=2,Assumptions!$B$7,IF(C53=3,Assumptions!$B$8,IF(C53=4,Assumptions!$B$9,Assumptions!$B$10)))) | E53: =ROUND(F52*Assumptions!$B$11,0) | F53: =F52+D53-E53 | G53: =ROUND(F53*Assumptions!$B$14*(365/12/7),0) | H53: =ROUND(G53*Assumptions!$B$15,0) | I53: =AO53*(1-Assumptions!$B$61) | J53: =M52 | K53: =IFERROR(J53/Assumptions!$B$17,0) | L53: =J53*Assumptions!$B$20/12 | M53: =MAX(J53+I53-K53-L53,0) | N53: =(J53+M53)/2 | O53: =N53*Assumptions!$B$18/12 | P53: =I53*Assumptions!$B$19 | Q53: =O53+P53 | R53: =Assumptions!$B$33*(1+Assumptions!$B$34)^(C53-1)/12 | S53: =L53 | T53: =Q53-R53-S53-AP53 | U53: =MIN(AE53,M53*Assumptions!$B$24/(1+Assumptions!$B$24)) | V53: =((U53+U52)/2)*Assumptions!$B$23/12 | W53: =T53-V53+AJ53 | X53: =X52+W53 | Y53: =MAX(M53-U53,0) | Z53: =R53*Assumptions!$B$25 | AA53: =Y53+Z53 | AB53: =MAX(AB52,AA53) | AC53: 0 | AD53: =AK53+AC53 | AE53: =IF(SUM($H$4:H53)<Assumptions!$B$57,0,MAX(MAX(Assumptions!$B$44,AE52),IF(M53*Assumptions!$B$24/(1+Assumptions!$B$24)>MAX(Assumptions!$B$44,AE52)*Assumptions!$B$53,M53*Assumptions!$B$24/(1+Assumptions!$B$24)/Assumptions!$B$54,MAX(Assumptions!$B$44,AE52)))) | AF53: =U53-U52 | AG53: =IFERROR(U53/AE53,0) | AH53: =MAX(0,AE53-AE52) | AI53: =MAX(AD52-Z53,0) | AJ53: =AI53*Assumptions!$B$46/12 | AK53: =AD52+Q53-R53-I53+K53+AF53-V53+AJ53-AP53 | AL53: =TRIM(IF(AH53>0,"Increase warehouse facility to $"&TEXT(AE53,"#,##0")&" (from $"&TEXT(AE52,"#,##0")&"). ","")&IF(AC53>0,"Raise ~$"&TEXT(AC53,"#,##0")&" of equity — annual raise, funds the next 12 months.","")) | AM53: =Q53-R53-I53+K53+AF53-V53-AP53 | AN53: =SUM($H$4:H53) | AO53: =H53*Assumptions!$B$16 | AP53: =MAX(AO53*Assumptions!$B$62,Assumptions!$B$63)+Assumptions!$B$64/12 | AQ53: =(O53+P53)*Assumptions!$B$61/(1-Assumptions!$B$61)
A54: 51 | B54: =EDATE(Assumptions!$B$4,50) | C54: =INT((A54-1)/12)+1 | D54: =IF(C54=1,Assumptions!$B$6,IF(C54=2,Assumptions!$B$7,IF(C54=3,Assumptions!$B$8,IF(C54=4,Assumptions!$B$9,Assumptions!$B$10)))) | E54: =ROUND(F53*Assumptions!$B$11,0) | F54: =F53+D54-E54 | G54: =ROUND(F54*Assumptions!$B$14*(365/12/7),0) | H54: =ROUND(G54*Assumptions!$B$15,0) | I54: =AO54*(1-Assumptions!$B$61) | J54: =M53 | K54: =IFERROR(J54/Assumptions!$B$17,0) | L54: =J54*Assumptions!$B$20/12 | M54: =MAX(J54+I54-K54-L54,0) | N54: =(J54+M54)/2 | O54: =N54*Assumptions!$B$18/12 | P54: =I54*Assumptions!$B$19 | Q54: =O54+P54 | R54: =Assumptions!$B$33*(1+Assumptions!$B$34)^(C54-1)/12 | S54: =L54 | T54: =Q54-R54-S54-AP54 | U54: =MIN(AE54,M54*Assumptions!$B$24/(1+Assumptions!$B$24)) | V54: =((U54+U53)/2)*Assumptions!$B$23/12 | W54: =T54-V54+AJ54 | X54: =X53+W54 | Y54: =MAX(M54-U54,0) | Z54: =R54*Assumptions!$B$25 | AA54: =Y54+Z54 | AB54: =MAX(AB53,AA54) | AC54: 0 | AD54: =AK54+AC54 | AE54: =IF(SUM($H$4:H54)<Assumptions!$B$57,0,MAX(MAX(Assumptions!$B$44,AE53),IF(M54*Assumptions!$B$24/(1+Assumptions!$B$24)>MAX(Assumptions!$B$44,AE53)*Assumptions!$B$53,M54*Assumptions!$B$24/(1+Assumptions!$B$24)/Assumptions!$B$54,MAX(Assumptions!$B$44,AE53)))) | AF54: =U54-U53 | AG54: =IFERROR(U54/AE54,0) | AH54: =MAX(0,AE54-AE53) | AI54: =MAX(AD53-Z54,0) | AJ54: =AI54*Assumptions!$B$46/12 | AK54: =AD53+Q54-R54-I54+K54+AF54-V54+AJ54-AP54 | AL54: =TRIM(IF(AH54>0,"Increase warehouse facility to $"&TEXT(AE54,"#,##0")&" (from $"&TEXT(AE53,"#,##0")&"). ","")&IF(AC54>0,"Raise ~$"&TEXT(AC54,"#,##0")&" of equity — annual raise, funds the next 12 months.","")) | AM54: =Q54-R54-I54+K54+AF54-V54-AP54 | AN54: =SUM($H$4:H54) | AO54: =H54*Assumptions!$B$16 | AP54: =MAX(AO54*Assumptions!$B$62,Assumptions!$B$63)+Assumptions!$B$64/12 | AQ54: =(O54+P54)*Assumptions!$B$61/(1-Assumptions!$B$61)
A55: 52 | B55: =EDATE(Assumptions!$B$4,51) | C55: =INT((A55-1)/12)+1 | D55: =IF(C55=1,Assumptions!$B$6,IF(C55=2,Assumptions!$B$7,IF(C55=3,Assumptions!$B$8,IF(C55=4,Assumptions!$B$9,Assumptions!$B$10)))) | E55: =ROUND(F54*Assumptions!$B$11,0) | F55: =F54+D55-E55 | G55: =ROUND(F55*Assumptions!$B$14*(365/12/7),0) | H55: =ROUND(G55*Assumptions!$B$15,0) | I55: =AO55*(1-Assumptions!$B$61) | J55: =M54 | K55: =IFERROR(J55/Assumptions!$B$17,0) | L55: =J55*Assumptions!$B$20/12 | M55: =MAX(J55+I55-K55-L55,0) | N55: =(J55+M55)/2 | O55: =N55*Assumptions!$B$18/12 | P55: =I55*Assumptions!$B$19 | Q55: =O55+P55 | R55: =Assumptions!$B$33*(1+Assumptions!$B$34)^(C55-1)/12 | S55: =L55 | T55: =Q55-R55-S55-AP55 | U55: =MIN(AE55,M55*Assumptions!$B$24/(1+Assumptions!$B$24)) | V55: =((U55+U54)/2)*Assumptions!$B$23/12 | W55: =T55-V55+AJ55 | X55: =X54+W55 | Y55: =MAX(M55-U55,0) | Z55: =R55*Assumptions!$B$25 | AA55: =Y55+Z55 | AB55: =MAX(AB54,AA55) | AC55: 0 | AD55: =AK55+AC55 | AE55: =IF(SUM($H$4:H55)<Assumptions!$B$57,0,MAX(MAX(Assumptions!$B$44,AE54),IF(M55*Assumptions!$B$24/(1+Assumptions!$B$24)>MAX(Assumptions!$B$44,AE54)*Assumptions!$B$53,M55*Assumptions!$B$24/(1+Assumptions!$B$24)/Assumptions!$B$54,MAX(Assumptions!$B$44,AE54)))) | AF55: =U55-U54 | AG55: =IFERROR(U55/AE55,0) | AH55: =MAX(0,AE55-AE54) | AI55: =MAX(AD54-Z55,0) | AJ55: =AI55*Assumptions!$B$46/12 | AK55: =AD54+Q55-R55-I55+K55+AF55-V55+AJ55-AP55 | AL55: =TRIM(IF(AH55>0,"Increase warehouse facility to $"&TEXT(AE55,"#,##0")&" (from $"&TEXT(AE54,"#,##0")&"). ","")&IF(AC55>0,"Raise ~$"&TEXT(AC55,"#,##0")&" of equity — annual raise, funds the next 12 months.","")) | AM55: =Q55-R55-I55+K55+AF55-V55-AP55 | AN55: =SUM($H$4:H55) | AO55: =H55*Assumptions!$B$16 | AP55: =MAX(AO55*Assumptions!$B$62,Assumptions!$B$63)+Assumptions!$B$64/12 | AQ55: =(O55+P55)*Assumptions!$B$61/(1-Assumptions!$B$61)
A56: 53 | B56: =EDATE(Assumptions!$B$4,52) | C56: =INT((A56-1)/12)+1 | D56: =IF(C56=1,Assumptions!$B$6,IF(C56=2,Assumptions!$B$7,IF(C56=3,Assumptions!$B$8,IF(C56=4,Assumptions!$B$9,Assumptions!$B$10)))) | E56: =ROUND(F55*Assumptions!$B$11,0) | F56: =F55+D56-E56 | G56: =ROUND(F56*Assumptions!$B$14*(365/12/7),0) | H56: =ROUND(G56*Assumptions!$B$15,0) | I56: =AO56*(1-Assumptions!$B$61) | J56: =M55 | K56: =IFERROR(J56/Assumptions!$B$17,0) | L56: =J56*Assumptions!$B$20/12 | M56: =MAX(J56+I56-K56-L56,0) | N56: =(J56+M56)/2 | O56: =N56*Assumptions!$B$18/12 | P56: =I56*Assumptions!$B$19 | Q56: =O56+P56 | R56: =Assumptions!$B$33*(1+Assumptions!$B$34)^(C56-1)/12 | S56: =L56 | T56: =Q56-R56-S56-AP56 | U56: =MIN(AE56,M56*Assumptions!$B$24/(1+Assumptions!$B$24)) | V56: =((U56+U55)/2)*Assumptions!$B$23/12 | W56: =T56-V56+AJ56 | X56: =X55+W56 | Y56: =MAX(M56-U56,0) | Z56: =R56*Assumptions!$B$25 | AA56: =Y56+Z56 | AB56: =MAX(AB55,AA56) | AC56: 0 | AD56: =AK56+AC56 | AE56: =IF(SUM($H$4:H56)<Assumptions!$B$57,0,MAX(MAX(Assumptions!$B$44,AE55),IF(M56*Assumptions!$B$24/(1+Assumptions!$B$24)>MAX(Assumptions!$B$44,AE55)*Assumptions!$B$53,M56*Assumptions!$B$24/(1+Assumptions!$B$24)/Assumptions!$B$54,MAX(Assumptions!$B$44,AE55)))) | AF56: =U56-U55 | AG56: =IFERROR(U56/AE56,0) | AH56: =MAX(0,AE56-AE55) | AI56: =MAX(AD55-Z56,0) | AJ56: =AI56*Assumptions!$B$46/12 | AK56: =AD55+Q56-R56-I56+K56+AF56-V56+AJ56-AP56 | AL56: =TRIM(IF(AH56>0,"Increase warehouse facility to $"&TEXT(AE56,"#,##0")&" (from $"&TEXT(AE55,"#,##0")&"). ","")&IF(AC56>0,"Raise ~$"&TEXT(AC56,"#,##0")&" of equity — annual raise, funds the next 12 months.","")) | AM56: =Q56-R56-I56+K56+AF56-V56-AP56 | AN56: =SUM($H$4:H56) | AO56: =H56*Assumptions!$B$16 | AP56: =MAX(AO56*Assumptions!$B$62,Assumptions!$B$63)+Assumptions!$B$64/12 | AQ56: =(O56+P56)*Assumptions!$B$61/(1-Assumptions!$B$61)
A57: 54 | B57: =EDATE(Assumptions!$B$4,53) | C57: =INT((A57-1)/12)+1 | D57: =IF(C57=1,Assumptions!$B$6,IF(C57=2,Assumptions!$B$7,IF(C57=3,Assumptions!$B$8,IF(C57=4,Assumptions!$B$9,Assumptions!$B$10)))) | E57: =ROUND(F56*Assumptions!$B$11,0) | F57: =F56+D57-E57 | G57: =ROUND(F57*Assumptions!$B$14*(365/12/7),0) | H57: =ROUND(G57*Assumptions!$B$15,0) | I57: =AO57*(1-Assumptions!$B$61) | J57: =M56 | K57: =IFERROR(J57/Assumptions!$B$17,0) | L57: =J57*Assumptions!$B$20/12 | M57: =MAX(J57+I57-K57-L57,0) | N57: =(J57+M57)/2 | O57: =N57*Assumptions!$B$18/12 | P57: =I57*Assumptions!$B$19 | Q57: =O57+P57 | R57: =Assumptions!$B$33*(1+Assumptions!$B$34)^(C57-1)/12 | S57: =L57 | T57: =Q57-R57-S57-AP57 | U57: =MIN(AE57,M57*Assumptions!$B$24/(1+Assumptions!$B$24)) | V57: =((U57+U56)/2)*Assumptions!$B$23/12 | W57: =T57-V57+AJ57 | X57: =X56+W57 | Y57: =MAX(M57-U57,0) | Z57: =R57*Assumptions!$B$25 | AA57: =Y57+Z57 | AB57: =MAX(AB56,AA57) | AC57: 0 | AD57: =AK57+AC57 | AE57: =IF(SUM($H$4:H57)<Assumptions!$B$57,0,MAX(MAX(Assumptions!$B$44,AE56),IF(M57*Assumptions!$B$24/(1+Assumptions!$B$24)>MAX(Assumptions!$B$44,AE56)*Assumptions!$B$53,M57*Assumptions!$B$24/(1+Assumptions!$B$24)/Assumptions!$B$54,MAX(Assumptions!$B$44,AE56)))) | AF57: =U57-U56 | AG57: =IFERROR(U57/AE57,0) | AH57: =MAX(0,AE57-AE56) | AI57: =MAX(AD56-Z57,0) | AJ57: =AI57*Assumptions!$B$46/12 | AK57: =AD56+Q57-R57-I57+K57+AF57-V57+AJ57-AP57 | AL57: =TRIM(IF(AH57>0,"Increase warehouse facility to $"&TEXT(AE57,"#,##0")&" (from $"&TEXT(AE56,"#,##0")&"). ","")&IF(AC57>0,"Raise ~$"&TEXT(AC57,"#,##0")&" of equity — annual raise, funds the next 12 months.","")) | AM57: =Q57-R57-I57+K57+AF57-V57-AP57 | AN57: =SUM($H$4:H57) | AO57: =H57*Assumptions!$B$16 | AP57: =MAX(AO57*Assumptions!$B$62,Assumptions!$B$63)+Assumptions!$B$64/12 | AQ57: =(O57+P57)*Assumptions!$B$61/(1-Assumptions!$B$61)
A58: 55 | B58: =EDATE(Assumptions!$B$4,54) | C58: =INT((A58-1)/12)+1 | D58: =IF(C58=1,Assumptions!$B$6,IF(C58=2,Assumptions!$B$7,IF(C58=3,Assumptions!$B$8,IF(C58=4,Assumptions!$B$9,Assumptions!$B$10)))) | E58: =ROUND(F57*Assumptions!$B$11,0) | F58: =F57+D58-E58 | G58: =ROUND(F58*Assumptions!$B$14*(365/12/7),0) | H58: =ROUND(G58*Assumptions!$B$15,0) | I58: =AO58*(1-Assumptions!$B$61) | J58: =M57 | K58: =IFERROR(J58/Assumptions!$B$17,0) | L58: =J58*Assumptions!$B$20/12 | M58: =MAX(J58+I58-K58-L58,0) | N58: =(J58+M58)/2 | O58: =N58*Assumptions!$B$18/12 | P58: =I58*Assumptions!$B$19 | Q58: =O58+P58 | R58: =Assumptions!$B$33*(1+Assumptions!$B$34)^(C58-1)/12 | S58: =L58 | T58: =Q58-R58-S58-AP58 | U58: =MIN(AE58,M58*Assumptions!$B$24/(1+Assumptions!$B$24)) | V58: =((U58+U57)/2)*Assumptions!$B$23/12 | W58: =T58-V58+AJ58 | X58: =X57+W58 | Y58: =MAX(M58-U58,0) | Z58: =R58*Assumptions!$B$25 | AA58: =Y58+Z58 | AB58: =MAX(AB57,AA58) | AC58: 0 | AD58: =AK58+AC58 | AE58: =IF(SUM($H$4:H58)<Assumptions!$B$57,0,MAX(MAX(Assumptions!$B$44,AE57),IF(M58*Assumptions!$B$24/(1+Assumptions!$B$24)>MAX(Assumptions!$B$44,AE57)*Assumptions!$B$53,M58*Assumptions!$B$24/(1+Assumptions!$B$24)/Assumptions!$B$54,MAX(Assumptions!$B$44,AE57)))) | AF58: =U58-U57 | AG58: =IFERROR(U58/AE58,0) | AH58: =MAX(0,AE58-AE57) | AI58: =MAX(AD57-Z58,0) | AJ58: =AI58*Assumptions!$B$46/12 | AK58: =AD57+Q58-R58-I58+K58+AF58-V58+AJ58-AP58 | AL58: =TRIM(IF(AH58>0,"Increase warehouse facility to $"&TEXT(AE58,"#,##0")&" (from $"&TEXT(AE57,"#,##0")&"). ","")&IF(AC58>0,"Raise ~$"&TEXT(AC58,"#,##0")&" of equity — annual raise, funds the next 12 months.","")) | AM58: =Q58-R58-I58+K58+AF58-V58-AP58 | AN58: =SUM($H$4:H58) | AO58: =H58*Assumptions!$B$16 | AP58: =MAX(AO58*Assumptions!$B$62,Assumptions!$B$63)+Assumptions!$B$64/12 | AQ58: =(O58+P58)*Assumptions!$B$61/(1-Assumptions!$B$61)
A59: 56 | B59: =EDATE(Assumptions!$B$4,55) | C59: =INT((A59-1)/12)+1 | D59: =IF(C59=1,Assumptions!$B$6,IF(C59=2,Assumptions!$B$7,IF(C59=3,Assumptions!$B$8,IF(C59=4,Assumptions!$B$9,Assumptions!$B$10)))) | E59: =ROUND(F58*Assumptions!$B$11,0) | F59: =F58+D59-E59 | G59: =ROUND(F59*Assumptions!$B$14*(365/12/7),0) | H59: =ROUND(G59*Assumptions!$B$15,0) | I59: =AO59*(1-Assumptions!$B$61) | J59: =M58 | K59: =IFERROR(J59/Assumptions!$B$17,0) | L59: =J59*Assumptions!$B$20/12 | M59: =MAX(J59+I59-K59-L59,0) | N59: =(J59+M59)/2 | O59: =N59*Assumptions!$B$18/12 | P59: =I59*Assumptions!$B$19 | Q59: =O59+P59 | R59: =Assumptions!$B$33*(1+Assumptions!$B$34)^(C59-1)/12 | S59: =L59 | T59: =Q59-R59-S59-AP59 | U59: =MIN(AE59,M59*Assumptions!$B$24/(1+Assumptions!$B$24)) | V59: =((U59+U58)/2)*Assumptions!$B$23/12 | W59: =T59-V59+AJ59 | X59: =X58+W59 | Y59: =MAX(M59-U59,0) | Z59: =R59*Assumptions!$B$25 | AA59: =Y59+Z59 | AB59: =MAX(AB58,AA59) | AC59: 0 | AD59: =AK59+AC59 | AE59: =IF(SUM($H$4:H59)<Assumptions!$B$57,0,MAX(MAX(Assumptions!$B$44,AE58),IF(M59*Assumptions!$B$24/(1+Assumptions!$B$24)>MAX(Assumptions!$B$44,AE58)*Assumptions!$B$53,M59*Assumptions!$B$24/(1+Assumptions!$B$24)/Assumptions!$B$54,MAX(Assumptions!$B$44,AE58)))) | AF59: =U59-U58 | AG59: =IFERROR(U59/AE59,0) | AH59: =MAX(0,AE59-AE58) | AI59: =MAX(AD58-Z59,0) | AJ59: =AI59*Assumptions!$B$46/12 | AK59: =AD58+Q59-R59-I59+K59+AF59-V59+AJ59-AP59 | AL59: =TRIM(IF(AH59>0,"Increase warehouse facility to $"&TEXT(AE59,"#,##0")&" (from $"&TEXT(AE58,"#,##0")&"). ","")&IF(AC59>0,"Raise ~$"&TEXT(AC59,"#,##0")&" of equity — annual raise, funds the next 12 months.","")) | AM59: =Q59-R59-I59+K59+AF59-V59-AP59 | AN59: =SUM($H$4:H59) | AO59: =H59*Assumptions!$B$16 | AP59: =MAX(AO59*Assumptions!$B$62,Assumptions!$B$63)+Assumptions!$B$64/12 | AQ59: =(O59+P59)*Assumptions!$B$61/(1-Assumptions!$B$61)
A60: 57 | B60: =EDATE(Assumptions!$B$4,56) | C60: =INT((A60-1)/12)+1 | D60: =IF(C60=1,Assumptions!$B$6,IF(C60=2,Assumptions!$B$7,IF(C60=3,Assumptions!$B$8,IF(C60=4,Assumptions!$B$9,Assumptions!$B$10)))) | E60: =ROUND(F59*Assumptions!$B$11,0) | F60: =F59+D60-E60 | G60: =ROUND(F60*Assumptions!$B$14*(365/12/7),0) | H60: =ROUND(G60*Assumptions!$B$15,0) | I60: =AO60*(1-Assumptions!$B$61) | J60: =M59 | K60: =IFERROR(J60/Assumptions!$B$17,0) | L60: =J60*Assumptions!$B$20/12 | M60: =MAX(J60+I60-K60-L60,0) | N60: =(J60+M60)/2 | O60: =N60*Assumptions!$B$18/12 | P60: =I60*Assumptions!$B$19 | Q60: =O60+P60 | R60: =Assumptions!$B$33*(1+Assumptions!$B$34)^(C60-1)/12 | S60: =L60 | T60: =Q60-R60-S60-AP60 | U60: =MIN(AE60,M60*Assumptions!$B$24/(1+Assumptions!$B$24)) | V60: =((U60+U59)/2)*Assumptions!$B$23/12 | W60: =T60-V60+AJ60 | X60: =X59+W60 | Y60: =MAX(M60-U60,0) | Z60: =R60*Assumptions!$B$25 | AA60: =Y60+Z60 | AB60: =MAX(AB59,AA60) | AC60: 0 | AD60: =AK60+AC60 | AE60: =IF(SUM($H$4:H60)<Assumptions!$B$57,0,MAX(MAX(Assumptions!$B$44,AE59),IF(M60*Assumptions!$B$24/(1+Assumptions!$B$24)>MAX(Assumptions!$B$44,AE59)*Assumptions!$B$53,M60*Assumptions!$B$24/(1+Assumptions!$B$24)/Assumptions!$B$54,MAX(Assumptions!$B$44,AE59)))) | AF60: =U60-U59 | AG60: =IFERROR(U60/AE60,0) | AH60: =MAX(0,AE60-AE59) | AI60: =MAX(AD59-Z60,0) | AJ60: =AI60*Assumptions!$B$46/12 | AK60: =AD59+Q60-R60-I60+K60+AF60-V60+AJ60-AP60 | AL60: =TRIM(IF(AH60>0,"Increase warehouse facility to $"&TEXT(AE60,"#,##0")&" (from $"&TEXT(AE59,"#,##0")&"). ","")&IF(AC60>0,"Raise ~$"&TEXT(AC60,"#,##0")&" of equity — annual raise, funds the next 12 months.","")) | AM60: =Q60-R60-I60+K60+AF60-V60-AP60 | AN60: =SUM($H$4:H60) | AO60: =H60*Assumptions!$B$16 | AP60: =MAX(AO60*Assumptions!$B$62,Assumptions!$B$63)+Assumptions!$B$64/12 | AQ60: =(O60+P60)*Assumptions!$B$61/(1-Assumptions!$B$61)
A61: 58 | B61: =EDATE(Assumptions!$B$4,57) | C61: =INT((A61-1)/12)+1 | D61: =IF(C61=1,Assumptions!$B$6,IF(C61=2,Assumptions!$B$7,IF(C61=3,Assumptions!$B$8,IF(C61=4,Assumptions!$B$9,Assumptions!$B$10)))) | E61: =ROUND(F60*Assumptions!$B$11,0) | F61: =F60+D61-E61 | G61: =ROUND(F61*Assumptions!$B$14*(365/12/7),0) | H61: =ROUND(G61*Assumptions!$B$15,0) | I61: =AO61*(1-Assumptions!$B$61) | J61: =M60 | K61: =IFERROR(J61/Assumptions!$B$17,0) | L61: =J61*Assumptions!$B$20/12 | M61: =MAX(J61+I61-K61-L61,0) | N61: =(J61+M61)/2 | O61: =N61*Assumptions!$B$18/12 | P61: =I61*Assumptions!$B$19 | Q61: =O61+P61 | R61: =Assumptions!$B$33*(1+Assumptions!$B$34)^(C61-1)/12 | S61: =L61 | T61: =Q61-R61-S61-AP61 | U61: =MIN(AE61,M61*Assumptions!$B$24/(1+Assumptions!$B$24)) | V61: =((U61+U60)/2)*Assumptions!$B$23/12 | W61: =T61-V61+AJ61 | X61: =X60+W61 | Y61: =MAX(M61-U61,0) | Z61: =R61*Assumptions!$B$25 | AA61: =Y61+Z61 | AB61: =MAX(AB60,AA61) | AC61: 0 | AD61: =AK61+AC61 | AE61: =IF(SUM($H$4:H61)<Assumptions!$B$57,0,MAX(MAX(Assumptions!$B$44,AE60),IF(M61*Assumptions!$B$24/(1+Assumptions!$B$24)>MAX(Assumptions!$B$44,AE60)*Assumptions!$B$53,M61*Assumptions!$B$24/(1+Assumptions!$B$24)/Assumptions!$B$54,MAX(Assumptions!$B$44,AE60)))) | AF61: =U61-U60 | AG61: =IFERROR(U61/AE61,0) | AH61: =MAX(0,AE61-AE60) | AI61: =MAX(AD60-Z61,0) | AJ61: =AI61*Assumptions!$B$46/12 | AK61: =AD60+Q61-R61-I61+K61+AF61-V61+AJ61-AP61 | AL61: =TRIM(IF(AH61>0,"Increase warehouse facility to $"&TEXT(AE61,"#,##0")&" (from $"&TEXT(AE60,"#,##0")&"). ","")&IF(AC61>0,"Raise ~$"&TEXT(AC61,"#,##0")&" of equity — annual raise, funds the next 12 months.","")) | AM61: =Q61-R61-I61+K61+AF61-V61-AP61 | AN61: =SUM($H$4:H61) | AO61: =H61*Assumptions!$B$16 | AP61: =MAX(AO61*Assumptions!$B$62,Assumptions!$B$63)+Assumptions!$B$64/12 | AQ61: =(O61+P61)*Assumptions!$B$61/(1-Assumptions!$B$61)
A62: 59 | B62: =EDATE(Assumptions!$B$4,58) | C62: =INT((A62-1)/12)+1 | D62: =IF(C62=1,Assumptions!$B$6,IF(C62=2,Assumptions!$B$7,IF(C62=3,Assumptions!$B$8,IF(C62=4,Assumptions!$B$9,Assumptions!$B$10)))) | E62: =ROUND(F61*Assumptions!$B$11,0) | F62: =F61+D62-E62 | G62: =ROUND(F62*Assumptions!$B$14*(365/12/7),0) | H62: =ROUND(G62*Assumptions!$B$15,0) | I62: =AO62*(1-Assumptions!$B$61) | J62: =M61 | K62: =IFERROR(J62/Assumptions!$B$17,0) | L62: =J62*Assumptions!$B$20/12 | M62: =MAX(J62+I62-K62-L62,0) | N62: =(J62+M62)/2 | O62: =N62*Assumptions!$B$18/12 | P62: =I62*Assumptions!$B$19 | Q62: =O62+P62 | R62: =Assumptions!$B$33*(1+Assumptions!$B$34)^(C62-1)/12 | S62: =L62 | T62: =Q62-R62-S62-AP62 | U62: =MIN(AE62,M62*Assumptions!$B$24/(1+Assumptions!$B$24)) | V62: =((U62+U61)/2)*Assumptions!$B$23/12 | W62: =T62-V62+AJ62 | X62: =X61+W62 | Y62: =MAX(M62-U62,0) | Z62: =R62*Assumptions!$B$25 | AA62: =Y62+Z62 | AB62: =MAX(AB61,AA62) | AC62: 0 | AD62: =AK62+AC62 | AE62: =IF(SUM($H$4:H62)<Assumptions!$B$57,0,MAX(MAX(Assumptions!$B$44,AE61),IF(M62*Assumptions!$B$24/(1+Assumptions!$B$24)>MAX(Assumptions!$B$44,AE61)*Assumptions!$B$53,M62*Assumptions!$B$24/(1+Assumptions!$B$24)/Assumptions!$B$54,MAX(Assumptions!$B$44,AE61)))) | AF62: =U62-U61 | AG62: =IFERROR(U62/AE62,0) | AH62: =MAX(0,AE62-AE61) | AI62: =MAX(AD61-Z62,0) | AJ62: =AI62*Assumptions!$B$46/12 | AK62: =AD61+Q62-R62-I62+K62+AF62-V62+AJ62-AP62 | AL62: =TRIM(IF(AH62>0,"Increase warehouse facility to $"&TEXT(AE62,"#,##0")&" (from $"&TEXT(AE61,"#,##0")&"). ","")&IF(AC62>0,"Raise ~$"&TEXT(AC62,"#,##0")&" of equity — annual raise, funds the next 12 months.","")) | AM62: =Q62-R62-I62+K62+AF62-V62-AP62 | AN62: =SUM($H$4:H62) | AO62: =H62*Assumptions!$B$16 | AP62: =MAX(AO62*Assumptions!$B$62,Assumptions!$B$63)+Assumptions!$B$64/12 | AQ62: =(O62+P62)*Assumptions!$B$61/(1-Assumptions!$B$61)
A63: 60 | B63: =EDATE(Assumptions!$B$4,59) | C63: =INT((A63-1)/12)+1 | D63: =IF(C63=1,Assumptions!$B$6,IF(C63=2,Assumptions!$B$7,IF(C63=3,Assumptions!$B$8,IF(C63=4,Assumptions!$B$9,Assumptions!$B$10)))) | E63: =ROUND(F62*Assumptions!$B$11,0) | F63: =F62+D63-E63 | G63: =ROUND(F63*Assumptions!$B$14*(365/12/7),0) | H63: =ROUND(G63*Assumptions!$B$15,0) | I63: =AO63*(1-Assumptions!$B$61) | J63: =M62 | K63: =IFERROR(J63/Assumptions!$B$17,0) | L63: =J63*Assumptions!$B$20/12 | M63: =MAX(J63+I63-K63-L63,0) | N63: =(J63+M63)/2 | O63: =N63*Assumptions!$B$18/12 | P63: =I63*Assumptions!$B$19 | Q63: =O63+P63 | R63: =Assumptions!$B$33*(1+Assumptions!$B$34)^(C63-1)/12 | S63: =L63 | T63: =Q63-R63-S63-AP63 | U63: =MIN(AE63,M63*Assumptions!$B$24/(1+Assumptions!$B$24)) | V63: =((U63+U62)/2)*Assumptions!$B$23/12 | W63: =T63-V63+AJ63 | X63: =X62+W63 | Y63: =MAX(M63-U63,0) | Z63: =R63*Assumptions!$B$25 | AA63: =Y63+Z63 | AB63: =MAX(AB62,AA63) | AC63: 0 | AD63: =AK63+AC63 | AE63: =IF(SUM($H$4:H63)<Assumptions!$B$57,0,MAX(MAX(Assumptions!$B$44,AE62),IF(M63*Assumptions!$B$24/(1+Assumptions!$B$24)>MAX(Assumptions!$B$44,AE62)*Assumptions!$B$53,M63*Assumptions!$B$24/(1+Assumptions!$B$24)/Assumptions!$B$54,MAX(Assumptions!$B$44,AE62)))) | AF63: =U63-U62 | AG63: =IFERROR(U63/AE63,0) | AH63: =MAX(0,AE63-AE62) | AI63: =MAX(AD62-Z63,0) | AJ63: =AI63*Assumptions!$B$46/12 | AK63: =AD62+Q63-R63-I63+K63+AF63-V63+AJ63-AP63 | AL63: =TRIM(IF(AH63>0,"Increase warehouse facility to $"&TEXT(AE63,"#,##0")&" (from $"&TEXT(AE62,"#,##0")&"). ","")&IF(AC63>0,"Raise ~$"&TEXT(AC63,"#,##0")&" of equity — annual raise, funds the next 12 months.","")) | AM63: =Q63-R63-I63+K63+AF63-V63-AP63 | AN63: =SUM($H$4:H63) | AO63: =H63*Assumptions!$B$16 | AP63: =MAX(AO63*Assumptions!$B$62,Assumptions!$B$63)+Assumptions!$B$64/12 | AQ63: =(O63+P63)*Assumptions!$B$61/(1-Assumptions!$B$61)

Sheet Annual Summary
A1: VetFinance | Annual Summary
A3: Period
A4: Metric | B4: Year 1 | C4: Year 2 | D4: Year 3 | E4: Year 4 | F4: Year 5 | G4: Total / Peak
A5: PRACTICE METRICS
A6: Practices at year end | B6: ='Monthly Model'!F15 | C6: ='Monthly Model'!F27 | D6: ='Monthly Model'!F39 | E6: ='Monthly Model'!F51 | F6: ='Monthly Model'!F63 | G6: =F6
A7: New practices added | B7: =SUMPRODUCT(('Monthly Model'!D4:D63)*('Monthly Model'!C4:C63=1)) | C7: =SUMPRODUCT(('Monthly Model'!D4:D63)*('Monthly Model'!C4:C63=2)) | D7: =SUMPRODUCT(('Monthly Model'!D4:D63)*('Monthly Model'!C4:C63=3)) | E7: =SUMPRODUCT(('Monthly Model'!D4:D63)*('Monthly Model'!C4:C63=4)) | F7: =SUMPRODUCT(('Monthly Model'!D4:D63)*('Monthly Model'!C4:C63=5)) | G7: =SUM(B7:F7)
A9: LOAN VOLUME
A10: Total originations ($) | B10: =SUMPRODUCT(('Monthly Model'!I4:I63)*('Monthly Model'!C4:C63=1)) | C10: =SUMPRODUCT(('Monthly Model'!I4:I63)*('Monthly Model'!C4:C63=2)) | D10: =SUMPRODUCT(('Monthly Model'!I4:I63)*('Monthly Model'!C4:C63=3)) | E10: =SUMPRODUCT(('Monthly Model'!I4:I63)*('Monthly Model'!C4:C63=4)) | F10: =SUMPRODUCT(('Monthly Model'!I4:I63)*('Monthly Model'!C4:C63=5)) | G10: =SUM(B10:F10)
A11: Total loans funded (count) | B11: =SUMPRODUCT(('Monthly Model'!H4:H63)*('Monthly Model'!C4:C63=1)) | C11: =SUMPRODUCT(('Monthly Model'!H4:H63)*('Monthly Model'!C4:C63=2)) | D11: =SUMPRODUCT(('Monthly Model'!H4:H63)*('Monthly Model'!C4:C63=3)) | E11: =SUMPRODUCT(('Monthly Model'!H4:H63)*('Monthly Model'!C4:C63=4)) | F11: =SUMPRODUCT(('Monthly Model'!H4:H63)*('Monthly Model'!C4:C63=5)) | G11: =SUM(B11:F11)
A12: Peak monthly originations ($) | B12: =MAX('Monthly Model'!I4:I15) | C12: =MAX('Monthly Model'!I16:I27) | D12: =MAX('Monthly Model'!I28:I39) | E12: =MAX('Monthly Model'!I40:I51) | F12: =MAX('Monthly Model'!I52:I63) | G12: =MAX(B12:F12)
A14: PORTFOLIO
A15: End-of-year portfolio balance ($) | B15: ='Monthly Model'!M15 | C15: ='Monthly Model'!M27 | D15: ='Monthly Model'!M39 | E15: ='Monthly Model'!M51 | F15: ='Monthly Model'!M63 | G15: =F15
A16: Average portfolio balance ($) | B16: =AVERAGEIF('Monthly Model'!C4:C63,1,'Monthly Model'!N4:N63) | C16: =AVERAGEIF('Monthly Model'!C4:C63,2,'Monthly Model'!N4:N63) | D16: =AVERAGEIF('Monthly Model'!C4:C63,3,'Monthly Model'!N4:N63) | E16: =AVERAGEIF('Monthly Model'!C4:C63,4,'Monthly Model'!N4:N63) | F16: =AVERAGEIF('Monthly Model'!C4:C63,5,'Monthly Model'!N4:N63) | G16: =F16
A18: PROFIT & LOSS
A19: Total revenue ($) | B19: =SUMPRODUCT(('Monthly Model'!Q4:Q63)*('Monthly Model'!C4:C63=1)) | C19: =SUMPRODUCT(('Monthly Model'!Q4:Q63)*('Monthly Model'!C4:C63=2)) | D19: =SUMPRODUCT(('Monthly Model'!Q4:Q63)*('Monthly Model'!C4:C63=3)) | E19: =SUMPRODUCT(('Monthly Model'!Q4:Q63)*('Monthly Model'!C4:C63=4)) | F19: =SUMPRODUCT(('Monthly Model'!Q4:Q63)*('Monthly Model'!C4:C63=5)) | G19: =SUM(B19:F19)
A20: Interest income ($) | B20: =SUMPRODUCT(('Monthly Model'!O4:O63)*('Monthly Model'!C4:C63=1)) | C20: =SUMPRODUCT(('Monthly Model'!O4:O63)*('Monthly Model'!C4:C63=2)) | D20: =SUMPRODUCT(('Monthly Model'!O4:O63)*('Monthly Model'!C4:C63=3)) | E20: =SUMPRODUCT(('Monthly Model'!O4:O63)*('Monthly Model'!C4:C63=4)) | F20: =SUMPRODUCT(('Monthly Model'!O4:O63)*('Monthly Model'!C4:C63=5)) | G20: =SUM(B20:F20)
A21: Origination fees ($) | B21: =SUMPRODUCT(('Monthly Model'!P4:P63)*('Monthly Model'!C4:C63=1)) | C21: =SUMPRODUCT(('Monthly Model'!P4:P63)*('Monthly Model'!C4:C63=2)) | D21: =SUMPRODUCT(('Monthly Model'!P4:P63)*('Monthly Model'!C4:C63=3)) | E21: =SUMPRODUCT(('Monthly Model'!P4:P63)*('Monthly Model'!C4:C63=4)) | F21: =SUMPRODUCT(('Monthly Model'!P4:P63)*('Monthly Model'!C4:C63=5)) | G21: =SUM(B21:F21)
A22: Operating expenses ($) | B22: =SUMPRODUCT(('Monthly Model'!R4:R63)*('Monthly Model'!C4:C63=1)) | C22: =SUMPRODUCT(('Monthly Model'!R4:R63)*('Monthly Model'!C4:C63=2)) | D22: =SUMPRODUCT(('Monthly Model'!R4:R63)*('Monthly Model'!C4:C63=3)) | E22: =SUMPRODUCT(('Monthly Model'!R4:R63)*('Monthly Model'!C4:C63=4)) | F22: =SUMPRODUCT(('Monthly Model'!R4:R63)*('Monthly Model'!C4:C63=5)) | G22: =SUM(B22:F22)
A23: Provision for losses ($) | B23: =SUMPRODUCT(('Monthly Model'!S4:S63)*('Monthly Model'!C4:C63=1)) | C23: =SUMPRODUCT(('Monthly Model'!S4:S63)*('Monthly Model'!C4:C63=2)) | D23: =SUMPRODUCT(('Monthly Model'!S4:S63)*('Monthly Model'!C4:C63=3)) | E23: =SUMPRODUCT(('Monthly Model'!S4:S63)*('Monthly Model'!C4:C63=4)) | F23: =SUMPRODUCT(('Monthly Model'!S4:S63)*('Monthly Model'!C4:C63=5)) | G23: =SUM(B23:F23)
A24: Cost of funds ($) | B24: =SUMPRODUCT(('Monthly Model'!V4:V63)*('Monthly Model'!C4:C63=1)) | C24: =SUMPRODUCT(('Monthly Model'!V4:V63)*('Monthly Model'!C4:C63=2)) | D24: =SUMPRODUCT(('Monthly Model'!V4:V63)*('Monthly Model'!C4:C63=3)) | E24: =SUMPRODUCT(('Monthly Model'!V4:V63)*('Monthly Model'!C4:C63=4)) | F24: =SUMPRODUCT(('Monthly Model'!V4:V63)*('Monthly Model'!C4:C63=5)) | G24: =SUM(B24:F24)
A25: Net income / (loss) ($) | B25: =SUMPRODUCT(('Monthly Model'!W4:W63)*('Monthly Model'!C4:C63=1)) | C25: =SUMPRODUCT(('Monthly Model'!W4:W63)*('Monthly Model'!C4:C63=2)) | D25: =SUMPRODUCT(('Monthly Model'!W4:W63)*('Monthly Model'!C4:C63=3)) | E25: =SUMPRODUCT(('Monthly Model'!W4:W63)*('Monthly Model'!C4:C63=4)) | F25: =SUMPRODUCT(('Monthly Model'!W4:W63)*('Monthly Model'!C4:C63=5)) | G25: =SUM(B25:F25)
A26: Cumulative net income ($) | B26: ='Monthly Model'!X15 | C26: ='Monthly Model'!X27 | D26: ='Monthly Model'!X39 | E26: ='Monthly Model'!X51 | F26: ='Monthly Model'!X63 | G26: =F26
A28: CAPITAL REQUIREMENTS
A29: Peak equity required ($) | B29: =MAX('Monthly Model'!AB4:AB15) | C29: =MAX('Monthly Model'!AB16:AB27) | D29: =MAX('Monthly Model'!AB28:AB39) | E29: =MAX('Monthly Model'!AB40:AB51) | F29: =MAX('Monthly Model'!AB52:AB63) | G29: =MAX(B29:F29)
A30: Incremental capital raised ($) | B30: =SUMPRODUCT(('Monthly Model'!AC4:AC63)*('Monthly Model'!C4:C63=1)) | C30: =SUMPRODUCT(('Monthly Model'!AC4:AC63)*('Monthly Model'!C4:C63=2)) | D30: =SUMPRODUCT(('Monthly Model'!AC4:AC63)*('Monthly Model'!C4:C63=3)) | E30: =SUMPRODUCT(('Monthly Model'!AC4:AC63)*('Monthly Model'!C4:C63=4)) | F30: =SUMPRODUCT(('Monthly Model'!AC4:AC63)*('Monthly Model'!C4:C63=5)) | G30: =SUM(B30:F30)
A31: Debt balance at year end ($) | B31: ='Monthly Model'!U15 | C31: ='Monthly Model'!U27 | D31: ='Monthly Model'!U39 | E31: ='Monthly Model'!U51 | F31: ='Monthly Model'!U63 | G31: =F31

Sheet Cash & Raises
A1: VetFinance | Monthly Cash & Funding Detail — Warehouse Facility, Cash Sweep & Raises
A5: Mo# | B5: Date | C5: Yr | D5: Active Practices | E5: Originations ($) | F5: End Portfolio ($) | G5: Debt Balance ($) | H5: Facility Limit ($) | I5: Utilization (%) | J5: Debt Draw / (Repay) ($) | K5: Interest Expense ($) | L5: Investable Excess Cash ($) | M5: Investment Income ($) | N5: Raise Triggered ($) | O5: End Cash & Investments ($) | P5: Recommended Action
A6: 1 | B6: ='Monthly Model'!B4 | C6: ='Monthly Model'!C4 | D6: ='Monthly Model'!F4 | E6: ='Monthly Model'!I4 | F6: ='Monthly Model'!M4 | G6: ='Monthly Model'!U4 | H6: ='Monthly Model'!AE4 | I6: ='Monthly Model'!AG4 | J6: ='Monthly Model'!AF4 | K6: ='Monthly Model'!V4 | L6: ='Monthly Model'!AI4 | M6: ='Monthly Model'!AJ4 | N6: ='Monthly Model'!AC4 | O6: ='Monthly Model'!AD4 | P6: ='Monthly Model'!AL4
A7: 2 | B7: ='Monthly Model'!B5 | C7: ='Monthly Model'!C5 | D7: ='Monthly Model'!F5 | E7: ='Monthly Model'!I5 | F7: ='Monthly Model'!M5 | G7: ='Monthly Model'!U5 | H7: ='Monthly Model'!AE5 | I7: ='Monthly Model'!AG5 | J7: ='Monthly Model'!AF5 | K7: ='Monthly Model'!V5 | L7: ='Monthly Model'!AI5 | M7: ='Monthly Model'!AJ5 | N7: ='Monthly Model'!AC5 | O7: ='Monthly Model'!AD5 | P7: ='Monthly Model'!AL5
A8: 3 | B8: ='Monthly Model'!B6 | C8: ='Monthly Model'!C6 | D8: ='Monthly Model'!F6 | E8: ='Monthly Model'!I6 | F8: ='Monthly Model'!M6 | G8: ='Monthly Model'!U6 | H8: ='Monthly Model'!AE6 | I8: ='Monthly Model'!AG6 | J8: ='Monthly Model'!AF6 | K8: ='Monthly Model'!V6 | L8: ='Monthly Model'!AI6 | M8: ='Monthly Model'!AJ6 | N8: ='Monthly Model'!AC6 | O8: ='Monthly Model'!AD6 | P8: ='Monthly Model'!AL6
A9: 4 | B9: ='Monthly Model'!B7 | C9: ='Monthly Model'!C7 | D9: ='Monthly Model'!F7 | E9: ='Monthly Model'!I7 | F9: ='Monthly Model'!M7 | G9: ='Monthly Model'!U7 | H9: ='Monthly Model'!AE7 | I9: ='Monthly Model'!AG7 | J9: ='Monthly Model'!AF7 | K9: ='Monthly Model'!V7 | L9: ='Monthly Model'!AI7 | M9: ='Monthly Model'!AJ7 | N9: ='Monthly Model'!AC7 | O9: ='Monthly Model'!AD7 | P9: ='Monthly Model'!AL7
A10: 5 | B10: ='Monthly Model'!B8 | C10: ='Monthly Model'!C8 | D10: ='Monthly Model'!F8 | E10: ='Monthly Model'!I8 | F10: ='Monthly Model'!M8 | G10: ='Monthly Model'!U8 | H10: ='Monthly Model'!AE8 | I10: ='Monthly Model'!AG8 | J10: ='Monthly Model'!AF8 | K10: ='Monthly Model'!V8 | L10: ='Monthly Model'!AI8 | M10: ='Monthly Model'!AJ8 | N10: ='Monthly Model'!AC8 | O10: ='Monthly Model'!AD8 | P10: ='Monthly Model'!AL8
A11: 6 | B11: ='Monthly Model'!B9 | C11: ='Monthly Model'!C9 | D11: ='Monthly Model'!F9 | E11: ='Monthly Model'!I9 | F11: ='Monthly Model'!M9 | G11: ='Monthly Model'!U9 | H11: ='Monthly Model'!AE9 | I11: ='Monthly Model'!AG9 | J11: ='Monthly Model'!AF9 | K11: ='Monthly Model'!V9 | L11: ='Monthly Model'!AI9 | M11: ='Monthly Model'!AJ9 | N11: ='Monthly Model'!AC9 | O11: ='Monthly Model'!AD9 | P11: ='Monthly Model'!AL9
A12: 7 | B12: ='Monthly Model'!B10 | C12: ='Monthly Model'!C10 | D12: ='Monthly Model'!F10 | E12: ='Monthly Model'!I10 | F12: ='Monthly Model'!M10 | G12: ='Monthly Model'!U10 | H12: ='Monthly Model'!AE10 | I12: ='Monthly Model'!AG10 | J12: ='Monthly Model'!AF10 | K12: ='Monthly Model'!V10 | L12: ='Monthly Model'!AI10 | M12: ='Monthly Model'!AJ10 | N12: ='Monthly Model'!AC10 | O12: ='Monthly Model'!AD10 | P12: ='Monthly Model'!AL10
A13: 8 | B13: ='Monthly Model'!B11 | C13: ='Monthly Model'!C11 | D13: ='Monthly Model'!F11 | E13: ='Monthly Model'!I11 | F13: ='Monthly Model'!M11 | G13: ='Monthly Model'!U11 | H13: ='Monthly Model'!AE11 | I13: ='Monthly Model'!AG11 | J13: ='Monthly Model'!AF11 | K13: ='Monthly Model'!V11 | L13: ='Monthly Model'!AI11 | M13: ='Monthly Model'!AJ11 | N13: ='Monthly Model'!AC11 | O13: ='Monthly Model'!AD11 | P13: ='Monthly Model'!AL11
A14: 9 | B14: ='Monthly Model'!B12 | C14: ='Monthly Model'!C12 | D14: ='Monthly Model'!F12 | E14: ='Monthly Model'!I12 | F14: ='Monthly Model'!M12 | G14: ='Monthly Model'!U12 | H14: ='Monthly Model'!AE12 | I14: ='Monthly Model'!AG12 | J14: ='Monthly Model'!AF12 | K14: ='Monthly Model'!V12 | L14: ='Monthly Model'!AI12 | M14: ='Monthly Model'!AJ12 | N14: ='Monthly Model'!AC12 | O14: ='Monthly Model'!AD12 | P14: ='Monthly Model'!AL12
A15: 10 | B15: ='Monthly Model'!B13 | C15: ='Monthly Model'!C13 | D15: ='Monthly Model'!F13 | E15: ='Monthly Model'!I13 | F15: ='Monthly Model'!M13 | G15: ='Monthly Model'!U13 | H15: ='Monthly Model'!AE13 | I15: ='Monthly Model'!AG13 | J15: ='Monthly Model'!AF13 | K15: ='Monthly Model'!V13 | L15: ='Monthly Model'!AI13 | M15: ='Monthly Model'!AJ13 | N15: ='Monthly Model'!AC13 | O15: ='Monthly Model'!AD13 | P15: ='Monthly Model'!AL13
A16: 11 | B16: ='Monthly Model'!B14 | C16: ='Monthly Model'!C14 | D16: ='Monthly Model'!F14 | E16: ='Monthly Model'!I14 | F16: ='Monthly Model'!M14 | G16: ='Monthly Model'!U14 | H16: ='Monthly Model'!AE14 | I16: ='Monthly Model'!AG14 | J16: ='Monthly Model'!AF14 | K16: ='Monthly Model'!V14 | L16: ='Monthly Model'!AI14 | M16: ='Monthly Model'!AJ14 | N16: ='Monthly Model'!AC14 | O16: ='Monthly Model'!AD14 | P16: ='Monthly Model'!AL14
A17: 12 | B17: ='Monthly Model'!B15 | C17: ='Monthly Model'!C15 | D17: ='Monthly Model'!F15 | E17: ='Monthly Model'!I15 | F17: ='Monthly Model'!M15 | G17: ='Monthly Model'!U15 | H17: ='Monthly Model'!AE15 | I17: ='Monthly Model'!AG15 | J17: ='Monthly Model'!AF15 | K17: ='Monthly Model'!V15 | L17: ='Monthly Model'!AI15 | M17: ='Monthly Model'!AJ15 | N17: ='Monthly Model'!AC15 | O17: ='Monthly Model'!AD15 | P17: ='Monthly Model'!AL15
... A65: 60 | B65: ='Monthly Model'!B63 | C65: ='Monthly Model'!C63 | D65: ='Monthly Model'!F63 | E65: ='Monthly Model'!I63 | F65: ='Monthly Model'!M63 | G65: ='Monthly Model'!U63 | H65: ='Monthly Model'!AE63 | I65: ='Monthly Model'!AG63 | J65: ='Monthly Model'!AF63 | K65: ='Monthly Model'!V63 | L65: ='Monthly Model'!AI63 | M65: ='Monthly Model'!AJ63 | N65: ='Monthly Model'!AC63 | O65: ='Monthly Model'!AD63 | P65: ='Monthly Model'!AL63
A68: SUMMARY — 5-YEAR FUNDING PICTURE
A69: Initial equity raised before launch ($) | G69: =Assumptions!$B$36
A70: Total incremental equity raised, Yr1-5 ($) | G70: =SUM(N6:N65)
A71: Total equity capital required, all-in ($) | G71: =G69+G70
A72: Number of equity raise events (months) | G72: =COUNTIF(N6:N65,">"&0)
A73: Warehouse facility — initial committed limit ($) | G73: =Assumptions!$B$44
A74: Warehouse facility — limit at end of Year 5 ($) | G74: =H65
A75: Number of facility increases over 5 years | G75: =SUMPRODUCT((H7:H65<>H6:H64)*1)
A76: Peak facility utilization (%) | G76: =MAX(I6:I65)
A77: Cash & investments — end Year 1 ($) | G77: =O17
A78: Cash & investments — end Year 2 ($) | G78: =O29
A79: Cash & investments — end Year 5 ($) | G79: =O65
A80: Minimum cash balance maintained ($) | G80: =MIN(O6:O65)
A81: Total interest expense on debt, 5yr ($) | G81: =SUM(K6:K65)
A82: Total investment income on excess cash, 5yr ($) | G82: =SUM(M6:M65)

Sheet Capital Plan
A1: VetFinance | Capital Plan — When to Raise, and How Much
A2: Quarterly view of the funding needs coming out of the Monthly Model: how much equity to raise, when the warehouse facility needs to be upsized (and to what size), and the resulting cash position. Rows highlighted amber require action. Adjust Assumptions to re-run the scenario.
A4: Qtr | B4: Period | C4: Yr | D4: Equity Raise This Qtr ($) | E4: Cumulative Equity Raised ($) | F4: Facility Limit at Qtr End ($) | G4: Facility Increase This Qtr ($) | H4: Facility Utilization at Qtr End (%) | I4: Cash & Investments at Qtr End ($) | J4: Recommended Action
A5: 1 | B5: ='Monthly Model'!B4 | C5: ='Monthly Model'!C6 | D5: =SUM('Monthly Model'!AC4:AC6) | E5: =Assumptions!$B$36+D5 | F5: ='Monthly Model'!AE6 | G5: =SUM('Monthly Model'!AH4:AH6) | H5: ='Monthly Model'!AG6 | I5: ='Monthly Model'!AD6 | J5: =TRIM(IF(G5>0,"Increase facility to $"&TEXT(F5,"#,##0")&". ","")&IF(D5>0,"Raise ~$"&TEXT(D5,"#,##0")&" of equity this quarter.",""))
A6: 2 | B6: ='Monthly Model'!B7 | C6: ='Monthly Model'!C9 | D6: =SUM('Monthly Model'!AC7:AC9) | E6: =E5+D6 | F6: ='Monthly Model'!AE9 | G6: =SUM('Monthly Model'!AH7:AH9) | H6: ='Monthly Model'!AG9 | I6: ='Monthly Model'!AD9 | J6: =TRIM(IF(G6>0,"Increase facility to $"&TEXT(F6,"#,##0")&". ","")&IF(D6>0,"Raise ~$"&TEXT(D6,"#,##0")&" of equity this quarter.",""))
A7: 3 | B7: ='Monthly Model'!B10 | C7: ='Monthly Model'!C12 | D7: =SUM('Monthly Model'!AC10:AC12) | E7: =E6+D7 | F7: ='Monthly Model'!AE12 | G7: =SUM('Monthly Model'!AH10:AH12) | H7: ='Monthly Model'!AG12 | I7: ='Monthly Model'!AD12 | J7: =TRIM(IF(G7>0,"Increase facility to $"&TEXT(F7,"#,##0")&". ","")&IF(D7>0,"Raise ~$"&TEXT(D7,"#,##0")&" of equity this quarter.",""))
A8: 4 | B8: ='Monthly Model'!B13 | C8: ='Monthly Model'!C15 | D8: =SUM('Monthly Model'!AC13:AC15) | E8: =E7+D8 | F8: ='Monthly Model'!AE15 | G8: =SUM('Monthly Model'!AH13:AH15) | H8: ='Monthly Model'!AG15 | I8: ='Monthly Model'!AD15 | J8: =TRIM(IF(G8>0,"Increase facility to $"&TEXT(F8,"#,##0")&". ","")&IF(D8>0,"Raise ~$"&TEXT(D8,"#,##0")&" of equity this quarter.",""))
A9: 5 | B9: ='Monthly Model'!B16 | C9: ='Monthly Model'!C18 | D9: =SUM('Monthly Model'!AC16:AC18) | E9: =E8+D9 | F9: ='Monthly Model'!AE18 | G9: =SUM('Monthly Model'!AH16:AH18) | H9: ='Monthly Model'!AG18 | I9: ='Monthly Model'!AD18 | J9: =TRIM(IF(G9>0,"Increase facility to $"&TEXT(F9,"#,##0")&". ","")&IF(D9>0,"Raise ~$"&TEXT(D9,"#,##0")&" of equity this quarter.",""))
A10: 6 | B10: ='Monthly Model'!B19 | C10: ='Monthly Model'!C21 | D10: =SUM('Monthly Model'!AC19:AC21) | E10: =E9+D10 | F10: ='Monthly Model'!AE21 | G10: =SUM('Monthly Model'!AH19:AH21) | H10: ='Monthly Model'!AG21 | I10: ='Monthly Model'!AD21 | J10: =TRIM(IF(G10>0,"Increase facility to $"&TEXT(F10,"#,##0")&". ","")&IF(D10>0,"Raise ~$"&TEXT(D10,"#,##0")&" of equity this quarter.",""))
A11: 7 | B11: ='Monthly Model'!B22 | C11: ='Monthly Model'!C24 | D11: =SUM('Monthly Model'!AC22:AC24) | E11: =E10+D11 | F11: ='Monthly Model'!AE24 | G11: =SUM('Monthly Model'!AH22:AH24) | H11: ='Monthly Model'!AG24 | I11: ='Monthly Model'!AD24 | J11: =TRIM(IF(G11>0,"Increase facility to $"&TEXT(F11,"#,##0")&". ","")&IF(D11>0,"Raise ~$"&TEXT(D11,"#,##0")&" of equity this quarter.",""))
A12: 8 | B12: ='Monthly Model'!B25 | C12: ='Monthly Model'!C27 | D12: =SUM('Monthly Model'!AC25:AC27) | E12: =E11+D12 | F12: ='Monthly Model'!AE27 | G12: =SUM('Monthly Model'!AH25:AH27) | H12: ='Monthly Model'!AG27 | I12: ='Monthly Model'!AD27 | J12: =TRIM(IF(G12>0,"Increase facility to $"&TEXT(F12,"#,##0")&". ","")&IF(D12>0,"Raise ~$"&TEXT(D12,"#,##0")&" of equity this quarter.",""))
A13: 9 | B13: ='Monthly Model'!B28 | C13: ='Monthly Model'!C30 | D13: =SUM('Monthly Model'!AC28:AC30) | E13: =E12+D13 | F13: ='Monthly Model'!AE30 | G13: =SUM('Monthly Model'!AH28:AH30) | H13: ='Monthly Model'!AG30 | I13: ='Monthly Model'!AD30 | J13: =TRIM(IF(G13>0,"Increase facility to $"&TEXT(F13,"#,##0")&". ","")&IF(D13>0,"Raise ~$"&TEXT(D13,"#,##0")&" of equity this quarter.",""))
A14: 10 | B14: ='Monthly Model'!B31 | C14: ='Monthly Model'!C33 | D14: =SUM('Monthly Model'!AC31:AC33) | E14: =E13+D14 | F14: ='Monthly Model'!AE33 | G14: =SUM('Monthly Model'!AH31:AH33) | H14: ='Monthly Model'!AG33 | I14: ='Monthly Model'!AD33 | J14: =TRIM(IF(G14>0,"Increase facility to $"&TEXT(F14,"#,##0")&". ","")&IF(D14>0,"Raise ~$"&TEXT(D14,"#,##0")&" of equity this quarter.",""))
A15: 11 | B15: ='Monthly Model'!B34 | C15: ='Monthly Model'!C36 | D15: =SUM('Monthly Model'!AC34:AC36) | E15: =E14+D15 | F15: ='Monthly Model'!AE36 | G15: =SUM('Monthly Model'!AH34:AH36) | H15: ='Monthly Model'!AG36 | I15: ='Monthly Model'!AD36 | J15: =TRIM(IF(G15>0,"Increase facility to $"&TEXT(F15,"#,##0")&". ","")&IF(D15>0,"Raise ~$"&TEXT(D15,"#,##0")&" of equity this quarter.",""))
A16: 12 | B16: ='Monthly Model'!B37 | C16: ='Monthly Model'!C39 | D16: =SUM('Monthly Model'!AC37:AC39) | E16: =E15+D16 | F16: ='Monthly Model'!AE39 | G16: =SUM('Monthly Model'!AH37:AH39) | H16: ='Monthly Model'!AG39 | I16: ='Monthly Model'!AD39 | J16: =TRIM(IF(G16>0,"Increase facility to $"&TEXT(F16,"#,##0")&". ","")&IF(D16>0,"Raise ~$"&TEXT(D16,"#,##0")&" of equity this quarter.",""))
A17: 13 | B17: ='Monthly Model'!B40 | C17: ='Monthly Model'!C42 | D17: =SUM('Monthly Model'!AC40:AC42) | E17: =E16+D17 | F17: ='Monthly Model'!AE42 | G17: =SUM('Monthly Model'!AH40:AH42) | H17: ='Monthly Model'!AG42 | I17: ='Monthly Model'!AD42 | J17: =TRIM(IF(G17>0,"Increase facility to $"&TEXT(F17,"#,##0")&". ","")&IF(D17>0,"Raise ~$"&TEXT(D17,"#,##0")&" of equity this quarter.",""))
A18: 14 | B18: ='Monthly Model'!B43 | C18: ='Monthly Model'!C45 | D18: =SUM('Monthly Model'!AC43:AC45) | E18: =E17+D18 | F18: ='Monthly Model'!AE45 | G18: =SUM('Monthly Model'!AH43:AH45) | H18: ='Monthly Model'!AG45 | I18: ='Monthly Model'!AD45 | J18: =TRIM(IF(G18>0,"Increase facility to $"&TEXT(F18,"#,##0")&". ","")&IF(D18>0,"Raise ~$"&TEXT(D18,"#,##0")&" of equity this quarter.",""))
A19: 15 | B19: ='Monthly Model'!B46 | C19: ='Monthly Model'!C48 | D19: =SUM('Monthly Model'!AC46:AC48) | E19: =E18+D19 | F19: ='Monthly Model'!AE48 | G19: =SUM('Monthly Model'!AH46:AH48) | H19: ='Monthly Model'!AG48 | I19: ='Monthly Model'!AD48 | J19: =TRIM(IF(G19>0,"Increase facility to $"&TEXT(F19,"#,##0")&". ","")&IF(D19>0,"Raise ~$"&TEXT(D19,"#,##0")&" of equity this quarter.",""))
A20: 16 | B20: ='Monthly Model'!B49 | C20: ='Monthly Model'!C51 | D20: =SUM('Monthly Model'!AC49:AC51) | E20: =E19+D20 | F20: ='Monthly Model'!AE51 | G20: =SUM('Monthly Model'!AH49:AH51) | H20: ='Monthly Model'!AG51 | I20: ='Monthly Model'!AD51 | J20: =TRIM(IF(G20>0,"Increase facility to $"&TEXT(F20,"#,##0")&". ","")&IF(D20>0,"Raise ~$"&TEXT(D20,"#,##0")&" of equity this quarter.",""))
A21: 17 | B21: ='Monthly Model'!B52 | C21: ='Monthly Model'!C54 | D21: =SUM('Monthly Model'!AC52:AC54) | E21: =E20+D21 | F21: ='Monthly Model'!AE54 | G21: =SUM('Monthly Model'!AH52:AH54) | H21: ='Monthly Model'!AG54 | I21: ='Monthly Model'!AD54 | J21: =TRIM(IF(G21>0,"Increase facility to $"&TEXT(F21,"#,##0")&". ","")&IF(D21>0,"Raise ~$"&TEXT(D21,"#,##0")&" of equity this quarter.",""))
A22: 18 | B22: ='Monthly Model'!B55 | C22: ='Monthly Model'!C57 | D22: =SUM('Monthly Model'!AC55:AC57) | E22: =E21+D22 | F22: ='Monthly Model'!AE57 | G22: =SUM('Monthly Model'!AH55:AH57) | H22: ='Monthly Model'!AG57 | I22: ='Monthly Model'!AD57 | J22: =TRIM(IF(G22>0,"Increase facility to $"&TEXT(F22,"#,##0")&". ","")&IF(D22>0,"Raise ~$"&TEXT(D22,"#,##0")&" of equity this quarter.",""))
A23: 19 | B23: ='Monthly Model'!B58 | C23: ='Monthly Model'!C60 | D23: =SUM('Monthly Model'!AC58:AC60) | E23: =E22+D23 | F23: ='Monthly Model'!AE60 | G23: =SUM('Monthly Model'!AH58:AH60) | H23: ='Monthly Model'!AG60 | I23: ='Monthly Model'!AD60 | J23: =TRIM(IF(G23>0,"Increase facility to $"&TEXT(F23,"#,##0")&". ","")&IF(D23>0,"Raise ~$"&TEXT(D23,"#,##0")&" of equity this quarter.",""))
A24: 20 | B24: ='Monthly Model'!B61 | C24: ='Monthly Model'!C63 | D24: =SUM('Monthly Model'!AC61:AC63) | E24: =E23+D24 | F24: ='Monthly Model'!AE63 | G24: =SUM('Monthly Model'!AH61:AH63) | H24: ='Monthly Model'!AG63 | I24: ='Monthly Model'!AD63 | J24: =TRIM(IF(G24>0,"Increase facility to $"&TEXT(F24,"#,##0")&". ","")&IF(D24>0,"Raise ~$"&TEXT(D24,"#,##0")&" of equity this quarter.",""))
A27: SUMMARY — CAPITAL ACTIONS OVER 5 YEARS
A29: Initial equity raised before launch ($) | G29: =Assumptions!$B$36
A30: Total incremental equity raised, Yr1-5 ($) | G30: =SUM(D5:D24)
A31: Total equity capital required, all-in ($) | G31: =G29+G30
A32: Number of quarters requiring an equity raise | G32: =COUNTIF(D5:D24,">"&0)
A33: Warehouse facility — initial committed limit ($) | G33: =Assumptions!$B$44
A34: Warehouse facility — limit at end of Year 5 ($) | G34: =F24
A35: Number of facility upsize events over 5 years | G35: =COUNTIF(G5:G24,">"&0)
A36: Peak facility utilization (%) | G36: =MAX('Monthly Model'!AG4:AG63)
A37: Cash & investments — end Year 5 ($) | G37: =I24
A38: Minimum cash balance maintained ($) | G38: =MIN('Monthly Model'!AD4:AD63)
A40: HOW TO READ THIS
A41: • Equity is raised at most once per year (start of each fiscal year), sized with a 12-month look-ahead so cash never dips below the minimum buffer before the next raise — no mid-year top-ups.
A42: • Facility increases are separate from equity raises and can happen more often: negotiate the upsize with your warehouse lender 2-3 months before the quarter shown, since credit facility amendments take time to arrange.
A43: • See the Monthly Model and Cash & Raises sheets for the full month-by-month detail behind these quarterly totals.
